Workbook
Name Slicer_Chapter: #N/A
Name Slicer_Chapter1: #N/A
Name Slicer_Chapter11: #N/A
Name Slicer_Chapter12: #N/A
Name Slicer_Chapter2: #N/A
Name Slicer_Chapter3: #N/A

Sheet PVT
B10: InReport | C10: TRUE | H10: InReport | I10: TRUE
U11: Total Portfolio
B12: Closed Positions | C12: Max of ToM | D12: Entry Value | E12: Exit Value | F12: Realized Gains | H12: Open Positions | I12: Holding Period (Mon) | J12: Entry Value USD | K12: Market Value USD | L12: Unrealized Gains | M12: Unrealized Gains % | O12: Row Labels | P12: Value | R12: Free Cash | S12: ='CLOSED POSITION HISTORY'!$J$9 -> 85.05 | U12: Portfolio Summary | V12: USD | W12: % Of Invested
B13: Stock Holding | C13: 10.102225 | D13: 843.87 | E13: 915.69 | F13: 51.7 | H13: Consumer Defensive | I13: 10.880315 | J13: 407.81 | K13: 409.92 | L13: 2.11 | M13: 0.0051739781 | O13: DIVIDENT | P13: 14.79 | R13: INV CAPITAL | S13: =MIN(O34:O246) -> -1560.49 | U13: Invested Capital | V13: =V14-V15 -> 1490.49 | W13: =V13/$V$13 -> 1
B14: Financial Services | C14: 8.9815609 | D14: 127.47 | E14: 148.9 | F14: 21.43 | H14: ETF | I14: 10.164654 | J14: 358.7 | K14: 364.3 | L14: 5.6 | M14: 0.015611932 | O14: commission | P14: 0 | U14: Active Investment Value | V14: =GETPIVOTDATA("Market Value USD",$H$12) -> 1557.83 | W14: =V14/$V$13 -> 1.0451798
B15: Energy & Utilities | C15: 4.1938561 | D15: 145.91 | E15: 161.8 | F15: 15.88 | H15: Energy & Utilities | I15: 9.2089968 | J15: 303.27 | K15: 312.25 | L15: 8.98 | M15: 0.029610578 | O15: Sec Fee | P15: -0.01 | U15: Unrealized Gains | V15: =GETPIVOTDATA("Unrealized Gains",$H$12) -> 67.34 | W15: =V15/$V$13 -> 0.045179773
B16: ETF | C16: 5.0261935 | D16: 92.47 | E16: 99.68 | F16: 7.21 | H16: Technology | I16: 10.10045 | J16: 233.35 | K16: 256.74 | L16: 23.39 | M16: 0.1002357 | O16: Withholding Tax | P16: -3.93 | U16: Realized Gains | V16: =GETPIVOTDATA("Realized Gains",$B$12,"Type","Stock Holding") -> 51.7 | W16: =V16/$V$13 -> 0.03468658
B17: Technology | C17: 10.102225 | D17: 404.77 | E17: 408.2 | F17: 3.43 | H17: Financial Services | I17: 5.5405044 | J17: 187.32 | K17: 214.58 | L17: 27.26 | M17: 0.14552637 | O17: Grand Total | P17: 10.85 | U17: Dividends | V17: =GETPIVOTDATA("Amount",$O$12,"Type","DIVIDENT") -> 14.79 | W17: =V17/$V$13 -> 0.0099229113
B18: Consumer Cyclical | C18: 3.7753006 | D18: 33.95 | E18: 36.71 | F18: 2.76 | H18: ING | I18: 5.5405044 | J18: 65.64 | K18: 83.09 | L18: 17.45 | M18: 0.265844 | U18: Available Cash | V18: =S12 -> 85.05 | W18: =V18/$V$13 -> 0.057061772
B19: Consumer Defensive | C19: 9.2747881 | D19: 39.3 | E19: 60.4 | F19: 0.99 | H19: BCS | I19: 0.91411083 | J19: 40 | K19: 44.28 | L19: 4.28 | M19: 0.107 | O19: Row Labels | P19: Value | U19: Total Cash Returns | V19: =V17+V16 -> 66.49 | W19: =V19/$V$13 -> 0.044609491
B20: Grand Total | C20: 10.102225 | D20: 843.87 | E20: 915.69 | F20: 51.7 | H20: MA | I20: 4.8142117 | J20: 30.46 | K20: 34.59 | L20: 4.13 | M20: 0.13558766 | O20: Grand Total | U20: Tax & Fees | V20: =IFERROR(GETPIVOTDATA("Amount",$O$12,"Type","commission"),0)+IFERROR(GETPIVOTDATA("Amount",$O$12,"Type","Sec Fee"),0)+IFERROR(GETPIVOTDATA("Amount",$O$12,"Type","Withholding Tax"),0) -> -3.94 | W20: =V20/$V$13 -> -0.002643426
H21: BBVA.ES | I21: 0.23164507 | J21: 25 | K21: 25.62 | L21: 0.62 | M21: 0.0248 | U21: Total P&L | V21: =V20+V17+V16+V15 -> 129.89 | W21: =V21/$V$13 -> 0.087145838
H22: CIB | I22: 0.10119022 | J22: 19.99 | K22: 20.05 | L22: 0.06 | M22: 0.0030015008 | U22: FCF | V22: =V19+V20 -> 62.55 | W22: =V22/$V$13 -> 0.041966065
H23: V | I23: 1.3439307 | J23: 6.23 | K23: 6.95 | L23: 0.72 | M23: 0.11556982 | O23: Row Labels | P23: Value
H24: Consumer Cyclical | I24: 4.8142337 | J24: 0.04 | K24: 0.04 | L24: 0 | M24: 0 | O24: Stock sale | P24: 823.62 | U24: Portfolio Metrics
H25: Grand Total | I25: 10.880315 | J25: 1490.49 | K25: 1557.83 | L25: 67.34 | M25: 0.045179773 | O25: Stock purchase | P25: -2314.1 | U25: Holding Period (Months) | V25: =MAX(GETPIVOTDATA("Holding Period (Mon)",$H$12),GETPIVOTDATA("Max of ToM",$B$12,"Type","Stock Holding")) -> 10.880315
O26: Grand Total | P26: -1490.48 | U26: Overall Return % | V26: =W21 -> 0.087145838
U27: Avg Monthly Return % | V27: =V26/V25 -> 0.0080094959
U28: CAGR % | V28: =((V13+V21)/V13)^(12/V25)-1 -> 0.096534142
U29: Overal FCF % | V29: =W22 -> 0.041966065
U30: Avg FCF % | V30: =W22/V25 -> 0.0038570634
M31: Type | N31: (Multiple Items) | Q31: Type | R31: deposit | U31: FCF CAGR % | V31: =((V13+V22)/V13)^(12/V25)-1 -> 0.046383476
M33: Row Labels | N33: Value | O33: ACCUMULATIVE | Q33: Row Labels | R33: Value
M34: 45446.646 | N34: -20.57 | O34: =SUM($N$34:N34) -> -20.57
M35: 45446.894 | N35: -20 | O35: =SUM($N$34:N35) -> -40.57
M36: 45448.646 | N36: -20.25 | O36: =SUM($N$34:N36) -> -60.82
M37: 45449.868 | N37: -10 | O37: =SUM($N$34:N37) -> -70.82
M38: 45453.913 | N38: -10 | O38: =SUM($N$34:N38) -> -80.82
M39: 45460.646 | N39: -0.2 | O39: =SUM($N$34:N39) -> -81.02
M40: 45460.738 | N40: 0.2 | O40: =SUM($N$34:N40) -> -80.82
M41: 45460.885 | N41: -19.99 | O41: =SUM($N$34:N41) -> -100.81
M42: 45464.646 | N42: 40.25 | O42: =SUM($N$34:N42) -> -60.56
M43: 45464.661 | N43: -20 | O43: =SUM($N$34:N43) -> -80.56
M44: 45464.674 | N44: -20.36 | O44: =SUM($N$34:N44) -> -100.92
M45: 45476.646 | N45: -25.28 | O45: =SUM($N$34:N45) -> -126.2
... M211: 45792.761 | N211: -10 | O211: =SUM($N$34:N211) -> -1490.48
O212: =SUM($N$34:N212) -> -1490.48
O213: =SUM($N$34:N213) -> -1490.48
O214: =SUM($N$34:N214) -> -1490.48
O215: =SUM($N$34:N215) -> -1490.48
O216: =SUM($N$34:N216) -> -1490.48
O217: =SUM($N$34:N217) -> -1490.48
O218: =SUM($N$34:N218) -> -1490.48
O219: =SUM($N$34:N219) -> -1490.48
O220: =SUM($N$34:N220) -> -1490.48
O221: =SUM($N$34:N221) -> -1490.48
O222: =SUM($N$34:N222) -> -1490.48
O223: =SUM($N$34:N223) -> -1490.48
... O246: =SUM($N$34:N246) -> -1490.48

Sheet Summary
B5: Sum of Amount | C5: Column Labels | G5: Sum of Amount | H5: Column Labels
B6: Row Labels | C6: Net Income | D6: deposit | E6: Exposed Capital | G6: Row Labels | H6: Net Income | I6: Exposed Capital | J6: DATES | L6: DATES | M6: DEPOSIT BALANCE | N6: EXPOSE BALANCE | O6: Net Income | P6: Net Income % | Q6: Proyected Annualized Return % | R6: EXPOSITION %
B7: 2024-05-31 | D7: 100 | G7: 2024-06-03 | I7: -40.57 | J7: =VALUE(G7) -> 45446 | L7: =VALUE(B7) -> 45443 | M7: =SUM($D7:D$7) -> 100 | N7: =-SUMIFS(I:I,J:J,"<="&L7) -> 0 | O7: =SUMIFS(H:H,J:J,"<="&L7) -> 0 | P7: =IFERROR(O7/N7,0) -> 0 | Q7: =IFERROR((P7+1)^(12/((MAX($J$7:J7)-$J$7)/30.5))-1,0) -> 0 | R7: =N7/M7 -> 0
B8: 2024-06-03 | E8: -69.09 | G8: 2024-06-05 | I8: -20.25 | J8: =VALUE(G8) -> 45448 | L8: =VALUE(B8) -> 45446 | M8: =SUM($D$7:D8) -> 100 | N8: =-SUMIFS(I:I,J:J,"<="&L8) -> 40.57 | O8: =SUMIFS(H:H,J:J,"<="&L8) -> 0 | P8: =IFERROR(O8/N8,0) -> 0 | Q8: =IFERROR((P8+1)^(12/((MAX($J$7:J8)-$J$7)/30.5))-1,0) -> 0 | R8: =N8/M8 -> 0.4057 | AL8: =PVT!U11 -> Total Portfolio | AM8: =PVT!V11 -> 0 | AN8: =PVT!W11 -> 0
B9: 2024-06-05 | E9: -20.25 | G9: 2024-06-06 | I9: -10 | J9: =VALUE(G9) -> 45449 | L9: =VALUE(B9) -> 45448 | M9: =SUM($D$7:D9) -> 100 | N9: =-SUMIFS(I:I,J:J,"<="&L9) -> 60.82 | O9: =SUMIFS(H:H,J:J,"<="&L9) -> 0 | P9: =IFERROR(O9/N9,0) -> 0 | Q9: =IFERROR((P9+1)^(12/((MAX($J$7:J9)-$J$7)/30.5))-1,0) -> 0 | R9: =N9/M9 -> 0.6082 | AL9: Resumen de Portafolio | AM9: =PVT!V12 -> USD | AN9: =PVT!W12 -> % Of Invested
B10: 2024-06-06 | E10: -10 | G10: 2024-06-10 | I10: -10 | J10: =VALUE(G10) -> 45453 | L10: =VALUE(B10) -> 45449 | M10: =SUM($D$7:D10) -> 100 | N10: =-SUMIFS(I:I,J:J,"<="&L10) -> 70.82 | O10: =SUMIFS(H:H,J:J,"<="&L10) -> 0 | P10: =IFERROR(O10/N10,0) -> 0 | Q10: =IFERROR((P10+1)^(12/((MAX($J$7:J10)-$J$7)/30.5))-1,0) -> 0 | R10: =N10/M10 -> 0.7082 | AL10: Capital invertido | AM10: =PVT!V13 -> 1490.49 | AN10: =PVT!W13 -> 1
B11: 2024-06-10 | C11: -2.28 | E11: 5.15 | G11: 2024-06-17 | H11: 0 | I11: -19.99 | J11: =VALUE(G11) -> 45460 | L11: =VALUE(B11) -> 45453 | M11: =SUM($D$7:D11) -> 100 | N11: =-SUMIFS(I:I,J:J,"<="&L11) -> 80.82 | O11: =SUMIFS(H:H,J:J,"<="&L11) -> 0 | P11: =IFERROR(O11/N11,0) -> 0 | Q11: =IFERROR((P11+1)^(12/((MAX($J$7:J11)-$J$7)/30.5))-1,0) -> 0 | R11: =N11/M11 -> 0.8082 | AL11: Valor de Mercado | AM11: =PVT!V14 -> 1557.83 | AN11: =PVT!W14 -> 1.0451798
B12: 2024-06-15 | D12: 50 | G12: 2024-06-18 | H12: 0 | J12: =VALUE(G12) -> 45461 | L12: =VALUE(B12) -> 45458 | M12: =SUM($D$7:D12) -> 150 | N12: =-SUMIFS(I:I,J:J,"<="&L12) -> 80.82 | O12: =SUMIFS(H:H,J:J,"<="&L12) -> 0 | P12: =IFERROR(O12/N12,0) -> 0 | Q12: =IFERROR((P12+1)^(12/((MAX($J$7:J12)-$J$7)/30.5))-1,0) -> 0 | R12: =N12/M12 -> 0.5388 | AL12: Ganancias no realizadas | AM12: =PVT!V15 -> 67.34 | AN12: =PVT!W15 -> 0.045179773
B13: 2024-06-17 | C13: -0.75 | E13: -50.18 | G13: 2024-06-21 | H13: 2.02 | I13: -0.11 | J13: =VALUE(G13) -> 45464 | L13: =VALUE(B13) -> 45460 | M13: =SUM($D$7:D13) -> 150 | N13: =-SUMIFS(I:I,J:J,"<="&L13) -> 100.81 | O13: =SUMIFS(H:H,J:J,"<="&L13) -> 0 | P13: =IFERROR(O13/N13,0) -> 0 | Q13: =IFERROR((P13+1)^(12/((MAX($J$7:J13)-$J$7)/30.5))-1,0) -> 0 | R13: =N13/M13 -> 0.67206667 | AL13: Ganancias realizadas | AM13: =PVT!V16 -> 51.7 | AN13: =PVT!W16 -> 0.03468658
B14: 2024-06-18 | C14: -0.01 | G14: 2024-06-24 | H14: 0 | J14: =VALUE(G14) -> 45467 | L14: =VALUE(B14) -> 45461 | M14: =SUM($D$7:D14) -> 150 | N14: =-SUMIFS(I:I,J:J,"<="&L14) -> 100.81 | O14: =SUMIFS(H:H,J:J,"<="&L14) -> 0 | P14: =IFERROR(O14/N14,0) -> 0 | Q14: =IFERROR((P14+1)^(12/((MAX($J$7:J14)-$J$7)/30.5))-1,0) -> 0 | R14: =N14/M14 -> 0.67206667 | AL14: Dividendos | AM14: =PVT!V17 -> 14.79 | AN14: =PVT!W17 -> 0.0099229113
B15: 2024-06-21 | C15: 0.56 | E15: 0.33 | G15: 2024-06-28 | H15: 0 | J15: =VALUE(G15) -> 45471 | L15: =VALUE(B15) -> 45464 | M15: =SUM($D$7:D15) -> 150 | N15: =-SUMIFS(I:I,J:J,"<="&L15) -> 100.92 | O15: =SUMIFS(H:H,J:J,"<="&L15) -> 2.02 | P15: =IFERROR(O15/N15,0) -> 0.020015854 | Q15: =IFERROR((P15+1)^(12/((MAX($J$7:J15)-$J$7)/30.5))-1,0) -> 0.33661195 | R15: =N15/M15 -> 0.6728 | AL15: Efectivo disponible | AM15: =PVT!V18 -> 85.05 | AN15: =PVT!W18 -> 0.057061772
B16: 2024-06-24 | C16: 0 | G16: 2024-07-03 | I16: -36.03 | J16: =VALUE(G16) -> 45476 | L16: =VALUE(B16) -> 45467 | M16: =SUM($D$7:D16) -> 150 | N16: =-SUMIFS(I:I,J:J,"<="&L16) -> 100.92 | O16: =SUMIFS(H:H,J:J,"<="&L16) -> 2.02 | P16: =IFERROR(O16/N16,0) -> 0.020015854 | Q16: =IFERROR((P16+1)^(12/((MAX($J$7:J16)-$J$7)/30.5))-1,0) -> 0.27351613 | R16: =N16/M16 -> 0.6728 | AL16: Retornos totales | AM16: =PVT!V19 -> 66.49 | AN16: =PVT!W19 -> 0.044609491
B17: 2024-06-28 | C17: 0 | G17: 2024-07-05 | H17: 3.7 | I17: -19.95 | J17: =VALUE(G17) -> 45478 | L17: =VALUE(B17) -> 45471 | M17: =SUM($D$7:D17) -> 150 | N17: =-SUMIFS(I:I,J:J,"<="&L17) -> 100.92 | O17: =SUMIFS(H:H,J:J,"<="&L17) -> 2.02 | P17: =IFERROR(O17/N17,0) -> 0.020015854 | Q17: =IFERROR((P17+1)^(12/((MAX($J$7:J17)-$J$7)/30.5))-1,0) -> 0.25441625 | R17: =N17/M17 -> 0.6728 | AL17: Impustos y Gastos | AM17: =PVT!V20 -> -3.94 | AN17: =PVT!W20 -> -0.002643426
B18: 2024-07-02 | D18: 50 | G18: 2024-07-08 | H18: 0.65 | I18: 39.55 | J18: =VALUE(G18) -> 45481 | L18: =VALUE(B18) -> 45475 | M18: =SUM($D$7:D18) -> 200 | N18: =-SUMIFS(I:I,J:J,"<="&L18) -> 100.92 | O18: =SUMIFS(H:H,J:J,"<="&L18) -> 2.02 | P18: =IFERROR(O18/N18,0) -> 0.020015854 | Q18: =IFERROR((P18+1)^(12/((MAX($J$7:J18)-$J$7)/30.5))-1,0) -> 0.23027957 | R18: =N18/M18 -> 0.5046 | AL18: Ganancias y Perdidas | AM18: =PVT!V21 -> 129.89 | AN18: =PVT!W21 -> 0.087145838
B19: 2024-07-03 | E19: -36.03 | G19: 2024-07-09 | H19: -0.31 | I19: -24.98 | J19: =VALUE(G19) -> 45482 | L19: =VALUE(B19) -> 45476 | M19: =SUM($D$7:D19) -> 200 | N19: =-SUMIFS(I:I,J:J,"<="&L19) -> 136.95 | O19: =SUMIFS(H:H,J:J,"<="&L19) -> 2.02 | P19: =IFERROR(O19/N19,0) -> 0.014749909 | Q19: =IFERROR((P19+1)^(12/((MAX($J$7:J19)-$J$7)/30.5))-1,0) -> 0.1605131 | R19: =N19/M19 -> 0.68475 | AL19: Flujo de Caja Libre | AM19: =PVT!V22 -> 62.55 | AN19: =PVT!W22 -> 0.041966065
B20: 2024-07-05 | C20: 3.7 | E20: -19.95 | G20: 2024-07-10 | H20: 0 | I20: -24.49 | J20: =VALUE(G20) -> 45483 | L20: =VALUE(B20) -> 45478 | M20: =SUM($D$7:D20) -> 200 | N20: =-SUMIFS(I:I,J:J,"<="&L20) -> 156.9 | O20: =SUMIFS(H:H,J:J,"<="&L20) -> 5.72 | P20: =IFERROR(O20/N20,0) -> 0.036456342 | Q20: =IFERROR((P20+1)^(12/((MAX($J$7:J20)-$J$7)/30.5))-1,0) -> 0.42504619 | R20: =N20/M20 -> 0.7845
B21: 2024-07-08 | C21: 0.65 | E21: 19.28 | G21: 2024-07-11 | H21: 0.78 | I21: -27.89 | J21: =VALUE(G21) -> 45484 | L21: =VALUE(B21) -> 45481 | M21: =SUM($D$7:D21) -> 200 | N21: =-SUMIFS(I:I,J:J,"<="&L21) -> 117.35 | O21: =SUMIFS(H:H,J:J,"<="&L21) -> 6.37 | P21: =IFERROR(O21/N21,0) -> 0.054282062 | Q21: =IFERROR((P21+1)^(12/((MAX($J$7:J21)-$J$7)/30.5))-1,0) -> 0.66383555 | R21: =N21/M21 -> 0.58675 | AL21: =PVT!U24 -> Portfolio Metrics
B22: 2024-07-09 | C22: -4.58 | E22: -2.09 | G22: 2024-07-12 | H22: 0 | J22: =VALUE(G22) -> 45485 | L22: =VALUE(B22) -> 45482 | M22: =SUM($D$7:D22) -> 200 | N22: =-SUMIFS(I:I,J:J,"<="&L22) -> 142.33 | O22: =SUMIFS(H:H,J:J,"<="&L22) -> 6.06 | P22: =IFERROR(O22/N22,0) -> 0.04257711 | Q22: =IFERROR((P22+1)^(12/((MAX($J$7:J22)-$J$7)/30.5))-1,0) -> 0.47889846 | R22: =N22/M22 -> 0.71165 | AL22: Periodo de Inversion (Mes) | AM22: =PVT!V25 -> 10.880315
B23: 2024-07-10 | C23: -0.21 | E23: -4.26 | G23: 2024-08-07 | I23: -44.97 | J23: =VALUE(G23) -> 45511 | L23: =VALUE(B23) -> 45483 | M23: =SUM($D$7:D23) -> 200 | N23: =-SUMIFS(I:I,J:J,"<="&L23) -> 166.82 | O23: =SUMIFS(H:H,J:J,"<="&L23) -> 6.06 | P23: =IFERROR(O23/N23,0) -> 0.03632658 | Q23: =IFERROR((P23+1)^(12/((MAX($J$7:J23)-$J$7)/30.5))-1,0) -> 0.22252567 | R23: =N23/M23 -> 0.8341 | AL23: Retorno total % | AM23: =PVT!V26 -> 0.087145838
B24: 2024-07-11 | C24: 1.02 | E24: -7.62 | G24: 2024-08-14 | I24: -35 | J24: =VALUE(G24) -> 45518 | L24: =VALUE(B24) -> 45484 | M24: =SUM($D$7:D24) -> 200 | N24: =-SUMIFS(I:I,J:J,"<="&L24) -> 194.71 | O24: =SUMIFS(H:H,J:J,"<="&L24) -> 6.84 | P24: =IFERROR(O24/N24,0) -> 0.035129166 | Q24: =IFERROR((P24+1)^(12/((MAX($J$7:J24)-$J$7)/30.5))-1,0) -> 0.19185185 | R24: =N24/M24 -> 0.97355 | AL24: Retorno mensual % | AM24: =PVT!V27 -> 0.0080094959
B25: 2024-07-12 | C25: 0 | G25: 2024-08-15 | H25: 0.01 | J25: =VALUE(G25) -> 45519 | L25: =VALUE(B25) -> 45485 | M25: =SUM($D$7:D25) -> 200 | N25: =-SUMIFS(I:I,J:J,"<="&L25) -> 194.71 | O25: =SUMIFS(H:H,J:J,"<="&L25) -> 6.84 | P25: =IFERROR(O25/N25,0) -> 0.035129166 | Q25: =IFERROR((P25+1)^(12/((MAX($J$7:J25)-$J$7)/30.5))-1,0) -> 0.18898981 | R25: =N25/M25 -> 0.97355 | AL25: Retotrno Anualizado % | AM25: =PVT!V28 -> 0.096534142
B26: 2024-07-22 | D26: 50 | G26: 2024-08-19 | I26: -19.97 | J26: =VALUE(G26) -> 45523 | L26: =VALUE(B26) -> 45495 | M26: =SUM($D$7:D26) -> 250 | N26: =-SUMIFS(I:I,J:J,"<="&L26) -> 194.71 | O26: =SUMIFS(H:H,J:J,"<="&L26) -> 6.84 | P26: =IFERROR(O26/N26,0) -> 0.035129166 | Q26: =IFERROR((P26+1)^(12/((MAX($J$7:J26)-$J$7)/30.5))-1,0) -> 0.17834585 | R26: =N26/M26 -> 0.77884 | AL26: Flujo de efectico total % | AM26: =PVT!V29 -> 0.041966065
B27: 2024-07-23 | C27: -0.01 | E27: -44.89 | G27: 2024-09-03 | H27: 0.02 | J27: =VALUE(G27) -> 45538 | L27: =VALUE(B27) -> 45496 | M27: =SUM($D$7:D27) -> 250 | N27: =-SUMIFS(I:I,J:J,"<="&L27) -> 194.71 | O27: =SUMIFS(H:H,J:J,"<="&L27) -> 6.84 | P27: =IFERROR(O27/N27,0) -> 0.035129166 | Q27: =IFERROR((P27+1)^(12/((MAX($J$7:J27)-$J$7)/30.5))-1,0) -> 0.14723454 | R27: =N27/M27 -> 0.77884 | AL27: Flujo de caja mensual % | AM27: =PVT!V30 -> 0.0038570634
B28: 2024-07-24 | C28: -0.02 | E28: 12.65 | G28: 2024-09-09 | I28: -31.18 | J28: =VALUE(G28) -> 45544 | L28: =VALUE(B28) -> 45497 | M28: =SUM($D$7:D28) -> 250 | N28: =-SUMIFS(I:I,J:J,"<="&L28) -> 194.71 | O28: =SUMIFS(H:H,J:J,"<="&L28) -> 6.84 | P28: =IFERROR(O28/N28,0) -> 0.035129166 | Q28: =IFERROR((P28+1)^(12/((MAX($J$7:J28)-$J$7)/30.5))-1,0) -> 0.13762739 | R28: =N28/M28 -> 0.77884 | AL28: Flujo de caja annual % | AM28: =PVT!V31 -> 0.046383476
B29: 2024-07-31 | C29: 0.01 | E29: -12.57 | G29: 2024-09-12 | H29: 0.03 | J29: =VALUE(G29) -> 45547 | L29: =VALUE(B29) -> 45504 | M29: =SUM($D$7:D29) -> 250 | N29: =-SUMIFS(I:I,J:J,"<="&L29) -> 194.71 | O29: =SUMIFS(H:H,J:J,"<="&L29) -> 6.84 | P29: =IFERROR(O29/N29,0) -> 0.035129166 | Q29: =IFERROR((P29+1)^(12/((MAX($J$7:J29)-$J$7)/30.5))-1,0) -> 0.13327855 | R29: =N29/M29 -> 0.77884
B30: 2024-08-06 | D30: 50 | G30: 2024-09-13 | I30: -14.83 | J30: =VALUE(G30) -> 45548 | L30: =VALUE(B30) -> 45510 | M30: =SUM($D$7:D30) -> 300 | N30: =-SUMIFS(I:I,J:J,"<="&L30) -> 194.71 | O30: =SUMIFS(H:H,J:J,"<="&L30) -> 6.84 | P30: =IFERROR(O30/N30,0) -> 0.035129166 | Q30: =IFERROR((P30+1)^(12/((MAX($J$7:J30)-$J$7)/30.5))-1,0) -> 0.13188931 | R30: =N30/M30 -> 0.64903333
B31: 2024-08-07 | C31: -0.19 | E31: -44.97 | G31: 2024-09-16 | H31: 1.78 | I31: 15 | J31: =VALUE(G31) -> 45551 | L31: =VALUE(B31) -> 45511 | M31: =SUM($D$7:D31) -> 300 | N31: =-SUMIFS(I:I,J:J,"<="&L31) -> 239.68 | O31: =SUMIFS(H:H,J:J,"<="&L31) -> 6.84 | P31: =IFERROR(O31/N31,0) -> 0.028538051 | Q31: =IFERROR((P31+1)^(12/((MAX($J$7:J31)-$J$7)/30.5))-1,0) -> 0.1030538 | R31: =N31/M31 -> 0.79893333
B32: 2024-08-08 | C32: 0 | G32: 2024-09-17 | H32: 0 | J32: =VALUE(G32) -> 45552 | L32: =VALUE(B32) -> 45512 | M32: =SUM($D$7:D32) -> 300 | N32: =-SUMIFS(I:I,J:J,"<="&L32) -> 239.68 | O32: =SUMIFS(H:H,J:J,"<="&L32) -> 6.84 | P32: =IFERROR(O32/N32,0) -> 0.028538051 | Q32: =IFERROR((P32+1)^(12/((MAX($J$7:J32)-$J$7)/30.5))-1,0) -> 0.10203361 | R32: =N32/M32 -> 0.79893333
B33: 2024-08-14 | D33: 50 | E33: -35 | G33: 2024-09-18 | I33: -20 | J33: =VALUE(G33) -> 45553 | L33: =VALUE(B33) -> 45518 | M33: =SUM($D$7:D33) -> 350 | N33: =-SUMIFS(I:I,J:J,"<="&L33) -> 274.68 | O33: =SUMIFS(H:H,J:J,"<="&L33) -> 6.84 | P33: =IFERROR(O33/N33,0) -> 0.024901704 | Q33: =IFERROR((P33+1)^(12/((MAX($J$7:J33)-$J$7)/30.5))-1,0) -> 0.087775231 | R33: =N33/M33 -> 0.7848
B34: 2024-08-15 | C34: 0.01 | G34: 2024-09-24 | H34: -3.95 | I34: 0.29 | J34: =VALUE(G34) -> 45559 | L34: =VALUE(B34) -> 45519 | M34: =SUM($D$7:D34) -> 350 | N34: =-SUMIFS(I:I,J:J,"<="&L34) -> 274.68 | O34: =SUMIFS(H:H,J:J,"<="&L34) -> 6.85 | P34: =IFERROR(O34/N34,0) -> 0.02493811 | Q34: =IFERROR((P34+1)^(12/((MAX($J$7:J34)-$J$7)/30.5))-1,0) -> 0.083051226 | R34: =N34/M34 -> 0.7848
B35: 2024-08-19 | E35: -19.97 | G35: 2024-09-25 | H35: -3.78 | I35: 5 | J35: =VALUE(G35) -> 45560 | L35: =VALUE(B35) -> 45523 | M35: =SUM($D$7:D35) -> 350 | N35: =-SUMIFS(I:I,J:J,"<="&L35) -> 294.65 | O35: =SUMIFS(H:H,J:J,"<="&L35) -> 6.85 | P35: =IFERROR(O35/N35,0) -> 0.023247921 | Q35: =IFERROR((P35+1)^(12/((MAX($J$7:J35)-$J$7)/30.5))-1,0) -> 0.076573906 | R35: =N35/M35 -> 0.84185714
B36: 2024-09-03 | C36: 0.02 | G36: 2024-09-26 | H36: 0.08 | J36: =VALUE(G36) -> 45561 | L36: =VALUE(B36) -> 45538 | M36: =SUM($D$7:D36) -> 350 | N36: =-SUMIFS(I:I,J:J,"<="&L36) -> 294.65 | O36: =SUMIFS(H:H,J:J,"<="&L36) -> 6.87 | P36: =IFERROR(O36/N36,0) -> 0.023315798 | Q36: =IFERROR((P36+1)^(12/((MAX($J$7:J36)-$J$7)/30.5))-1,0) -> 0.076110556 | R36: =N36/M36 -> 0.84185714
B37: 2024-09-04 | D37: 50 | G37: 2024-09-30 | H37: 0.11 | J37: =VALUE(G37) -> 45565 | L37: =VALUE(B37) -> 45539 | M37: =SUM($D$7:D37) -> 400 | N37: =-SUMIFS(I:I,J:J,"<="&L37) -> 294.65 | O37: =SUMIFS(H:H,J:J,"<="&L37) -> 6.87 | P37: =IFERROR(O37/N37,0) -> 0.023315798 | Q37: =IFERROR((P37+1)^(12/((MAX($J$7:J37)-$J$7)/30.5))-1,0) -> 0.073460508 | R37: =N37/M37 -> 0.736625
B38: 2024-09-09 | E38: -31.18 | G38: 2024-10-03 | I38: -29.97 | J38: =VALUE(G38) -> 45568 | L38: =VALUE(B38) -> 45544 | M38: =SUM($D$7:D38) -> 400 | N38: =-SUMIFS(I:I,J:J,"<="&L38) -> 325.83 | O38: =SUMIFS(H:H,J:J,"<="&L38) -> 6.87 | P38: =IFERROR(O38/N38,0) -> 0.021084615 | Q38: =IFERROR((P38+1)^(12/((MAX($J$7:J38)-$J$7)/30.5))-1,0) -> 0.0645969 | R38: =N38/M38 -> 0.814575
B39: 2024-09-12 | C39: 0.03 | G39: 2024-10-09 | H39: 0.06 | J39: =VALUE(G39) -> 45574 | L39: =VALUE(B39) -> 45547 | M39: =SUM($D$7:D39) -> 400 | N39: =-SUMIFS(I:I,J:J,"<="&L39) -> 325.83 | O39: =SUMIFS(H:H,J:J,"<="&L39) -> 6.9 | P39: =IFERROR(O39/N39,0) -> 0.021176687 | Q39: =IFERROR((P39+1)^(12/((MAX($J$7:J39)-$J$7)/30.5))-1,0) -> 0.061751448 | R39: =N39/M39 -> 0.814575
B40: 2024-09-13 | E40: -14.83 | G40: 2024-10-10 | H40: 0.49 | J40: =VALUE(G40) -> 45575 | L40: =VALUE(B40) -> 45548 | M40: =SUM($D$7:D40) -> 400 | N40: =-SUMIFS(I:I,J:J,"<="&L40) -> 340.66 | O40: =SUMIFS(H:H,J:J,"<="&L40) -> 6.9 | P40: =IFERROR(O40/N40,0) -> 0.0202548 | Q40: =IFERROR((P40+1)^(12/((MAX($J$7:J40)-$J$7)/30.5))-1,0) -> 0.058542386 | R40: =N40/M40 -> 0.85165
B41: 2024-09-16 | C41: 1.78 | E41: 15 | G41: 2024-10-15 | I41: -39.99 | J41: =VALUE(G41) -> 45580 | L41: =VALUE(B41) -> 45551 | M41: =SUM($D$7:D41) -> 400 | N41: =-SUMIFS(I:I,J:J,"<="&L41) -> 325.66 | O41: =SUMIFS(H:H,J:J,"<="&L41) -> 8.68 | P41: =IFERROR(O41/N41,0) -> 0.026653565 | Q41: =IFERROR((P41+1)^(12/((MAX($J$7:J41)-$J$7)/30.5))-1,0) -> 0.074490663 | R41: =N41/M41 -> 0.81415
B42: 2024-09-17 | C42: 0 | G42: 2024-10-17 | I42: -12.98 | J42: =VALUE(G42) -> 45582 | L42: =VALUE(B42) -> 45552 | M42: =SUM($D$7:D42) -> 400 | N42: =-SUMIFS(I:I,J:J,"<="&L42) -> 325.66 | O42: =SUMIFS(H:H,J:J,"<="&L42) -> 8.68 | P42: =IFERROR(O42/N42,0) -> 0.026653565 | Q42: =IFERROR((P42+1)^(12/((MAX($J$7:J42)-$J$7)/30.5))-1,0) -> 0.073355988 | R42: =N42/M42 -> 0.81415
B43: 2024-09-18 | E43: -20 | G43: 2024-10-18 | I43: -20.48 | J43: =VALUE(G43) -> 45583 | L43: =VALUE(B43) -> 45553 | M43: =SUM($D$7:D43) -> 400 | N43: =-SUMIFS(I:I,J:J,"<="&L43) -> 345.66 | O43: =SUMIFS(H:H,J:J,"<="&L43) -> 8.68 | P43: =IFERROR(O43/N43,0) -> 0.025111381 | Q43: =IFERROR((P43+1)^(12/((MAX($J$7:J43)-$J$7)/30.5))-1,0) -> 0.068501725 | R43: =N43/M43 -> 0.86415
B44: 2024-09-24 | C44: -3.95 | D44: 50 | E44: 0.29 | G44: 2024-10-28 | I44: -14.98 | J44: =VALUE(G44) -> 45593 | L44: =VALUE(B44) -> 45559 | M44: =SUM($D$7:D44) -> 450 | N44: =-SUMIFS(I:I,J:J,"<="&L44) -> 345.37 | O44: =SUMIFS(H:H,J:J,"<="&L44) -> 4.73 | P44: =IFERROR(O44/N44,0) -> 0.013695457 | Q44: =IFERROR((P44+1)^(12/((MAX($J$7:J44)-$J$7)/30.5))-1,0) -> 0.034447537 | R44: =N44/M44 -> 0.76748889
B45: 2024-09-25 | C45: -3.64 | E45: 5 | G45: 2024-11-01 | I45: -41.89 | J45: =VALUE(G45) -> 45597 | L45: =VALUE(B45) -> 45560 | M45: =SUM($D$7:D45) -> 450 | N45: =-SUMIFS(I:I,J:J,"<="&L45) -> 340.37 | O45: =SUMIFS(H:H,J:J,"<="&L45) -> 0.95 | P45: =IFERROR(O45/N45,0) -> 0.0027910803 | Q45: =IFERROR((P45+1)^(12/((MAX($J$7:J45)-$J$7)/30.5))-1,0) -> 0.0067785828 | R45: =N45/M45 -> 0.75637778
B46: 2024-09-26 | C46: 0.08 | G46: 2024-11-07 | H46: 2.6 | I46: 19.98 | J46: =VALUE(G46) -> 45603 | L46: =VALUE(B46) -> 45561 | M46: =SUM($D$7:D46) -> 450 | N46: =-SUMIFS(I:I,J:J,"<="&L46) -> 340.37 | O46: =SUMIFS(H:H,J:J,"<="&L46) -> 1.03 | P46: =IFERROR(O46/N46,0) -> 0.0030261186 | Q46: =IFERROR((P46+1)^(12/((MAX($J$7:J46)-$J$7)/30.5))-1,0) -> 0.0070687326 | R46: =N46/M46 -> 0.75637778
B47: 2024-09-27 | E47: -14.97 | G47: 2024-11-08 | H47: 0.01 | J47: =VALUE(G47) -> 45604 | L47: =VALUE(B47) -> 45562 | M47: =SUM($D$7:D47) -> 450 | N47: =-SUMIFS(I:I,J:J,"<="&L47) -> 340.37 | O47: =SUMIFS(H:H,J:J,"<="&L47) -> 1.03 | P47: =IFERROR(O47/N47,0) -> 0.0030261186 | Q47: =IFERROR((P47+1)^(12/((MAX($J$7:J47)-$J$7)/30.5))-1,0) -> 0.007023837 | R47: =N47/M47 -> 0.75637778
B48: 2024-09-30 | C48: 0.11 | G48: 2024-11-12 | I48: -12.98 | J48: =VALUE(G48) -> 45608 | L48: =VALUE(B48) -> 45565 | M48: =SUM($D$7:D48) -> 450 | N48: =-SUMIFS(I:I,J:J,"<="&L48) -> 340.37 | O48: =SUMIFS(H:H,J:J,"<="&L48) -> 1.14 | P48: =IFERROR(O48/N48,0) -> 0.0033492964 | Q48: =IFERROR((P48+1)^(12/((MAX($J$7:J48)-$J$7)/30.5))-1,0) -> 0.0075828907 | R48: =N48/M48 -> 0.75637778
B49: 2024-10-03 | E49: -29.97 | G49: 2024-11-13 | I49: -10.95 | J49: =VALUE(G49) -> 45609 | L49: =VALUE(B49) -> 45568 | M49: =SUM($D$7:D49) -> 450 | N49: =-SUMIFS(I:I,J:J,"<="&L49) -> 370.34 | O49: =SUMIFS(H:H,J:J,"<="&L49) -> 1.14 | P49: =IFERROR(O49/N49,0) -> 0.0030782524 | Q49: =IFERROR((P49+1)^(12/((MAX($J$7:J49)-$J$7)/30.5))-1,0) -> 0.0069251565 | R49: =N49/M49 -> 0.82297778
B50: 2024-10-09 | C50: 0.06 | D50: 50 | G50: 2024-11-14 | H50: 0.03 | J50: =VALUE(G50) -> 45610 | L50: =VALUE(B50) -> 45574 | M50: =SUM($D$7:D50) -> 500 | N50: =-SUMIFS(I:I,J:J,"<="&L50) -> 370.34 | O50: =SUMIFS(H:H,J:J,"<="&L50) -> 1.2 | P50: =IFERROR(O50/N50,0) -> 0.0032402657 | Q50: =IFERROR((P50+1)^(12/((MAX($J$7:J50)-$J$7)/30.5))-1,0) -> 0.0072457586 | R50: =N50/M50 -> 0.74068
B51: 2024-10-10 | C51: 0.49 | G51: 2024-11-25 | I51: -19.99 | J51: =VALUE(G51) -> 45621 | L51: =VALUE(B51) -> 45575 | M51: =SUM($D$7:D51) -> 500 | N51: =-SUMIFS(I:I,J:J,"<="&L51) -> 370.34 | O51: =SUMIFS(H:H,J:J,"<="&L51) -> 1.69 | P51: =IFERROR(O51/N51,0) -> 0.0045633742 | Q51: =IFERROR((P51+1)^(12/((MAX($J$7:J51)-$J$7)/30.5))-1,0) -> 0.0095677418 | R51: =N51/M51 -> 0.74068
B52: 2024-10-14 | E52: -14.96 | G52: 2024-11-27 | I52: -44.97 | J52: =VALUE(G52) -> 45623 | L52: =VALUE(B52) -> 45579 | M52: =SUM($D$7:D52) -> 500 | N52: =-SUMIFS(I:I,J:J,"<="&L52) -> 370.34 | O52: =SUMIFS(H:H,J:J,"<="&L52) -> 1.69 | P52: =IFERROR(O52/N52,0) -> 0.0045633742 | Q52: =IFERROR((P52+1)^(12/((MAX($J$7:J52)-$J$7)/30.5))-1,0) -> 0.009459122 | R52: =N52/M52 -> 0.74068
B53: 2024-10-15 | E53: -39.99 | G53: 2024-12-02 | H53: 0.06 | I53: -49.97 | J53: =VALUE(G53) -> 45628 | L53: =VALUE(B53) -> 45580 | M53: =SUM($D$7:D53) -> 500 | N53: =-SUMIFS(I:I,J:J,"<="&L53) -> 410.33 | O53: =SUMIFS(H:H,J:J,"<="&L53) -> 1.69 | P53: =IFERROR(O53/N53,0) -> 0.0041186362 | Q53: =IFERROR((P53+1)^(12/((MAX($J$7:J53)-$J$7)/30.5))-1,0) -> 0.0082997762 | R53: =N53/M53 -> 0.82066
B54: 2024-10-17 | D54: 50 | E54: -12.98 | G54: 2024-12-03 | I54: -51.41 | J54: =VALUE(G54) -> 45629 | L54: =VALUE(B54) -> 45582 | M54: =SUM($D$7:D54) -> 550 | N54: =-SUMIFS(I:I,J:J,"<="&L54) -> 423.31 | O54: =SUMIFS(H:H,J:J,"<="&L54) -> 1.69 | P54: =IFERROR(O54/N54,0) -> 0.003992346 | Q54: =IFERROR((P54+1)^(12/((MAX($J$7:J54)-$J$7)/30.5))-1,0) -> 0.0080006309 | R54: =N54/M54 -> 0.76965455
B55: 2024-10-18 | E55: -20.48 | G55: 2024-12-04 | I55: -10 | J55: =VALUE(G55) -> 45630 | L55: =VALUE(B55) -> 45583 | M55: =SUM($D$7:D55) -> 550 | N55: =-SUMIFS(I:I,J:J,"<="&L55) -> 443.79 | O55: =SUMIFS(H:H,J:J,"<="&L55) -> 1.69 | P55: =IFERROR(O55/N55,0) -> 0.0038081074 | Q55: =IFERROR((P55+1)^(12/((MAX($J$7:J55)-$J$7)/30.5))-1,0) -> 0.0075890883 | R55: =N55/M55 -> 0.80689091
B56: 2024-10-25 | C56: 2.89 | G56: 2024-12-06 | I56: -20 | J56: =VALUE(G56) -> 45632 | L56: =VALUE(B56) -> 45590 | M56: =SUM($D$7:D56) -> 550 | N56: =-SUMIFS(I:I,J:J,"<="&L56) -> 443.79 | O56: =SUMIFS(H:H,J:J,"<="&L56) -> 1.69 | P56: =IFERROR(O56/N56,0) -> 0.0038081074 | Q56: =IFERROR((P56+1)^(12/((MAX($J$7:J56)-$J$7)/30.5))-1,0) -> 0.0075071797 | R56: =N56/M56 -> 0.80689091
B57: 2024-10-28 | E57: -14.98 | G57: 2024-12-12 | H57: 0.07 | J57: =VALUE(G57) -> 45638 | L57: =VALUE(B57) -> 45593 | M57: =SUM($D$7:D57) -> 550 | N57: =-SUMIFS(I:I,J:J,"<="&L57) -> 458.77 | O57: =SUMIFS(H:H,J:J,"<="&L57) -> 1.69 | P57: =IFERROR(O57/N57,0) -> 0.0036837631 | Q57: =IFERROR((P57+1)^(12/((MAX($J$7:J57)-$J$7)/30.5))-1,0) -> 0.0070338935 | R57: =N57/M57 -> 0.83412727
B58: 2024-10-30 | C58: 2.12 | G58: 2024-12-13 | H58: 0.08 | J58: =VALUE(G58) -> 45639 | L58: =VALUE(B58) -> 45595 | M58: =SUM($D$7:D58) -> 550 | N58: =-SUMIFS(I:I,J:J,"<="&L58) -> 458.77 | O58: =SUMIFS(H:H,J:J,"<="&L58) -> 1.69 | P58: =IFERROR(O58/N58,0) -> 0.0036837631 | Q58: =IFERROR((P58+1)^(12/((MAX($J$7:J58)-$J$7)/30.5))-1,0) -> 0.0069973213 | R58: =N58/M58 -> 0.83412727
B59: 2024-11-01 | C59: 5.46 | D59: 50 | E59: -41.89 | G59: 2024-12-16 | H59: 0.08 | J59: =VALUE(G59) -> 45642 | L59: =VALUE(B59) -> 45597 | M59: =SUM($D$7:D59) -> 600 | N59: =-SUMIFS(I:I,J:J,"<="&L59) -> 500.66 | O59: =SUMIFS(H:H,J:J,"<="&L59) -> 1.69 | P59: =IFERROR(O59/N59,0) -> 0.0033755443 | Q59: =IFERROR((P59+1)^(12/((MAX($J$7:J59)-$J$7)/30.5))-1,0) -> 0.0063125382 | R59: =N59/M59 -> 0.83443333
B60: 2024-11-04 | C60: -18 | G60: 2024-12-19 | H60: 0.12 | I60: -74.97 | J60: =VALUE(G60) -> 45645 | L60: =VALUE(B60) -> 45600 | M60: =SUM($D$7:D60) -> 600 | N60: =-SUMIFS(I:I,J:J,"<="&L60) -> 500.66 | O60: =SUMIFS(H:H,J:J,"<="&L60) -> 1.69 | P60: =IFERROR(O60/N60,0) -> 0.0033755443 | Q60: =IFERROR((P60+1)^(12/((MAX($J$7:J60)-$J$7)/30.5))-1,0) -> 0.0062170791 | R60: =N60/M60 -> 0.83443333
B61: 2024-11-07 | C61: 2.6 | E61: 19.98 | G61: 2024-12-20 | I61: -10.32 | J61: =VALUE(G61) -> 45646 | L61: =VALUE(B61) -> 45603 | M61: =SUM($D$7:D61) -> 600 | N61: =-SUMIFS(I:I,J:J,"<="&L61) -> 480.68 | O61: =SUMIFS(H:H,J:J,"<="&L61) -> 4.29 | P61: =IFERROR(O61/N61,0) -> 0.0089248565 | Q61: =IFERROR((P61+1)^(12/((MAX($J$7:J61)-$J$7)/30.5))-1,0) -> 0.016392949 | R61: =N61/M61 -> 0.80113333
B62: 2024-11-08 | C62: 7.32 | G62: 2025-01-02 | I62: -17.11 | J62: =VALUE(G62) -> 45659 | L62: =VALUE(B62) -> 45604 | M62: =SUM($D$7:D62) -> 600 | N62: =-SUMIFS(I:I,J:J,"<="&L62) -> 480.68 | O62: =SUMIFS(H:H,J:J,"<="&L62) -> 4.3 | P62: =IFERROR(O62/N62,0) -> 0.0089456603 | Q62: =IFERROR((P62+1)^(12/((MAX($J$7:J62)-$J$7)/30.5))-1,0) -> 0.015420761 | R62: =N62/M62 -> 0.80113333
B63: 2024-11-12 | C63: 0.2 | E63: -12.98 | G63: 2025-01-03 | H63: 0.3 | J63: =VALUE(G63) -> 45660 | L63: =VALUE(B63) -> 45608 | M63: =SUM($D$7:D63) -> 600 | N63: =-SUMIFS(I:I,J:J,"<="&L63) -> 493.66 | O63: =SUMIFS(H:H,J:J,"<="&L63) -> 4.3 | P63: =IFERROR(O63/N63,0) -> 0.0087104485 | Q63: =IFERROR((P63+1)^(12/((MAX($J$7:J63)-$J$7)/30.5))-1,0) -> 0.014943354 | R63: =N63/M63 -> 0.82276667
B64: 2024-11-13 | C64: 2.24 | E64: -10.95 | G64: 2025-01-06 | H64: 1.43 | I64: -74.43 | J64: =VALUE(G64) -> 45663 | L64: =VALUE(B64) -> 45609 | M64: =SUM($D$7:D64) -> 600 | N64: =-SUMIFS(I:I,J:J,"<="&L64) -> 504.61 | O64: =SUMIFS(H:H,J:J,"<="&L64) -> 4.3 | P64: =IFERROR(O64/N64,0) -> 0.0085214324 | Q64: =IFERROR((P64+1)^(12/((MAX($J$7:J64)-$J$7)/30.5))-1,0) -> 0.014414565 | R64: =N64/M64 -> 0.84101667
B65: 2024-11-14 | C65: 6 | G65: 2025-01-07 | H65: 0 | J65: =VALUE(G65) -> 45664 | L65: =VALUE(B65) -> 45610 | M65: =SUM($D$7:D65) -> 600 | N65: =-SUMIFS(I:I,J:J,"<="&L65) -> 504.61 | O65: =SUMIFS(H:H,J:J,"<="&L65) -> 4.33 | P65: =IFERROR(O65/N65,0) -> 0.0085808842 | Q65: =IFERROR((P65+1)^(12/((MAX($J$7:J65)-$J$7)/30.5))-1,0) -> 0.014448363 | R65: =N65/M65 -> 0.84101667
B66: 2024-11-19 | C66: 10.51 | G66: 2025-01-09 | H66: 0.17 | J66: =VALUE(G66) -> 45666 | L66: =VALUE(B66) -> 45615 | M66: =SUM($D$7:D66) -> 600 | N66: =-SUMIFS(I:I,J:J,"<="&L66) -> 504.61 | O66: =SUMIFS(H:H,J:J,"<="&L66) -> 4.33 | P66: =IFERROR(O66/N66,0) -> 0.0085808842 | Q66: =IFERROR((P66+1)^(12/((MAX($J$7:J66)-$J$7)/30.5))-1,0) -> 0.014316079 | R66: =N66/M66 -> 0.84101667
B67: 2024-11-25 | E67: -19.99 | G67: 2025-01-10 | H67: -3.36 | I67: -4.06 | J67: =VALUE(G67) -> 45667 | L67: =VALUE(B67) -> 45621 | M67: =SUM($D$7:D67) -> 600 | N67: =-SUMIFS(I:I,J:J,"<="&L67) -> 524.6 | O67: =SUMIFS(H:H,J:J,"<="&L67) -> 4.33 | P67: =IFERROR(O67/N67,0) -> 0.0082539077 | Q67: =IFERROR((P67+1)^(12/((MAX($J$7:J67)-$J$7)/30.5))-1,0) -> 0.013706346 | R67: =N67/M67 -> 0.87433333
B68: 2024-11-27 | C68: -4.96 | D68: 85 | E68: -44.97 | G68: 2025-01-13 | H68: -0.01 | J68: =VALUE(G68) -> 45670 | L68: =VALUE(B68) -> 45623 | M68: =SUM($D$7:D68) -> 685 | N68: =-SUMIFS(I:I,J:J,"<="&L68) -> 569.57 | O68: =SUMIFS(H:H,J:J,"<="&L68) -> 4.33 | P68: =IFERROR(O68/N68,0) -> 0.0076022262 | Q68: =IFERROR((P68+1)^(12/((MAX($J$7:J68)-$J$7)/30.5))-1,0) -> 0.012451398 | R68: =N68/M68 -> 0.83148905
B69: 2024-11-28 | C69: 10.17 | G69: 2025-01-21 | H69: 3.87 | I69: -5.02 | J69: =VALUE(G69) -> 45678 | L69: =VALUE(B69) -> 45624 | M69: =SUM($D$7:D69) -> 685 | N69: =-SUMIFS(I:I,J:J,"<="&L69) -> 569.57 | O69: =SUMIFS(H:H,J:J,"<="&L69) -> 4.33 | P69: =IFERROR(O69/N69,0) -> 0.0076022262 | Q69: =IFERROR((P69+1)^(12/((MAX($J$7:J69)-$J$7)/30.5))-1,0) -> 0.01201947 | R69: =N69/M69 -> 0.83148905
B70: 2024-11-30 | D70: 85 | G70: 2025-01-22 | H70: 0 | J70: =VALUE(G70) -> 45679 | L70: =VALUE(B70) -> 45626 | M70: =SUM($D$7:D70) -> 770 | N70: =-SUMIFS(I:I,J:J,"<="&L70) -> 569.57 | O70: =SUMIFS(H:H,J:J,"<="&L70) -> 4.33 | P70: =IFERROR(O70/N70,0) -> 0.0076022262 | Q70: =IFERROR((P70+1)^(12/((MAX($J$7:J70)-$J$7)/30.5))-1,0) -> 0.011967577 | R70: =N70/M70 -> 0.7397013
B71: 2024-12-02 | C71: 0.06 | E71: -49.97 | G71: 2025-01-23 | H71: -3.09 | I71: 36.27 | J71: =VALUE(G71) -> 45680 | L71: =VALUE(B71) -> 45628 | M71: =SUM($D$7:D71) -> 770 | N71: =-SUMIFS(I:I,J:J,"<="&L71) -> 619.54 | O71: =SUMIFS(H:H,J:J,"<="&L71) -> 4.39 | P71: =IFERROR(O71/N71,0) -> 0.0070859024 | Q71: =IFERROR((P71+1)^(12/((MAX($J$7:J71)-$J$7)/30.5))-1,0) -> 0.011105206 | R71: =N71/M71 -> 0.8045974
B72: 2024-12-03 | E72: -51.41 | G72: 2025-01-24 | H72: 0.28 | J72: =VALUE(G72) -> 45681 | L72: =VALUE(B72) -> 45629 | M72: =SUM($D$7:D72) -> 770 | N72: =-SUMIFS(I:I,J:J,"<="&L72) -> 670.95 | O72: =SUMIFS(H:H,J:J,"<="&L72) -> 4.39 | P72: =IFERROR(O72/N72,0) -> 0.0065429615 | Q72: =IFERROR((P72+1)^(12/((MAX($J$7:J72)-$J$7)/30.5))-1,0) -> 0.01020888 | R72: =N72/M72 -> 0.87136364
B73: 2024-12-04 | C73: 0.17 | E73: -10 | G73: 2025-01-28 | H73: 10.31 | I73: 18.98 | J73: =VALUE(G73) -> 45685 | L73: =VALUE(B73) -> 45630 | M73: =SUM($D$7:D73) -> 770 | N73: =-SUMIFS(I:I,J:J,"<="&L73) -> 680.95 | O73: =SUMIFS(H:H,J:J,"<="&L73) -> 4.39 | P73: =IFERROR(O73/N73,0) -> 0.0064468757 | Q73: =IFERROR((P73+1)^(12/((MAX($J$7:J73)-$J$7)/30.5))-1,0) -> 0.0098895149 | R73: =N73/M73 -> 0.88435065
B74: 2024-12-05 | C74: -6.99 | G74: 2025-01-29 | H74: 0 | I74: -44.24 | J74: =VALUE(G74) -> 45686 | L74: =VALUE(B74) -> 45631 | M74: =SUM($D$7:D74) -> 770 | N74: =-SUMIFS(I:I,J:J,"<="&L74) -> 680.95 | O74: =SUMIFS(H:H,J:J,"<="&L74) -> 4.39 | P74: =IFERROR(O74/N74,0) -> 0.0064468757 | Q74: =IFERROR((P74+1)^(12/((MAX($J$7:J74)-$J$7)/30.5))-1,0) -> 0.0098481064 | R74: =N74/M74 -> 0.88435065
B75: 2024-12-06 | E75: -20 | G75: 2025-01-30 | I75: -10 | J75: =VALUE(G75) -> 45687 | L75: =VALUE(B75) -> 45632 | M75: =SUM($D$7:D75) -> 770 | N75: =-SUMIFS(I:I,J:J,"<="&L75) -> 700.95 | O75: =SUMIFS(H:H,J:J,"<="&L75) -> 4.39 | P75: =IFERROR(O75/N75,0) -> 0.0062629289 | Q75: =IFERROR((P75+1)^(12/((MAX($J$7:J75)-$J$7)/30.5))-1,0) -> 0.0095267688 | R75: =N75/M75 -> 0.91032468
B76: 2024-12-12 | C76: 0.07 | G76: 2025-02-04 | I76: -29.99 | J76: =VALUE(G76) -> 45692 | L76: =VALUE(B76) -> 45638 | M76: =SUM($D$7:D76) -> 770 | N76: =-SUMIFS(I:I,J:J,"<="&L76) -> 700.95 | O76: =SUMIFS(H:H,J:J,"<="&L76) -> 4.46 | P76: =IFERROR(O76/N76,0) -> 0.0063627934 | Q76: =IFERROR((P76+1)^(12/((MAX($J$7:J76)-$J$7)/30.5))-1,0) -> 0.0094812703 | R76: =N76/M76 -> 0.91032468
B77: 2024-12-13 | C77: 0.08 | G77: 2025-02-05 | I77: -41.84 | J77: =VALUE(G77) -> 45693 | L77: =VALUE(B77) -> 45639 | M77: =SUM($D$7:D77) -> 770 | N77: =-SUMIFS(I:I,J:J,"<="&L77) -> 700.95 | O77: =SUMIFS(H:H,J:J,"<="&L77) -> 4.54 | P77: =IFERROR(O77/N77,0) -> 0.0064769242 | Q77: =IFERROR((P77+1)^(12/((MAX($J$7:J77)-$J$7)/30.5))-1,0) -> 0.009612343 | R77: =N77/M77 -> 0.91032468
B78: 2024-12-16 | C78: 0.08 | G78: 2025-02-07 | H78: 2.81 | I78: -7.52 | J78: =VALUE(G78) -> 45695 | L78: =VALUE(B78) -> 45642 | M78: =SUM($D$7:D78) -> 770 | N78: =-SUMIFS(I:I,J:J,"<="&L78) -> 700.95 | O78: =SUMIFS(H:H,J:J,"<="&L78) -> 4.62 | P78: =IFERROR(O78/N78,0) -> 0.006591055 | Q78: =IFERROR((P78+1)^(12/((MAX($J$7:J78)-$J$7)/30.5))-1,0) -> 0.0097030413 | R78: =N78/M78 -> 0.91032468
B79: 2024-12-19 | C79: 0.12 | D79: 85 | E79: -74.97 | G79: 2025-02-10 | H79: 0 | J79: =VALUE(G79) -> 45698 | L79: =VALUE(B79) -> 45645 | M79: =SUM($D$7:D79) -> 855 | N79: =-SUMIFS(I:I,J:J,"<="&L79) -> 775.92 | O79: =SUMIFS(H:H,J:J,"<="&L79) -> 4.74 | P79: =IFERROR(O79/N79,0) -> 0.0061088772 | Q79: =IFERROR((P79+1)^(12/((MAX($J$7:J79)-$J$7)/30.5))-1,0) -> 0.0088846629 | R79: =N79/M79 -> 0.90750877
B80: 2024-12-20 | C80: -17.89 | E80: 19.61 | G80: 2025-02-11 | I80: -10 | J80: =VALUE(G80) -> 45699 | L80: =VALUE(B80) -> 45646 | M80: =SUM($D$7:D80) -> 855 | N80: =-SUMIFS(I:I,J:J,"<="&L80) -> 786.24 | O80: =SUMIFS(H:H,J:J,"<="&L80) -> 4.74 | P80: =IFERROR(O80/N80,0) -> 0.0060286935 | Q80: =IFERROR((P80+1)^(12/((MAX($J$7:J80)-$J$7)/30.5))-1,0) -> 0.0087330799 | R80: =N80/M80 -> 0.91957895
B81: 2024-12-23 | C81: 7.15 | G81: 2025-02-13 | H81: 0.03 | J81: =VALUE(G81) -> 45701 | L81: =VALUE(B81) -> 45649 | M81: =SUM($D$7:D81) -> 855 | N81: =-SUMIFS(I:I,J:J,"<="&L81) -> 786.24 | O81: =SUMIFS(H:H,J:J,"<="&L81) -> 4.74 | P81: =IFERROR(O81/N81,0) -> 0.0060286935 | Q81: =IFERROR((P81+1)^(12/((MAX($J$7:J81)-$J$7)/30.5))-1,0) -> 0.0086642893 | R81: =N81/M81 -> 0.91957895
B82: 2024-12-24 | C82: 1.64 | G82: 2025-02-18 | H82: 3.01 | I82: 2.13 | J82: =VALUE(G82) -> 45706 | L82: =VALUE(B82) -> 45650 | M82: =SUM($D$7:D82) -> 855 | N82: =-SUMIFS(I:I,J:J,"<="&L82) -> 786.24 | O82: =SUMIFS(H:H,J:J,"<="&L82) -> 4.74 | P82: =IFERROR(O82/N82,0) -> 0.0060286935 | Q82: =IFERROR((P82+1)^(12/((MAX($J$7:J82)-$J$7)/30.5))-1,0) -> 0.0084969625 | R82: =N82/M82 -> 0.91957895
B83: 2024-12-27 | C83: 0.12 | G83: 2025-02-19 | H83: 0 | J83: =VALUE(G83) -> 45707 | L83: =VALUE(B83) -> 45653 | M83: =SUM($D$7:D83) -> 855 | N83: =-SUMIFS(I:I,J:J,"<="&L83) -> 786.24 | O83: =SUMIFS(H:H,J:J,"<="&L83) -> 4.74 | P83: =IFERROR(O83/N83,0) -> 0.0060286935 | Q83: =IFERROR((P83+1)^(12/((MAX($J$7:J83)-$J$7)/30.5))-1,0) -> 0.0084642697 | R83: =N83/M83 -> 0.91957895
B84: 2025-01-02 | E84: -17.11 | G84: 2025-02-20 | I84: -74.95 | J84: =VALUE(G84) -> 45708 | L84: =VALUE(B84) -> 45659 | M84: =SUM($D$7:D84) -> 855 | N84: =-SUMIFS(I:I,J:J,"<="&L84) -> 803.35 | O84: =SUMIFS(H:H,J:J,"<="&L84) -> 4.74 | P84: =IFERROR(O84/N84,0) -> 0.0059002925 | Q84: =IFERROR((P84+1)^(12/((MAX($J$7:J84)-$J$7)/30.5))-1,0) -> 0.0082520342 | R84: =N84/M84 -> 0.93959064
B85: 2025-01-03 | C85: 0.3 | G85: 2025-02-21 | H85: 0.31 | J85: =VALUE(G85) -> 45709 | L85: =VALUE(B85) -> 45660 | M85: =SUM($D$7:D85) -> 855 | N85: =-SUMIFS(I:I,J:J,"<="&L85) -> 803.35 | O85: =SUMIFS(H:H,J:J,"<="&L85) -> 5.04 | P85: =IFERROR(O85/N85,0) -> 0.0062737288 | Q85: =IFERROR((P85+1)^(12/((MAX($J$7:J85)-$J$7)/30.5))-1,0) -> 0.0087414526 | R85: =N85/M85 -> 0.93959064
B86: 2025-01-06 | C86: 1.43 | D86: 85 | E86: -74.43 | G86: 2025-02-28 | I86: -94.46 | J86: =VALUE(G86) -> 45716 | L86: =VALUE(B86) -> 45663 | M86: =SUM($D$7:D86) -> 940 | N86: =-SUMIFS(I:I,J:J,"<="&L86) -> 877.78 | O86: =SUMIFS(H:H,J:J,"<="&L86) -> 6.47 | P86: =IFERROR(O86/N86,0) -> 0.0073708674 | Q86: =IFERROR((P86+1)^(12/((MAX($J$7:J86)-$J$7)/30.5))-1,0) -> 0.010004692 | R86: =N86/M86 -> 0.93380851
B87: 2025-01-07 | C87: 0 | G87: 2025-03-07 | H87: 0 | J87: =VALUE(G87) -> 45723 | L87: =VALUE(B87) -> 45664 | M87: =SUM($D$7:D87) -> 940 | N87: =-SUMIFS(I:I,J:J,"<="&L87) -> 877.78 | O87: =SUMIFS(H:H,J:J,"<="&L87) -> 6.47 | P87: =IFERROR(O87/N87,0) -> 0.0073708674 | Q87: =IFERROR((P87+1)^(12/((MAX($J$7:J87)-$J$7)/30.5))-1,0) -> 0.0097506377 | R87: =N87/M87 -> 0.93380851
B88: 2025-01-09 | C88: 0.17 | G88: 2025-03-11 | I88: -49.98 | J88: =VALUE(G88) -> 45727 | L88: =VALUE(B88) -> 45666 | M88: =SUM($D$7:D88) -> 940 | N88: =-SUMIFS(I:I,J:J,"<="&L88) -> 877.78 | O88: =SUMIFS(H:H,J:J,"<="&L88) -> 6.64 | P88: =IFERROR(O88/N88,0) -> 0.0075645378 | Q88: =IFERROR((P88+1)^(12/((MAX($J$7:J88)-$J$7)/30.5))-1,0) -> 0.009863996 | R88: =N88/M88 -> 0.93380851
B89: 2025-01-10 | C89: -3.36 | E89: -4.06 | G89: 2025-03-13 | H89: 0.08 | J89: =VALUE(G89) -> 45729 | L89: =VALUE(B89) -> 45667 | M89: =SUM($D$7:D89) -> 940 | N89: =-SUMIFS(I:I,J:J,"<="&L89) -> 881.84 | O89: =SUMIFS(H:H,J:J,"<="&L89) -> 3.28 | P89: =IFERROR(O89/N89,0) -> 0.0037194956 | Q89: =IFERROR((P89+1)^(12/((MAX($J$7:J89)-$J$7)/30.5))-1,0) -> 0.0048129939 | R89: =N89/M89 -> 0.93812766
B90: 2025-01-13 | C90: -0.01 | G90: 2025-03-14 | H90: 0.21 | J90: =VALUE(G90) -> 45730 | L90: =VALUE(B90) -> 45670 | M90: =SUM($D$7:D90) -> 940 | N90: =-SUMIFS(I:I,J:J,"<="&L90) -> 881.84 | O90: =SUMIFS(H:H,J:J,"<="&L90) -> 3.27 | P90: =IFERROR(O90/N90,0) -> 0.0037081557 | Q90: =IFERROR((P90+1)^(12/((MAX($J$7:J90)-$J$7)/30.5))-1,0) -> 0.0047813764 | R90: =N90/M90 -> 0.93812766
B91: 2025-01-21 | C91: 3.87 | E91: -5.02 | G91: 2025-03-17 | H91: 0.31 | J91: =VALUE(G91) -> 45733 | L91: =VALUE(B91) -> 45678 | M91: =SUM($D$7:D91) -> 940 | N91: =-SUMIFS(I:I,J:J,"<="&L91) -> 886.86 | O91: =SUMIFS(H:H,J:J,"<="&L91) -> 7.14 | P91: =IFERROR(O91/N91,0) -> 0.0080508761 | Q91: =IFERROR((P91+1)^(12/((MAX($J$7:J91)-$J$7)/30.5))-1,0) -> 0.010278325 | R91: =N91/M91 -> 0.94346809
B92: 2025-01-22 | C92: 0 | G92: 2025-03-18 | I92: -30.98 | J92: =VALUE(G92) -> 45734 | L92: =VALUE(B92) -> 45679 | M92: =SUM($D$7:D92) -> 940 | N92: =-SUMIFS(I:I,J:J,"<="&L92) -> 886.86 | O92: =SUMIFS(H:H,J:J,"<="&L92) -> 7.14 | P92: =IFERROR(O92/N92,0) -> 0.0080508761 | Q92: =IFERROR((P92+1)^(12/((MAX($J$7:J92)-$J$7)/30.5))-1,0) -> 0.010242454 | R92: =N92/M92 -> 0.94346809
B93: 2025-01-23 | C93: -3.09 | E93: 36.27 | G93: 2025-03-25 | H93: 3.11 | I93: 9.33 | J93: =VALUE(G93) -> 45741 | L93: =VALUE(B93) -> 45680 | M93: =SUM($D$7:D93) -> 940 | N93: =-SUMIFS(I:I,J:J,"<="&L93) -> 850.59 | O93: =SUMIFS(H:H,J:J,"<="&L93) -> 4.05 | P93: =IFERROR(O93/N93,0) -> 0.0047614009 | Q93: =IFERROR((P93+1)^(12/((MAX($J$7:J93)-$J$7)/30.5))-1,0) -> 0.0059107459 | R93: =N93/M93 -> 0.90488298
B94: 2025-01-24 | C94: 0.28 | G94: 2025-03-26 | H94: 0.92 | I94: 4.55 | J94: =VALUE(G94) -> 45742 | L94: =VALUE(B94) -> 45681 | M94: =SUM($D$7:D94) -> 940 | N94: =-SUMIFS(I:I,J:J,"<="&L94) -> 850.59 | O94: =SUMIFS(H:H,J:J,"<="&L94) -> 4.33 | P94: =IFERROR(O94/N94,0) -> 0.0050905842 | Q94: =IFERROR((P94+1)^(12/((MAX($J$7:J94)-$J$7)/30.5))-1,0) -> 0.0062982224 | R94: =N94/M94 -> 0.90488298
B95: 2025-01-28 | C95: 10.31 | E95: 18.98 | G95: 2025-03-27 | H95: 1.05 | I95: -125.76 | J95: =VALUE(G95) -> 45743 | L95: =VALUE(B95) -> 45685 | M95: =SUM($D$7:D95) -> 940 | N95: =-SUMIFS(I:I,J:J,"<="&L95) -> 831.61 | O95: =SUMIFS(H:H,J:J,"<="&L95) -> 14.64 | P95: =IFERROR(O95/N95,0) -> 0.017604406 | Q95: =IFERROR((P95+1)^(12/((MAX($J$7:J95)-$J$7)/30.5))-1,0) -> 0.021738484 | R95: =N95/M95 -> 0.88469149
B96: 2025-01-29 | C96: 0 | E96: -44.24 | G96: 2025-03-28 | H96: 0 | I96: -15 | J96: =VALUE(G96) -> 45744 | L96: =VALUE(B96) -> 45686 | M96: =SUM($D$7:D96) -> 940 | N96: =-SUMIFS(I:I,J:J,"<="&L96) -> 875.85 | O96: =SUMIFS(H:H,J:J,"<="&L96) -> 14.64 | P96: =IFERROR(O96/N96,0) -> 0.016715191 | Q96: =IFERROR((P96+1)^(12/((MAX($J$7:J96)-$J$7)/30.5))-1,0) -> 0.02056838 | R96: =N96/M96 -> 0.93175532
B97: 2025-01-30 | E97: -20 | G97: 2025-03-31 | H97: 0.48 | J97: =VALUE(G97) -> 45747 | L97: =VALUE(B97) -> 45687 | M97: =SUM($D$7:D97) -> 940 | N97: =-SUMIFS(I:I,J:J,"<="&L97) -> 885.85 | O97: =SUMIFS(H:H,J:J,"<="&L97) -> 14.64 | P97: =IFERROR(O97/N97,0) -> 0.0165265 | Q97: =IFERROR((P97+1)^(12/((MAX($J$7:J97)-$J$7)/30.5))-1,0) -> 0.02013105 | R97: =N97/M97 -> 0.94239362
B98: 2025-02-04 | D98: 85 | E98: -29.99 | G98: 2025-04-02 | H98: 0.45 | J98: =VALUE(G98) -> 45749 | L98: =VALUE(B98) -> 45692 | M98: =SUM($D$7:D98) -> 1025 | N98: =-SUMIFS(I:I,J:J,"<="&L98) -> 915.84 | O98: =SUMIFS(H:H,J:J,"<="&L98) -> 14.64 | P98: =IFERROR(O98/N98,0) -> 0.015985325 | Q98: =IFERROR((P98+1)^(12/((MAX($J$7:J98)-$J$7)/30.5))-1,0) -> 0.01934096 | R98: =N98/M98 -> 0.89350244
B99: 2025-02-05 | E99: -41.84 | G99: 2025-04-03 | H99: 0.17 | J99: =VALUE(G99) -> 45750 | L99: =VALUE(B99) -> 45693 | M99: =SUM($D$7:D99) -> 1025 | N99: =-SUMIFS(I:I,J:J,"<="&L99) -> 957.68 | O99: =SUMIFS(H:H,J:J,"<="&L99) -> 14.64 | P99: =IFERROR(O99/N99,0) -> 0.015286943 | Q99: =IFERROR((P99+1)^(12/((MAX($J$7:J99)-$J$7)/30.5))-1,0) -> 0.01843325 | R99: =N99/M99 -> 0.93432195
B100: 2025-02-07 | C100: 2.81 | E100: -7.52 | G100: 2025-04-04 | I100: -169.11 | J100: =VALUE(G100) -> 45751 | L100: =VALUE(B100) -> 45695 | M100: =SUM($D$7:D100) -> 1025 | N100: =-SUMIFS(I:I,J:J,"<="&L100) -> 965.2 | O100: =SUMIFS(H:H,J:J,"<="&L100) -> 17.45 | P100: =IFERROR(O100/N100,0) -> 0.018079155 | Q100: =IFERROR((P100+1)^(12/((MAX($J$7:J100)-$J$7)/30.5))-1,0) -> 0.021734021 | R100: =N100/M100 -> 0.94165854
B101: 2025-02-10 | C101: 0 | G101: 2025-04-07 | H101: 2.66 | I101: -12.35 | J101: =VALUE(G101) -> 45754 | L101: =VALUE(B101) -> 45698 | M101: =SUM($D$7:D101) -> 1025 | N101: =-SUMIFS(I:I,J:J,"<="&L101) -> 965.2 | O101: =SUMIFS(H:H,J:J,"<="&L101) -> 17.45 | P101: =IFERROR(O101/N101,0) -> 0.018079155 | Q101: =IFERROR((P101+1)^(12/((MAX($J$7:J101)-$J$7)/30.5))-1,0) -> 0.021520064 | R101: =N101/M101 -> 0.94165854
B102: 2025-02-11 | E102: -10 | G102: 2025-04-08 | H102: 0 | I102: -19.97 | J102: =VALUE(G102) -> 45755 | L102: =VALUE(B102) -> 45699 | M102: =SUM($D$7:D102) -> 1025 | N102: =-SUMIFS(I:I,J:J,"<="&L102) -> 975.2 | O102: =SUMIFS(H:H,J:J,"<="&L102) -> 17.45 | P102: =IFERROR(O102/N102,0) -> 0.017893765 | Q102: =IFERROR((P102+1)^(12/((MAX($J$7:J102)-$J$7)/30.5))-1,0) -> 0.021229368 | R102: =N102/M102 -> 0.95141463
B103: 2025-02-13 | C103: 0.03 | G103: 2025-04-10 | H103: 0.38 | J103: =VALUE(G103) -> 45757 | L103: =VALUE(B103) -> 45701 | M103: =SUM($D$7:D103) -> 1025 | N103: =-SUMIFS(I:I,J:J,"<="&L103) -> 975.2 | O103: =SUMIFS(H:H,J:J,"<="&L103) -> 17.48 | P103: =IFERROR(O103/N103,0) -> 0.017924528 | Q103: =IFERROR((P103+1)^(12/((MAX($J$7:J103)-$J$7)/30.5))-1,0) -> 0.021127732 | R103: =N103/M103 -> 0.95141463
B104: 2025-02-14 | C104: -5.9 | D104: 85 | G104: 2025-04-17 | H104: -0.17 | I104: 7.02 | J104: =VALUE(G104) -> 45764 | L104: =VALUE(B104) -> 45702 | M104: =SUM($D$7:D104) -> 1110 | N104: =-SUMIFS(I:I,J:J,"<="&L104) -> 975.2 | O104: =SUMIFS(H:H,J:J,"<="&L104) -> 17.48 | P104: =IFERROR(O104/N104,0) -> 0.017924528 | Q104: =IFERROR((P104+1)^(12/((MAX($J$7:J104)-$J$7)/30.5))-1,0) -> 0.020657885 | R104: =N104/M104 -> 0.87855856
...

Sheet Positions
B11: InReport | C11: TRUE
B13: Chapter | C13: Symbol | D13: Start Date | E13: Volume | F13: Entry Price USD | G13: Holding Period (Mon) | H13: Entry Value USD | I13: Market Value USD | J13: Unrealized Gains | K13: Unrealized Gains %
B14: Consumer Defensive | C14: PEP | D14: 45460.885 | E14: 0.6548 | F14: 151.03849 | G14: 10.880315 | H14: 98.9 | I14: 86.11 | J14: -12.79 | K14: -0.12932255
B15: Consumer Defensive | C15: MO | D15: 45518.844 | E15: 1.7987 | F15: 52.676933 | G15: 8.98002 | H15: 94.75 | I15: 104.22 | J15: 9.47 | K15: 0.09994723
B16: Consumer Defensive | C16: ACI | D16: 45693.855 | E16: 4 | F16: 20.95 | G16: 3.2419632 | H16: 83.8 | I16: 87.6 | J16: 3.8 | K16: 0.045346062
B17: Consumer Defensive | C17: KMB | D17: 45544.652 | E17: 0.4 | F17: 135.975 | G17: 8.1338774 | H17: 54.39 | I17: 54.95 | J17: 0.56 | K17: 0.01029601
B18: Consumer Defensive | C18: INGR | D18: 45580.706 | E18: 0.3486 | F18: 131.92771 | G18: 6.9517513 | H18: 45.99 | I18: 48.37 | J18: 2.38 | K18: 0.051750381
B19: Consumer Defensive | C19: DAR | D19: 45708.681 | E19: 0.8121 | F19: 36.916636 | G19: 2.7558539 | H19: 29.98 | I19: 28.67 | J19: -1.31 | K19: -0.043695797
B20: ETF | C20: BND | D20: 45743.774 | E20: 2 | F20: 73.5 | G20: 1.6052787 | H20: 147 | I20: 144.84 | J20: -2.16 | K20: -0.014693878
B21: ETF | C21: VWO | D21: 45686.833 | E21: 3 | F21: 44.946667 | G21: 3.4722024 | H21: 134.84 | I21: 143.07 | J21: 8.23 | K21: 0.061035301
B22: ETF | C22: BOTZ.UK | D22: 45482.713 | E22: 2 | F22: 20.925 | G22: 10.164654 | H22: 41.85 | I22: 40.65 | J22: -1.2 | K22: -0.028673835
B23: ETF | C23: BATT.NL | D23: 45484.679 | E23: 2 | F23: 17.505 | G23: 10.100201 | H23: 35.01 | I23: 35.74 | J23: 0.73 | K23: 0.020851185
B24: Energy & Utilities | C24: APA | D24: 45632.877 | E24: 5.7971 | F24: 18.968105 | G24: 5.2412533 | H24: 109.96 | I24: 102.84 | J24: -7.12 | K24: -0.064750818
B25: Energy & Utilities | C25: YPF | D25: 45663.738 | E25: 2.2045 | F25: 36.289408 | G25: 4.2294227 | H25: 80 | I25: 78.64 | J25: -1.36 | K25: -0.017
... B40: Consumer Cyclical | C40: YUM | D40: 45645.901 | E40: 0.0003 | F40: 133.33333 | G40: 4.8142337 | H40: 0.04 | I40: 0.04 | J40: 0 | K40: 0
B41: Grand Total | D41: 45460.885 | E41: 37.5471 | F41: 40.495538 | G41: 10.880315 | H41: 1520.49 | I41: 1585.25 | J41: 64.76 | K41: 0.042591533

Sheet CLOSED POSITION HISTORY
J6: Name and surname | M6: Account | P6: Currency | Y6: 45793.063
J7: SAMUEL EDUARDO RODRIGUEZ WALTON | M7: 50704832 | P7: USD
J8: Balance | M8: Equity | P8: Margin | S8: Free margin | V8: Margin level
J9: 85.05 | M9: 1605.25 | P9: 0 | S9: 85.05 | V9: 0
B10: CLOSED POSITION HISTORY
B11: 01/01/2006 - 16/05/2025
B12: Balance :
B13: Position | C13: Symbol | D13: Chapter | E13: ToM | F13: Type | G13: InReport | H13: Type | I13: Volume | J13: Open time | K13: Open price | L13: Close time | M13: Close price | N13: Open origin | O13: Close origin | P13: Purchase value | Q13: Sale value | R13: SL | S13: TP | T13: Margin | U13: Commission | V13: Swap | W13: Rollover | X13: Gross P/L | Y13: Comment
B14: 1345716305 | C14: NVDA | D14: =IFERROR(INDEX([1]Positions!$A:$A,MATCH(C14,[1]Positions!$C:$C,0)),"Other") -> Technology | E14: =(L14-J14)/30.5 -> 0.12621084 | F14: =IF(ISBLANK(T14),"Stock Holding","SWAP Contract") -> Stock Holding | G14: =ISNUMBER(I14) -> TRUE | H14: BUY | I14: 0.0171 | J14: 45448.646 | K14: 1184.19 | L14: 45452.495 | M14: 1184.19 | N14: xStation Mobile iOS | O14: correction | P14: 20.25 | Q14: 20.25 | U14: 0 | V14: 0 | W14: 0 | X14: 0 | Y14: STC Transfer Out
B15: 1393281432 | C15: FLOA.UK | D15: =IFERROR(INDEX([1]Positions!$A:$A,MATCH(C15,[1]Positions!$C:$C,0)),"Other") -> MISC | E15: =(L15-J15)/30.5 -> 0.007937333 | F15: =IF(ISBLANK(T15),"Stock Holding","SWAP Contract") -> Stock Holding | G15: =ISNUMBER(I15) -> TRUE | H15: BUY | I15: 0.632 | J15: 45496.376 | K15: 5.981 | L15: 45496.618 | M15: 5.967 | N15: xStation 5 | O15: xStation 5 | P15: 3.78 | Q15: 3.77 | U15: 0 | V15: 0 | W15: 0 | X15: -0.01
B16: 1393281260 | C16: SDIA.UK | D16: =IFERROR(INDEX([1]Positions!$A:$A,MATCH(C16,[1]Positions!$C:$C,0)),"Other") -> MISC | E16: =(L16-J16)/30.5 -> 0.0079381755 | F16: =IF(ISBLANK(T16),"Stock Holding","SWAP Contract") -> Stock Holding | G16: =ISNUMBER(I16) -> TRUE | H16: BUY | I16: 0.5612 | J16: 45496.376 | K16: 5.812 | L16: 45496.618 | M16: 5.81 | N16: xStation 5 | O16: xStation 5 | P16: 3.26 | Q16: 3.26 | U16: 0 | V16: 0 | W16: 0 | X16: 0
B17: 1342063955 | C17: SHELL.NL | D17: =IFERROR(INDEX([1]Positions!$A:$A,MATCH(C17,[1]Positions!$C:$C,0)),"Other") -> MISC | E17: =(L17-J17)/30.5 -> 0.23895908 | F17: =IF(ISBLANK(T17),"Stock Holding","SWAP Contract") -> Stock Holding | G17: =ISNUMBER(I17) -> TRUE | H17: BUY | I17: 0.4139 | J17: 45446.375 | K17: 33.545 | L17: 45453.664 | M17: 32.605 | N17: xStation Mobile iOS | O17: xStation Mobile iOS | P17: 15.15 | Q17: 14.42 | U17: 0 | V17: 0 | W17: 0 | X17: -0.73
B18: 1393281260 | C18: SDIA.UK | D18: =IFERROR(INDEX([1]Positions!$A:$A,MATCH(C18,[1]Positions!$C:$C,0)),"Other") -> MISC | E18: =(L18-J18)/30.5 -> 0.041921144 | F18: =IF(ISBLANK(T18),"Stock Holding","SWAP Contract") -> Stock Holding | G18: =ISNUMBER(I18) -> TRUE | H18: BUY | I18: 0.555 | J18: 45496.376 | K18: 5.812 | L18: 45497.654 | M18: 5.801 | N18: xStation 5 | O18: xStation 5 | P18: 3.23 | Q18: 3.22 | U18: 0 | V18: 0 | W18: 0 | X18: -0.01
B19: 1393281432 | C19: FLOA.UK | D19: =IFERROR(INDEX([1]Positions!$A:$A,MATCH(C19,[1]Positions!$C:$C,0)),"Other") -> MISC | E19: =(L19-J19)/30.5 -> 0.041920327 | F19: =IF(ISBLANK(T19),"Stock Holding","SWAP Contract") -> Stock Holding | G19: =ISNUMBER(I19) -> TRUE | H19: BUY | I19: 0.4344 | J19: 45496.376 | K19: 5.981 | L19: 45497.654 | M19: 5.968 | N19: xStation 5 | O19: xStation 5 | P19: 2.6 | Q19: 2.59 | U19: 0 | V19: 0 | W19: 0 | X19: -0.01
B20: 1393281260 | C20: SDIA.UK | D20: =IFERROR(INDEX([1]Positions!$A:$A,MATCH(C20,[1]Positions!$C:$C,0)),"Other") -> MISC | E20: =(L20-J20)/30.5 -> 0.041921401 | F20: =IF(ISBLANK(T20),"Stock Holding","SWAP Contract") -> Stock Holding | G20: =ISNUMBER(I20) -> TRUE | H20: BUY | I20: 1 | J20: 45496.376 | K20: 5.812 | L20: 45497.654 | M20: 5.814 | N20: xStation 5 | O20: xStation 5 | P20: 5.81 | Q20: 5.81 | U20: 0 | V20: 0 | W20: 0 | X20: 0
B21: 1393281432 | C21: FLOA.UK | D21: =IFERROR(INDEX([1]Positions!$A:$A,MATCH(C21,[1]Positions!$C:$C,0)),"Other") -> MISC | E21: =(L21-J21)/30.5 -> 0.041920625 | F21: =IF(ISBLANK(T21),"Stock Holding","SWAP Contract") -> Stock Holding | G21: =ISNUMBER(I21) -> TRUE | H21: BUY | I21: 1 | J21: 45496.376 | K21: 5.981 | L21: 45497.654 | M21: 5.978 | N21: xStation 5 | O21: xStation 5 | P21: 5.98 | Q21: 5.98 | U21: 0 | V21: 0 | W21: 0 | X21: 0
B22: 1350877137 | C22: US30 | D22: =IFERROR(INDEX([1]Positions!$A:$A,MATCH(C22,[1]Positions!$C:$C,0)),"Other") -> Other | E22: =(L22-J22)/30.5 -> 0.00013678241 | F22: =IF(ISBLANK(T22),"Stock Holding","SWAP Contract") -> SWAP Contract | G22: =ISNUMBER(I22) -> TRUE | H22: BUY | I22: 0.01 | J22: 45453.906 | K22: 38900 | L22: 45453.91 | M22: 38869 | N22: xStation Mobile iOS | O22: pending(t/p|s/l) | R22: 38874 | S22: 38933 | T22: 9.73 | U22: 0 | V22: 0 | W22: 0 | X22: -1.55 | Y22: [S/L]
B23: 1393281260 | C23: SDIA.UK | D23: =IFERROR(INDEX([1]Positions!$A:$A,MATCH(C23,[1]Positions!$C:$C,0)),"Other") -> MISC | E23: =(L23-J23)/30.5 -> 0.27081714 | F23: =IF(ISBLANK(T23),"Stock Holding","SWAP Contract") -> Stock Holding | G23: =ISNUMBER(I23) -> TRUE | H23: BUY | I23: 0.4206 | J23: 45496.376 | K23: 5.812 | L23: 45504.636 | M23: 5.826 | N23: xStation 5 | O23: xStation 5 | P23: 2.44 | Q23: 2.45 | U23: 0 | V23: 0 | W23: 0 | X23: 0.01
B24: 1393281432 | C24: FLOA.UK | D24: =IFERROR(INDEX([1]Positions!$A:$A,MATCH(C24,[1]Positions!$C:$C,0)),"Other") -> MISC | E24: =(L24-J24)/30.5 -> 0.27081632 | F24: =IF(ISBLANK(T24),"Stock Holding","SWAP Contract") -> Stock Holding | G24: =ISNUMBER(I24) -> TRUE | H24: BUY | I24: 0.4033 | J24: 45496.376 | K24: 5.981 | L24: 45504.636 | M24: 5.98 | N24: xStation 5 | O24: xStation 5 | P24: 2.41 | Q24: 2.41 | U24: 0 | V24: 0 | W24: 0 | X24: 0
B25: 1357581812 | C25: PEP | D25: =IFERROR(INDEX([1]Positions!$A:$A,MATCH(C25,[1]Positions!$C:$C,0)),"Other") -> Consumer Defensive | E25: =(L25-J25)/30.5 -> 0.0030362018 | F25: =IF(ISBLANK(T25),"Stock Holding","SWAP Contract") -> Stock Holding | G25: =ISNUMBER(I25) -> TRUE | H25: BUY | I25: 0.123 | J25: 45460.646 | K25: 1.65 | L25: 45460.738 | M25: 165.24 | N25: xStation Mobile iOS | O25: correction | P25: 0.2 | Q25: 20.32 | U25: 0 | V25: 0 | W25: 0 | X25: 0
B26: 1393281432 | C26: FLOA.UK | D26: =IFERROR(INDEX([1]Positions!$A:$A,MATCH(C26,[1]Positions!$C:$C,0)),"Other") -> MISC | E26: =(L26-J26)/30.5 -> 0.27101363 | F26: =IF(ISBLANK(T26),"Stock Holding","SWAP Contract") -> Stock Holding | G26: =ISNUMBER(I26) -> TRUE | H26: BUY | I26: 0.4201 | J26: 45496.376 | K26: 5.981 | L26: 45504.642 | M26: 5.98 | N26: xStation 5 | O26: xStation 5 | P26: 2.51 | Q26: 2.51 | U26: 0 | V26: 0 | W26: 0 | X26: 0
B27: 1393281432 | C27: FLOA.UK | D27: =IFERROR(INDEX([1]Positions!$A:$A,MATCH(C27,[1]Positions!$C:$C,0)),"Other") -> MISC | E27: =(L27-J27)/30.5 -> 7.5409692 | F27: =IF(ISBLANK(T27),"Stock Holding","SWAP Contract") -> Stock Holding | G27: =ISNUMBER(I27) -> TRUE | H27: BUY | I27: 1 | J27: 45496.376 | K27: 5.981 | L27: 45726.375 | M27: 6.186 | N27: xStation 5 | O27: xStation 5 | P27: 5.98 | Q27: 6.19 | U27: 0 | V27: 0 | W27: 0 | X27: 0.21
B28: 1393281260 | C28: SDIA.UK | D28: =IFERROR(INDEX([1]Positions!$A:$A,MATCH(C28,[1]Positions!$C:$C,0)),"Other") -> MISC | E28: =(L28-J28)/30.5 -> 7.5409712 | F28: =IF(ISBLANK(T28),"Stock Holding","SWAP Contract") -> Stock Holding | G28: =ISNUMBER(I28) -> TRUE | H28: BUY | I28: 1.4632 | J28: 45496.376 | K28: 5.812 | L28: 45726.375 | M28: 6.02 | N28: xStation 5 | O28: xStation 5 | P28: 8.5 | Q28: 8.81 | U28: 0 | V28: 0 | W28: 0 | X28: 0.3
B29: 1393287040 | C29: SDIA.UK | D29: =IFERROR(INDEX([1]Positions!$A:$A,MATCH(C29,[1]Positions!$C:$C,0)),"Other") -> MISC | E29: =(L29-J29)/30.5 -> 7.5409086 | F29: =IF(ISBLANK(T29),"Stock Holding","SWAP Contract") -> Stock Holding | G29: =ISNUMBER(I29) -> TRUE | H29: BUY | I29: 0.2503 | J29: 45496.378 | K29: 5.811 | L29: 45726.375 | M29: 6.02 | N29: xStation 5 | O29: xStation 5 | P29: 1.45 | Q29: 1.51 | U29: 0 | V29: 0 | W29: 0 | X29: 0.06
B30: 1403180431 | C30: SDIA.UK | D30: =IFERROR(INDEX([1]Positions!$A:$A,MATCH(C30,[1]Positions!$C:$C,0)),"Other") -> MISC | E30: =(L30-J30)/30.5 -> 7.2699105 | F30: =IF(ISBLANK(T30),"Stock Holding","SWAP Contract") -> Stock Holding | G30: =ISNUMBER(I30) -> TRUE | H30: BUY | I30: 0.2773 | J30: 45504.643 | K30: 5.84 | L30: 45726.375 | M30: 6.02 | N30: xStation 5 | O30: xStation 5 | P30: 1.62 | Q30: 1.67 | U30: 0 | V30: 0 | W30: 0 | X30: 0.05
B31: 1403180445 | C31: SDIA.UK | D31: =IFERROR(INDEX([1]Positions!$A:$A,MATCH(C31,[1]Positions!$C:$C,0)),"Other") -> MISC | E31: =(L31-J31)/30.5 -> 7.2699102 | F31: =IF(ISBLANK(T31),"Stock Holding","SWAP Contract") -> Stock Holding | G31: =ISNUMBER(I31) -> TRUE | H31: BUY | I31: 0.0092 | J31: 45504.643 | K31: 5.836 | L31: 45726.375 | M31: 6.02 | N31: xStation 5 | O31: xStation 5 | P31: 0.05 | Q31: 0.06 | U31: 0 | V31: 0 | W31: 0 | X31: 0.01
B32: 1343394966 | C32: SMFG | D32: =IFERROR(INDEX([1]Positions!$A:$A,MATCH(C32,[1]Positions!$C:$C,0)),"Other") -> MISC | E32: =(L32-J32)/30.5 -> 0.45839116 | F32: =IF(ISBLANK(T32),"Stock Holding","SWAP Contract") -> Stock Holding | G32: =ISNUMBER(I32) -> TRUE | H32: BUY | I32: 1 | J32: 45446.904 | K32: 13.37 | L32: 45460.885 | M32: 12.62 | N32: xStation Mobile iOS | O32: xStation Mobile iOS | P32: 13.37 | Q32: 12.62 | U32: 0 | V32: 0 | W32: 0 | X32: -0.75
B33: 1393735509 | C33: VHYD.UK | D33: =IFERROR(INDEX([1]Positions!$A:$A,MATCH(C33,[1]Positions!$C:$C,0)),"Other") -> MISC | E33: =(L33-J33)/30.5 -> 7.5330577 | F33: =IF(ISBLANK(T33),"Stock Holding","SWAP Contract") -> Stock Holding | G33: =ISNUMBER(I33) -> TRUE | H33: BUY | I33: 0.0366 | J33: 45496.618 | K33: 67.37 | L33: 45726.376 | M33: 71.16 | N33: xStation 5 | O33: xStation 5 | P33: 2.47 | Q33: 2.6 | U33: 0 | V33: 0 | W33: 0 | X33: 0.13
B34: 1395218355 | C34: VHYD.UK | D34: =IFERROR(INDEX([1]Positions!$A:$A,MATCH(C34,[1]Positions!$C:$C,0)),"Other") -> MISC | E34: =(L34-J34)/30.5 -> 7.4990754 | F34: =IF(ISBLANK(T34),"Stock Holding","SWAP Contract") -> Stock Holding | G34: =ISNUMBER(I34) -> TRUE | H34: BUY | I34: 0.074 | J34: 45497.654 | K34: 67.13 | L34: 45726.376 | M34: 71.16 | N34: xStation 5 | O34: xStation 5 | P34: 4.97 | Q34: 5.27 | U34: 0 | V34: 0 | W34: 0 | X34: 0.3
... B38: 1403180445 | C38: SDIA.UK | D38: =IFERROR(INDEX([1]Positions!$A:$A,MATCH(C38,[1]Positions!$C:$C,0)),"Other") -> MISC | E38: =(L38-J38)/30.5 -> 7.2717807 | F38: =IF(ISBLANK(T38),"Stock Holding","SWAP Contract") -> Stock Holding | G38: =ISNUMBER(I38) -> TRUE | H38: BUY | I38: 0.9908 | J38: 45504.643 | K38: 5.836 | L38: 45726.432 | M38: 6.027 | N38: xStation 5 | O38: xStation 5 | P38: 5.78 | Q38: 5.97 | U38: 0 | V38: 0 | W38: 0 | X38: 0.18
B39: 1349530190 | C39: NVDA | D39: =IFERROR(INDEX([1]Positions!$A:$A,MATCH(C39,[1]Positions!$C:$C,0)),"Other") -> Technology | E39: =(L39-J39)/30.5 -> 0.39350062 | F39: =IF(ISBLANK(T39),"Stock Holding","SWAP Contract") -> Stock Holding | G39: =ISNUMBER(I39) -> TRUE | H39: BUY | I39: 0.12 | J39: 45452.644 | K39: 118.42 | L39: 45464.646 | M39: 126.75 | N39: correction | O39: xStation Mobile iOS | P39: 14.21 | Q39: 15.21 | U39: 0 | V39: 0 | W39: 0 | X39: 1 | Y39: NVDA.US split 10 for 1
B40: 1393281432 | C40: FLOA.UK | D40: =IFERROR(INDEX([1]Positions!$A:$A,MATCH(C40,[1]Positions!$C:$C,0)),"Other") -> MISC | E40: =(L40-J40)/30.5 -> 7.5741219 | F40: =IF(ISBLANK(T40),"Stock Holding","SWAP Contract") -> Stock Holding | G40: =ISNUMBER(I40) -> TRUE | H40: BUY | I40: 0.1102 | J40: 45496.376 | K40: 5.981 | L40: 45727.386 | M40: 6.176 | N40: xStation 5 | O40: xStation 5 | P40: 0.66 | Q40: 0.68 | U40: 0 | V40: 0 | W40: 0 | X40: 0.02
B41: 1393301698 | C41: FLOA.UK | D41: =IFERROR(INDEX([1]Positions!$A:$A,MATCH(C41,[1]Positions!$C:$C,0)),"Other") -> MISC | E41: =(L41-J41)/30.5 -> 7.5740171 | F41: =IF(ISBLANK(T41),"Stock Holding","SWAP Contract") -> Stock Holding | G41: =ISNUMBER(I41) -> TRUE | H41: BUY | I41: 0.1401 | J41: 45496.379 | K41: 5.99 | L41: 45727.386 | M41: 6.176 | N41: xStation 5 | O41: xStation 5 | P41: 0.84 | Q41: 0.87 | U41: 0 | V41: 0 | W41: 0 | X41: 0.03
B42: 1403180427 | C42: FLOA.UK | D42: =IFERROR(INDEX([1]Positions!$A:$A,MATCH(C42,[1]Positions!$C:$C,0)),"Other") -> MISC | E42: =(L42-J42)/30.5 -> 7.303062 | F42: =IF(ISBLANK(T42),"Stock Holding","SWAP Contract") -> Stock Holding | G42: =ISNUMBER(I42) -> TRUE | H42: BUY | I42: 0.4203 | J42: 45504.643 | K42: 5.989 | L42: 45727.386 | M42: 6.176 | N42: xStation 5 | O42: xStation 5 | P42: 2.52 | Q42: 2.6 | U42: 0 | V42: 0 | W42: 0 | X42: 0.08
B43: 1343379129 | C43: QCOM | D43: =IFERROR(INDEX([1]Positions!$A:$A,MATCH(C43,[1]Positions!$C:$C,0)),"Other") -> Technology | E43: =(L43-J43)/30.5 -> 0.5820396 | F43: =IF(ISBLANK(T43),"Stock Holding","SWAP Contract") -> Stock Holding | G43: =ISNUMBER(I43) -> TRUE | H43: BUY | I43: 0.0975 | J43: 45446.894 | K43: 205.08 | L43: 45464.646 | M43: 211.24 | N43: xStation Mobile iOS | O43: xStation Mobile iOS | P43: 20 | Q43: 20.6 | U43: 0 | V43: 0 | W43: 0 | X43: 0.6
B44: 1349530190 | C44: NVDA | D44: =IFERROR(INDEX([1]Positions!$A:$A,MATCH(C44,[1]Positions!$C:$C,0)),"Other") -> Technology | E44: =(L44-J44)/30.5 -> 0.39350065 | F44: =IF(ISBLANK(T44),"Stock Holding","SWAP Contract") -> Stock Holding | G44: =ISNUMBER(I44) -> TRUE | H44: BUY | I44: 0.051 | J44: 45452.644 | K44: 118.42 | L44: 45464.646 | M44: 126.76 | N44: correction | O44: xStation Mobile iOS | P44: 6.04 | Q44: 6.46 | U44: 0 | V44: 0 | W44: 0 | X44: 0.42 | Y44: NVDA.US split 10 for 1
B45: 1357737013 | C45: AVGO | D45: =IFERROR(INDEX([1]Positions!$A:$A,MATCH(C45,[1]Positions!$C:$C,0)),"Other") -> MISC | E45: =(L45-J45)/30.5 -> 0.13030328 | F45: =IF(ISBLANK(T45),"Stock Holding","SWAP Contract") -> Stock Holding | G45: =ISNUMBER(I45) -> TRUE | H45: BUY | I45: 0.0115 | J45: 45460.686 | K45: 1797.13 | L45: 45464.66 | M45: 1686.26 | N45: xStation Mobile iOS | O45: xStation Mobile iOS | P45: 20.67 | Q45: 19.39 | U45: 0 | V45: 0 | W45: 0 | X45: -1.28
B46: 1362492338 | C46: GILD | D46: =IFERROR(INDEX([1]Positions!$A:$A,MATCH(C46,[1]Positions!$C:$C,0)),"Other") -> MISC | E46: =(L46-J46)/30.5 -> 0.00018840278 | F46: =IF(ISBLANK(T46),"Stock Holding","SWAP Contract") -> Stock Holding | G46: =ISNUMBER(I46) -> TRUE | H46: BUY | I46: 0.2806 | J46: 45464.662 | K46: 71.61 | L46: 45464.667 | M46: 70.96 | N46: xStation Mobile iOS | O46: xStation Mobile iOS | P46: 20.09 | Q46: 19.91 | U46: 0 | V46: 0 | W46: 0 | X46: -0.18
B47: 1342641165 | C47: TSM | D47: =IFERROR(INDEX([1]Positions!$A:$A,MATCH(C47,[1]Positions!$C:$C,0)),"Other") -> Technology | E47: =(L47-J47)/30.5 -> 1.0493769 | F47: =IF(ISBLANK(T47),"Stock Holding","SWAP Contract") -> Stock Holding | G47: =ISNUMBER(I47) -> TRUE | H47: BUY | I47: 0.1322 | J47: 45446.646 | K47: 155.59 | L47: 45478.652 | M47: 183.6 | N47: xStation Mobile iOS | O47: xStation Mobile iOS | P47: 20.57 | Q47: 24.27 | U47: 0 | V47: 0 | W47: 0 | X47: 3.7
B48: 1347626622 | C48: WMT | D48: =IFERROR(INDEX([1]Positions!$A:$A,MATCH(C48,[1]Positions!$C:$C,0)),"Other") -> Consumer Defensive | E48: =(L48-J48)/30.5 -> 1.042299 | F48: =IF(ISBLANK(T48),"Stock Holding","SWAP Contract") -> Stock Holding | G48: =ISNUMBER(I48) -> TRUE | H48: BUY | I48: 0.1488 | J48: 45449.868 | K48: 67.2 | L48: 45481.658 | M48: 69.65 | N48: xStation Mobile iOS | O48: xStation Mobile iOS | P48: 10 | Q48: 10.36 | U48: 0 | V48: 0 | W48: 0 | X48: 0.36
B49: 1362562387 | C49: DUK | D49: =IFERROR(INDEX([1]Positions!$A:$A,MATCH(C49,[1]Positions!$C:$C,0)),"Other") -> Energy & Utilities | E49: =(L49-J49)/30.5 -> 0.5572591 | F49: =IF(ISBLANK(T49),"Stock Holding","SWAP Contract") -> Stock Holding | G49: =ISNUMBER(I49) -> TRUE | H49: BUY | I49: 0.202 | J49: 45464.674 | K49: 100.78 | L49: 45481.67 | M49: 100.83 | N49: xStation Mobile iOS | O49: xStation Mobile iOS | P49: 20.36 | Q49: 20.37 | U49: 0 | V49: 0 | W49: 0 | X49: 0.01
B50: 1362488938 | C50: NEE | D50: =IFERROR(INDEX([1]Positions!$A:$A,MATCH(C50,[1]Positions!$C:$C,0)),"Other") -> Energy & Utilities | E50: =(L50-J50)/30.5 -> 0.5612481 | F50: =IF(ISBLANK(T50),"Stock Holding","SWAP Contract") -> Stock Holding | G50: =ISNUMBER(I50) -> TRUE | H50: BUY | I50: 0.2742 | J50: 45464.661 | K50: 72.93 | L50: 45481.779 | M50: 72.29 | N50: xStation Mobile iOS | O50: xStation Mobile iOS | P50: 20 | Q50: 19.82 | U50: 0 | V50: 0 | W50: 0 | X50: -0.18
B51: 1375967973 | C51: TSM | D51: =IFERROR(INDEX([1]Positions!$A:$A,MATCH(C51,[1]Positions!$C:$C,0)),"Other") -> Technology | E51: =(L51-J51)/30.5 -> 0.1027508 | F51: =IF(ISBLANK(T51),"Stock Holding","SWAP Contract") -> Stock Holding | G51: =ISNUMBER(I51) -> TRUE | H51: BUY | I51: 0.109 | J51: 45478.678 | K51: 183 | L51: 45481.812 | M51: 186.5 | N51: xStation Mobile iOS | O51: xStation Mobile iOS | P51: 19.95 | Q51: 20.33 | U51: 0 | V51: 0 | W51: 0 | X51: 0.39
B52: 1375856858 | C52: GOOGL | D52: =IFERROR(INDEX([1]Positions!$A:$A,MATCH(C52,[1]Positions!$C:$C,0)),"Other") -> Technology | E52: =(L52-J52)/30.5 -> 0.10395074 | F52: =IF(ISBLANK(T52),"Stock Holding","SWAP Contract") -> Stock Holding | G52: =ISNUMBER(I52) -> TRUE | H52: BUY | I52: 0.1052 | J52: 45478.656 | K52: 188.48 | L52: 45481.826 | M52: 189.21 | N52: xStation Mobile iOS | O52: xStation Mobile iOS | P52: 19.83 | Q52: 19.9 | U52: 0 | V52: 0 | W52: 0 | X52: 0.07
B53: 1357595824 | C53: LEVI | D53: =IFERROR(INDEX([1]Positions!$A:$A,MATCH(C53,[1]Positions!$C:$C,0)),"Other") -> MISC | E53: =(L53-J53)/30.5 -> 0.72351261 | F53: =IF(ISBLANK(T53),"Stock Holding","SWAP Contract") -> Stock Holding | G53: =ISNUMBER(I53) -> TRUE | H53: BUY | I53: 1 | J53: 45460.646 | K53: 22.89 | L53: 45482.713 | M53: 18.62 | N53: xStation Mobile iOS | O53: xStation Mobile iOS | P53: 22.89 | Q53: 18.62 | U53: 0 | V53: 0 | W53: 0 | X53: -4.27
B54: 1375967973 | C54: TSM | D54: =IFERROR(INDEX([1]Positions!$A:$A,MATCH(C54,[1]Positions!$C:$C,0)),"Other") -> Technology | E54: =(L54-J54)/30.5 -> 0.1328462 | F54: =IF(ISBLANK(T54),"Stock Holding","SWAP Contract") -> Stock Holding | G54: =ISNUMBER(I54) -> TRUE | H54: BUY | I54: 0.0014 | J54: 45478.678 | K54: 183 | L54: 45482.73 | M54: 182.97 | N54: xStation Mobile iOS | O54: xStation Mobile iOS | P54: 0.26 | Q54: 0.26 | U54: 0 | V54: 0 | W54: 0 | X54: 0
B55: 1377834040 | C55: TSM | D55: =IFERROR(INDEX([1]Positions!$A:$A,MATCH(C55,[1]Positions!$C:$C,0)),"Other") -> Technology | E55: =(L55-J55)/30.5 -> 0.029464979 | F55: =IF(ISBLANK(T55),"Stock Holding","SWAP Contract") -> Stock Holding | G55: =ISNUMBER(I55) -> TRUE | H55: BUY | I55: 0.1077 | J55: 45481.831 | K55: 186.7 | L55: 45482.73 | M55: 182.97 | N55: xStation Mobile iOS | O55: xStation Mobile iOS | P55: 20.11 | Q55: 19.71 | U55: 0 | V55: 0 | W55: 0 | X55: -0.39
B56: 1377407433 | C56: NVDA | D56: =IFERROR(INDEX([1]Positions!$A:$A,MATCH(C56,[1]Positions!$C:$C,0)),"Other") -> Technology | E56: =(L56-J56)/30.5 -> 0.039561948 | F56: =IF(ISBLANK(T56),"Stock Holding","SWAP Contract") -> Stock Holding | G56: =ISNUMBER(I56) -> TRUE | H56: BUY | I56: 0.0771 | J56: 45481.658 | K56: 129.48 | L56: 45482.865 | M56: 130.75 | N56: xStation Mobile iOS | O56: xStation Mobile iOS | P56: 9.98 | Q56: 10.08 | U56: 0 | V56: 0 | W56: 0 | X56: 0.09
... B69: 1380259753 | C69: GOOGL | D69: =IFERROR(INDEX([1]Positions!$A:$A,MATCH(C69,[1]Positions!$C:$C,0)),"Other") -> Technology | E69: =(L69-J69)/30.5 -> 2.5256771 | F69: =IF(ISBLANK(T69),"Stock Holding","SWAP Contract") -> Stock Holding | G69: =ISNUMBER(I69) -> TRUE | H69: BUY | I69: 0.131 | J69: 45483.787 | K69: 190.71 | L69: 45560.82 | M69: 161.87 | N69: xStation Mobile iOS | O69: xStation Mobile iOS | P69: 24.98 | Q69: 21.2 | U69: 0 | V69: 0 | W69: 0 | X69: -3.78
B70: 1509051251 | C70: USDMXN | D70: =IFERROR(INDEX([1]Positions!$A:$A,MATCH(C70,[1]Positions!$C:$C,0)),"Other") -> Other | E70: =(L70-J70)/30.5 -> 6.393898e-05 | F70: =IF(ISBLANK(T70),"Stock Holding","SWAP Contract") -> SWAP Contract | G70: =ISNUMBER(I70) -> TRUE | H70: SELL | I70: 0.02 | J70: 45590.728 | K70: 19.8731 | L70: 45590.73 | M70: 19.8835 | N70: xStation Mobile iOS | O70: xStation Mobile iOS | T70: 10 | U70: 0 | V70: 0 | W70: 0 | X70: -1.05
B71: 1508055372 | C71: USDMXN | D71: =IFERROR(INDEX([1]Positions!$A:$A,MATCH(C71,[1]Positions!$C:$C,0)),"Other") -> Other | E71: =(L71-J71)/30.5 -> 0.016637209 | F71: =IF(ISBLANK(T71),"Stock Holding","SWAP Contract") -> SWAP Contract | G71: =ISNUMBER(I71) -> TRUE | H71: BUY | I71: 0.02 | J71: 45590.223 | K71: 19.8369 | L71: 45590.731 | M71: 19.8761 | N71: xStation Mobile iOS | O71: xStation Mobile iOS | T71: 10 | U71: 0 | V71: 0 | W71: 0 | X71: 3.94
B72: 1512925323 | C72: USDMXN | D72: =IFERROR(INDEX([1]Positions!$A:$A,MATCH(C72,[1]Positions!$C:$C,0)),"Other") -> Other | E72: =(L72-J72)/30.5 -> 0.025088833 | F72: =IF(ISBLANK(T72),"Stock Holding","SWAP Contract") -> SWAP Contract | G72: =ISNUMBER(I72) -> TRUE | H72: BUY | I72: 0.01 | J72: 45594.791 | K72: 20.0663 | L72: 45595.556 | M72: 20.1405 | N72: xStation Mobile iOS | O72: xStation Mobile iOS | T72: 5 | U72: 0 | V72: -0.22 | W72: 0 | X72: 3.68
B73: 1514707570 | C73: USDMXN | D73: =IFERROR(INDEX([1]Positions!$A:$A,MATCH(C73,[1]Positions!$C:$C,0)),"Other") -> Other | E73: =(L73-J73)/30.5 -> 0.0020974954 | F73: =IF(ISBLANK(T73),"Stock Holding","SWAP Contract") -> SWAP Contract | G73: =ISNUMBER(I73) -> TRUE | H73: SELL | I73: 0.01 | J73: 45595.882 | K73: 20.1597 | L73: 45595.946 | M73: 20.1911 | N73: xStation Mobile iOS | O73: xStation Mobile iOS | R73: 20.19 | S73: 20.12 | T73: 5 | U73: 0 | V73: 0 | W73: 0 | X73: -1.56 | Y73: [S/L]
B74: 1516787001 | C74: GOLD | D74: =IFERROR(INDEX([1]Positions!$A:$A,MATCH(C74,[1]Positions!$C:$C,0)),"Other") -> Other | E74: =(L74-J74)/30.5 -> 3.2446495e-05 | F74: =IF(ISBLANK(T74),"Stock Holding","SWAP Contract") -> SWAP Contract | G74: =ISNUMBER(I74) -> TRUE | H74: SELL | I74: 0.01 | J74: 45597.132 | K74: 2748.04 | L74: 45597.133 | M74: 2747.79 | N74: xStation Mobile iOS | O74: xStation Mobile iOS | T74: 13.74 | U74: 0 | V74: 0 | W74: 0 | X74: 0.25
B75: 1516790032 | C75: GOLD | D75: =IFERROR(INDEX([1]Positions!$A:$A,MATCH(C75,[1]Positions!$C:$C,0)),"Other") -> Other | E75: =(L75-J75)/30.5 -> 0.00010900653 | F75: =IF(ISBLANK(T75),"Stock Holding","SWAP Contract") -> SWAP Contract | G75: =ISNUMBER(I75) -> TRUE | H75: BUY | I75: 0.01 | J75: 45597.135 | K75: 2747.23 | L75: 45597.139 | M75: 2747.25 | N75: xStation Mobile iOS | O75: xStation Mobile iOS | T75: 13.74 | U75: 0 | V75: 0 | W75: 0 | X75: 0.02
B76: 1516793905 | C76: GOLD | D76: =IFERROR(INDEX([1]Positions!$A:$A,MATCH(C76,[1]Positions!$C:$C,0)),"Other") -> Other | E76: =(L76-J76)/30.5 -> 0.00017176989 | F76: =IF(ISBLANK(T76),"Stock Holding","SWAP Contract") -> SWAP Contract | G76: =ISNUMBER(I76) -> TRUE | H76: SELL | I76: 0.01 | J76: 45597.14 | K76: 2747.11 | L76: 45597.145 | M76: 2747.77 | N76: xStation Mobile iOS | O76: xStation Mobile iOS | T76: 13.74 | U76: 0 | V76: 0 | W76: 0 | X76: -0.66
B77: 1516796610 | C77: GOLD | D77: =IFERROR(INDEX([1]Positions!$A:$A,MATCH(C77,[1]Positions!$C:$C,0)),"Other") -> Other | E77: =(L77-J77)/30.5 -> 0.00012473627 | F77: =IF(ISBLANK(T77),"Stock Holding","SWAP Contract") -> SWAP Contract | G77: =ISNUMBER(I77) -> TRUE | H77: BUY | I77: 0.01 | J77: 45597.146 | K77: 2748.12 | L77: 45597.149 | M77: 2746.29 | N77: xStation Mobile iOS | O77: xStation Mobile iOS | T77: 13.74 | U77: 0 | V77: 0 | W77: 0 | X77: -1.83
B78: 1516798655 | C78: GOLD | D78: =IFERROR(INDEX([1]Positions!$A:$A,MATCH(C78,[1]Positions!$C:$C,0)),"Other") -> Other | E78: =(L78-J78)/30.5 -> 4.1284911e-05 | F78: =IF(ISBLANK(T78),"Stock Holding","SWAP Contract") -> SWAP Contract | G78: =ISNUMBER(I78) -> TRUE | H78: SELL | I78: 0.01 | J78: 45597.149 | K78: 2746.13 | L78: 45597.151 | M78: 2747.4 | N78: xStation Mobile iOS | O78: xStation Mobile iOS | T78: 13.73 | U78: 0 | V78: 0 | W78: 0 | X78: -1.27
B79: 1516805560 | C79: GOLD | D79: =IFERROR(INDEX([1]Positions!$A:$A,MATCH(C79,[1]Positions!$C:$C,0)),"Other") -> Other | E79: =(L79-J79)/30.5 -> 0.00012187728 | F79: =IF(ISBLANK(T79),"Stock Holding","SWAP Contract") -> SWAP Contract | G79: =ISNUMBER(I79) -> TRUE | H79: BUY | I79: 0.01 | J79: 45597.164 | K79: 2748.03 | L79: 45597.168 | M79: 2748.36 | N79: xStation Mobile iOS | O79: xStation Mobile iOS | T79: 13.74 | U79: 0 | V79: 0 | W79: 0 | X79: 0.33
B80: 1516814771 | C80: GOLD | D80: =IFERROR(INDEX([1]Positions!$A:$A,MATCH(C80,[1]Positions!$C:$C,0)),"Other") -> Other | E80: =(L80-J80)/30.5 -> 0.0001822727 | F80: =IF(ISBLANK(T80),"Stock Holding","SWAP Contract") -> SWAP Contract | G80: =ISNUMBER(I80) -> TRUE | H80: BUY | I80: 0.01 | J80: 45597.184 | K80: 2749.48 | L80: 45597.19 | M80: 2749.54 | N80: xStation Mobile iOS | O80: xStation Mobile iOS | T80: 13.75 | U80: 0 | V80: 0 | W80: 0 | X80: 0.06
B81: 1516838270 | C81: GOLD | D81: =IFERROR(INDEX([1]Positions!$A:$A,MATCH(C81,[1]Positions!$C:$C,0)),"Other") -> Other | E81: =(L81-J81)/30.5 -> 0.010637264 | F81: =IF(ISBLANK(T81),"Stock Holding","SWAP Contract") -> SWAP Contract | G81: =ISNUMBER(I81) -> TRUE | H81: BUY | I81: 0.01 | J81: 45597.238 | K81: 2751.84 | L81: 45597.563 | M81: 2756.23 | N81: xStation Mobile iOS | O81: xStation Mobile iOS | S81: 2754.07 | T81: 13.76 | U81: 0 | V81: 0 | W81: 0 | X81: 4.39 | Y81: [T/P]
B82: 1515520253 | C82: USDMXN | D82: =IFERROR(INDEX([1]Positions!$A:$A,MATCH(C82,[1]Positions!$C:$C,0)),"Other") -> Other | E82: =(L82-J82)/30.5 -> 0.038447564 | F82: =IF(ISBLANK(T82),"Stock Holding","SWAP Contract") -> SWAP Contract | G82: =ISNUMBER(I82) -> TRUE | H82: BUY | I82: 0.01 | J82: 45596.558 | K82: 20.0901 | L82: 45597.731 | M82: 20.0775 | N82: xStation Mobile iOS | O82: xStation Mobile iOS | T82: 5 | U82: 0 | V82: -0.22 | W82: 0 | X82: -0.63
B83: 1517450167 | C83: USDMXN | D83: =IFERROR(INDEX([1]Positions!$A:$A,MATCH(C83,[1]Positions!$C:$C,0)),"Other") -> Other | E83: =(L83-J83)/30.5 -> 0.0044060216 | F83: =IF(ISBLANK(T83),"Stock Holding","SWAP Contract") -> SWAP Contract | G83: =ISNUMBER(I83) -> TRUE | H83: BUY | I83: 0.01 | J83: 45597.596 | K83: 19.9771 | L83: 45597.731 | M83: 20.0775 | N83: xStation Mobile iOS | O83: xStation Mobile iOS | T83: 5 | U83: 0 | V83: 0 | W83: 0 | X83: 5
B84: 1517930572 | C84: USDMXN | D84: =IFERROR(INDEX([1]Positions!$A:$A,MATCH(C84,[1]Positions!$C:$C,0)),"Other") -> Other | E84: =(L84-J84)/30.5 -> 1.6508426e-05 | F84: =IF(ISBLANK(T84),"Stock Holding","SWAP Contract") -> SWAP Contract | G84: =ISNUMBER(I84) -> TRUE | H84: SELL | I84: 0.01 | J84: 45597.73 | K84: 20.078 | L84: 45597.731 | M84: 20.082 | N84: xStation Mobile iOS | O84: xStation Mobile iOS | T84: 5 | U84: 0 | V84: 0 | W84: 0 | X84: -0.2
B85: 1517879253 | C85: VIX | D85: =IFERROR(INDEX([1]Positions!$A:$A,MATCH(C85,[1]Positions!$C:$C,0)),"Other") -> Other | E85: =(L85-J85)/30.5 -> 0.097652302 | F85: =IF(ISBLANK(T85),"Stock Holding","SWAP Contract") -> SWAP Contract | G85: =ISNUMBER(I85) -> TRUE | H85: BUY | I85: 0.01 | J85: 45597.706 | K85: 20.08 | L85: 45600.684 | M85: 19.63 | N85: xStation Mobile iOS | O85: stop-out | S85: 20.92 | T85: 12.05 | U85: 0 | V85: -0.63 | W85: 0 | X85: -18 | Y85: [S/O 29.63% 3.57 / 12.05 (USD)]
B86: 1379227659 | C86: NVDA | D86: =IFERROR(INDEX([1]Positions!$A:$A,MATCH(C86,[1]Positions!$C:$C,0)),"Other") -> Technology | E86: =(L86-J86)/30.5 -> 3.965763 | F86: =IF(ISBLANK(T86),"Stock Holding","SWAP Contract") -> Stock Holding | G86: =ISNUMBER(I86) -> TRUE | H86: BUY | I86: 0.1521 | J86: 45482.916 | K86: 131.38 | L86: 45603.872 | M86: 148.18 | N86: xStation Mobile iOS | O86: xStation Mobile iOS | P86: 19.98 | Q86: 22.54 | U86: 0 | V86: 0 | W86: 0 | X86: 2.56
B87: 1527051962 | C87: USDMXN | D87: =IFERROR(INDEX([1]Positions!$A:$A,MATCH(C87,[1]Positions!$C:$C,0)),"Other") -> Other | E87: =(L87-J87)/30.5 -> 0.01414253 | F87: =IF(ISBLANK(T87),"Stock Holding","SWAP Contract") -> SWAP Contract | G87: =ISNUMBER(I87) -> TRUE | H87: BUY | I87: 0.01 | J87: 45604.131 | K87: 19.8302 | L87: 45604.563 | M87: 19.9681 | N87: xStation Mobile iOS | O87: xStation Mobile iOS | R87: 19.97 | S87: 20.12 | T87: 5 | U87: 0 | V87: 0 | W87: 0 | X87: 6.9 | Y87: [S/L]
B88: 1527744522 | C88: USDMXN | D88: =IFERROR(INDEX([1]Positions!$A:$A,MATCH(C88,[1]Positions!$C:$C,0)),"Other") -> Other | E88: =(L88-J88)/30.5 -> 0.00048379895 | F88: =IF(ISBLANK(T88),"Stock Holding","SWAP Contract") -> SWAP Contract | G88: =ISNUMBER(I88) -> TRUE | H88: BUY | I88: 0.01 | J88: 45604.556 | K88: 19.9784 | L88: 45604.571 | M88: 19.9497 | N88: xStation Mobile iOS | O88: xStation Mobile iOS | R88: 19.95 | S88: 20.2 | T88: 5 | U88: 0 | V88: 0 | W88: 0 | X88: -1.44 | Y88: [S/L]
B89: 1528126100 | C89: USDMXN | D89: =IFERROR(INDEX([1]Positions!$A:$A,MATCH(C89,[1]Positions!$C:$C,0)),"Other") -> Other | E89: =(L89-J89)/30.5 -> 0.0016380852 | F89: =IF(ISBLANK(T89),"Stock Holding","SWAP Contract") -> SWAP Contract | G89: =ISNUMBER(I89) -> TRUE | H89: BUY | I89: 0.01 | J89: 45604.669 | K89: 20.0428 | L89: 45604.719 | M89: 20.0988 | N89: xStation Mobile iOS | O89: xStation 5 | R89: 20.0988 | S89: 20.2 | T89: 5 | U89: 0 | V89: 0 | W89: 0 | X89: 2.79 | Y89: [S/L]
B90: 1528325630 | C90: USDMXN | D90: =IFERROR(INDEX([1]Positions!$A:$A,MATCH(C90,[1]Positions!$C:$C,0)),"Other") -> Other | E90: =(L90-J90)/30.5 -> 7.5786659e-05 | F90: =IF(ISBLANK(T90),"Stock Holding","SWAP Contract") -> SWAP Contract | G90: =ISNUMBER(I90) -> TRUE | H90: SELL | I90: 0.01 | J90: 45604.72 | K90: 20.0912 | L90: 45604.723 | M90: 20.1101 | N90: xStation 5 | O90: xStation Mobile iOS | R90: 20.11 | S90: 20.0219 | T90: 5 | U90: 0 | V90: 0 | W90: 0 | X90: -0.94 | Y90: [S/L]
B91: 1531224336 | C91: USDJPY | D91: =IFERROR(INDEX([1]Positions!$A:$A,MATCH(C91,[1]Positions!$C:$C,0)),"Other") -> Other | E91: =(L91-J91)/30.5 -> 0.00014576047 | F91: =IF(ISBLANK(T91),"Stock Holding","SWAP Contract") -> SWAP Contract | G91: =ISNUMBER(I91) -> TRUE | H91: BUY | I91: 0.01 | J91: 45608.246 | K91: 153.589 | L91: 45608.25 | M91: 153.468 | N91: xStation Mobile iOS | O91: xStation Mobile iOS | R91: 153.47 | S91: 153.619 | T91: 5 | U91: 0 | V91: 0 | W91: 0 | X91: -0.79 | Y91: [S/L]
B92: 1531227124 | C92: USDJPY | D92: =IFERROR(INDEX([1]Positions!$A:$A,MATCH(C92,[1]Positions!$C:$C,0)),"Other") -> Other | E92: =(L92-J92)/30.5 -> 6.3023302e-05 | F92: =IF(ISBLANK(T92),"Stock Holding","SWAP Contract") -> SWAP Contract | G92: =ISNUMBER(I92) -> TRUE | H92: SELL | I92: 0.01 | J92: 45608.25 | K92: 153.483 | L92: 45608.252 | M92: 153.458 | N92: xStation Mobile iOS | O92: xStation Mobile iOS | R92: 153.458 | T92: 5 | U92: 0 | V92: 0 | W92: 0 | X92: 0.16 | Y92: [S/L]
B93: 1531230129 | C93: USDJPY | D93: =IFERROR(INDEX([1]Positions!$A:$A,MATCH(C93,[1]Positions!$C:$C,0)),"Other") -> Other | E93: =(L93-J93)/30.5 -> 7.2839252e-05 | F93: =IF(ISBLANK(T93),"Stock Holding","SWAP Contract") -> SWAP Contract | G93: =ISNUMBER(I93) -> TRUE | H93: SELL | I93: 0.01 | J93: 45608.254 | K93: 153.445 | L93: 45608.257 | M93: 153.502 | N93: xStation Mobile iOS | O93: xStation Mobile iOS | R93: 153.502 | S93: 153.395 | T93: 5 | U93: 0 | V93: 0 | W93: 0 | X93: -0.37 | Y93: [S/L]
B94: 1531192665 | C94: USDMXN | D94: =IFERROR(INDEX([1]Positions!$A:$A,MATCH(C94,[1]Positions!$C:$C,0)),"Other") -> Other | E94: =(L94-J94)/30.5 -> 0.0047710288 | F94: =IF(ISBLANK(T94),"Stock Holding","SWAP Contract") -> SWAP Contract | G94: =ISNUMBER(I94) -> TRUE | H94: BUY | I94: 0.02 | J94: 45608.198 | K94: 20.412 | L94: 45608.344 | M94: 20.4421 | N94: xStation Mobile iOS | O94: xStation Mobile iOS | R94: 20.4429 | S94: 20.5326 | T94: 10 | U94: 0 | V94: 0 | W94: 0 | X94: 2.94 | Y94: [S/L]
B95: 1531349564 | C95: USDMXN | D95: =IFERROR(INDEX([1]Positions!$A:$A,MATCH(C95,[1]Positions!$C:$C,0)),"Other") -> Other | E95: =(L95-J95)/30.5 -> 1.3527623e-05 | F95: =IF(ISBLANK(T95),"Stock Holding","SWAP Contract") -> SWAP Contract | G95: =ISNUMBER(I95) -> TRUE | H95: SELL | I95: 0.01 | J95: 45608.344 | K95: 20.4344 | L95: 45608.345 | M95: 20.4507 | N95: xStation Mobile iOS | O95: xStation Mobile iOS | T95: 5 | U95: 0 | V95: 0 | W95: 0 | X95: -0.8
B96: 1531351286 | C96: USDMXN | D96: =IFERROR(INDEX([1]Positions!$A:$A,MATCH(C96,[1]Positions!$C:$C,0)),"Other") -> Other | E96: =(L96-J96)/30.5 -> 0.00019965695 | F96: =IF(ISBLANK(T96),"Stock Holding","SWAP Contract") -> SWAP Contract | G96: =ISNUMBER(I96) -> TRUE | H96: BUY | I96: 0.01 | J96: 45608.346 | K96: 20.4554 | L96: 45608.352 | M96: 20.45 | N96: xStation Mobile iOS | O96: xStation Mobile iOS | R96: 20.4381 | S96: 20.47 | T96: 5 | U96: 0 | V96: 0 | W96: 0 | X96: -0.26
B97: 1531358421 | C97: USDMXN | D97: =IFERROR(INDEX([1]Positions!$A:$A,MATCH(C97,[1]Positions!$C:$C,0)),"Other") -> Other | E97: =(L97-J97)/30.5 -> 0.00015355874 | F97: =IF(ISBLANK(T97),"Stock Holding","SWAP Contract") -> SWAP Contract | G97: =ISNUMBER(I97) -> TRUE | H97: BUY | I97: 0.02 | J97: 45608.35 | K97: 20.4503 | L97: 45608.355 | M97: 20.4382 | N97: xStation Mobile iOS | O97: xStation Mobile iOS | R97: 20.4388 | S97: 20.4767 | T97: 10 | U97: 0 | V97: 0 | W97: 0 | X97: -1.18 | Y97: [S/L]
B98: 1532703059 | C98: USDMXN | D98: =IFERROR(INDEX([1]Positions!$A:$A,MATCH(C98,[1]Positions!$C:$C,0)),"Other") -> Other | E98: =(L98-J98)/30.5 -> 0.00026851169 | F98: =IF(ISBLANK(T98),"Stock Holding","SWAP Contract") -> SWAP Contract | G98: =ISNUMBER(I98) -> TRUE | H98: BUY | I98: 0.02 | J98: 45608.757 | K98: 20.6261 | L98: 45608.765 | M98: 20.6299 | N98: xStation Mobile iOS | O98: xStation Mobile iOS | R98: 20.5745 | S98: 20.6364 | T98: 10 | U98: 0 | V98: 0 | W98: 0 | X98: 0.37
B99: 1532729622 | C99: USDJPY | D99: =IFERROR(INDEX([1]Positions!$A:$A,MATCH(C99,[1]Positions!$C:$C,0)),"Other") -> Other | E99: =(L99-J99)/30.5 -> 4.7218429e-05 | F99: =IF(ISBLANK(T99),"Stock Holding","SWAP Contract") -> SWAP Contract | G99: =ISNUMBER(I99) -> TRUE | H99: BUY | I99: 0.01 | J99: 45608.767 | K99: 154.853 | L99: 45608.768 | M99: 154.873 | N99: xStation Mobile iOS | O99: xStation Mobile iOS | T99: 5 | U99: 0 | V99: 0 | W99: 0 | X99: 0.13
B100: 1533930062 | C100: USDMXN | D100: =IFERROR(INDEX([1]Positions!$A:$A,MATCH(C100,[1]Positions!$C:$C,0)),"Other") -> Other | E100: =(L100-J100)/30.5 -> 0.00076063031 | F100: =IF(ISBLANK(T100),"Stock Holding","SWAP Contract") -> SWAP Contract | G100: =ISNUMBER(I100) -> TRUE | H100: BUY | I100: 0.01 | J100: 45609.616 | K100: 20.507 | L100: 45609.639 | M100: 20.5531 | N100: xStation Mobile iOS | O100: xStation Mobile iOS | R100: 20.431 | S100: 20.5528 | T100: 5 | U100: 0 | V100: 0 | W100: 0 | X100: 2.24 | Y100: [T/P]
B101: 1536772518 | C101: USDMXN | D101: =IFERROR(INDEX([1]Positions!$A:$A,MATCH(C101,[1]Positions!$C:$C,0)),"Other") -> Other | E101: =(L101-J101)/30.5 -> 0.00035574264 | F101: =IF(ISBLANK(T101),"Stock Holding","SWAP Contract") -> SWAP Contract | G101: =ISNUMBER(I101) -> TRUE | H101: BUY | I101: 0.02 | J101: 45610.87 | K101: 20.4311 | L101: 45610.881 | M101: 20.4923 | N101: xStation Mobile iOS | O101: xStation Mobile iOS | R101: 20.4941 | S101: 20.5653 | T101: 10 | U101: 0 | V101: 0 | W101: 0 | X101: 5.97 | Y101: [S/L]
B102: 1540892910 | C102: USDMXN | D102: =IFERROR(INDEX([1]Positions!$A:$A,MATCH(C102,[1]Positions!$C:$C,0)),"Other") -> Other | E102: =(L102-J102)/30.5 -> 0.019715866 | F102: =IF(ISBLANK(T102),"Stock Holding","SWAP Contract") -> SWAP Contract | G102: =ISNUMBER(I102) -> TRUE | H102: BUY | I102: 0.02 | J102: 45614.837 | K102: 20.2371 | L102: 45615.438 | M102: 20.3181 | N102: xStation Mobile iOS | O102: xStation Mobile iOS | R102: 20.17 | S102: 20.3179 | T102: 10 | U102: 0 | V102: -0.45 | W102: 0 | X102: 7.97 | Y102: [T/P]
B103: 1541930457 | C103: USDMXN | D103: =IFERROR(INDEX([1]Positions!$A:$A,MATCH(C103,[1]Positions!$C:$C,0)),"Other") -> Other | E103: =(L103-J103)/30.5 -> 0.00077037872 | F103: =IF(ISBLANK(T103),"Stock Holding","SWAP Contract") -> SWAP Contract | G103: =ISNUMBER(I103) -> TRUE | H103: BUY | I103: 0.02 | J103: 45615.562 | K103: 20.2629 | L103: 45615.585 | M103: 20.2887 | N103: xStation Mobile iOS | O103: xStation Mobile iOS | R103: 20.2059 | S103: 20.2856 | T103: 10 | U103: 0 | V103: 0 | W103: 0 | X103: 2.54 | Y103: [T/P]
B104: 1553997553 | C104: USDMXN | D104: =IFERROR(INDEX([1]Positions!$A:$A,MATCH(C104,[1]Positions!$C:$C,0)),"Other") -> Other | E104: =(L104-J104)/30.5 -> 0.0013185352 | F104: =IF(ISBLANK(T104),"Stock Holding","SWAP Contract") -> SWAP Contract | G104: =ISNUMBER(I104) -> TRUE | H104: SELL | I104: 0.01 | J104: 45623.535 | K104: 20.7084 | L104: 45623.575 | M104: 20.7775 | N104: xStation Mobile iOS | O104: xStation Mobile iOS | R104: 20.7706 | S104: 20.68 | T104: 5 | U104: 0 | V104: 0 | W104: 0 | X104: -3.33 | Y104: [S/L]
B105: 1554074835 | C105: USDMXN | D105: =IFERROR(INDEX([1]Positions!$A:$A,MATCH(C105,[1]Positions!$C:$C,0)),"Other") -> Other | E105: =(L105-J105)/30.5 -> 1.887219e-05 | F105: =IF(ISBLANK(T105),"Stock Holding","SWAP Contract") -> SWAP Contract | G105: =ISNUMBER(I105) -> TRUE | H105: SELL | I105: 0.01 | J105: 45623.575 | K105: 20.7426 | L105: 45623.576 | M105: 20.7764 | N105: xStation Mobile iOS | O105: xStation Mobile iOS | T105: 5 | U105: 0 | V105: 0 | W105: 0 | X105: -1.63
B106: 1555669398 | C106: USDMXN | D106: =IFERROR(INDEX([1]Positions!$A:$A,MATCH(C106,[1]Positions!$C:$C,0)),"Other") -> Other | E106: =(L106-J106)/30.5 -> 0.0055216667 | F106: =IF(ISBLANK(T106),"Stock Holding","SWAP Contract") -> SWAP Contract | G106: =ISNUMBER(I106) -> TRUE | H106: BUY | I106: 0.02 | J106: 45624.551 | K106: 20.3273 | L106: 45624.719 | M106: 20.4312 | N106: xStation Mobile iOS | O106: xStation Mobile iOS | R106: 20.1748 | S106: 20.4293 | T106: 10 | U106: 0 | V106: 0 | W106: 0 | X106: 10.17 | Y106: [T/P]
B107: 1563562241 | C107: USDMXN | D107: =IFERROR(INDEX([1]Positions!$A:$A,MATCH(C107,[1]Positions!$C:$C,0)),"Other") -> Other | E107: =(L107-J107)/30.5 -> 0.012312895 | F107: =IF(ISBLANK(T107),"Stock Holding","SWAP Contract") -> SWAP Contract | G107: =ISNUMBER(I107) -> TRUE | H107: BUY | I107: 0.02 | J107: 45631.25 | K107: 20.3099 | L107: 45631.626 | M107: 20.2391 | N107: xStation Mobile iOS | O107: xStation Mobile iOS | R107: 20.24 | S107: 20.3672 | T107: 10 | U107: 0 | V107: 0 | W107: 0 | X107: -6.99 | Y107: [S/L]
B108: 1473693877 | C108: MC.FR | D108: =IFERROR(INDEX([1]Positions!$A:$A,MATCH(C108,[1]Positions!$C:$C,0)),"Other") -> MISC | E108: =(L108-J108)/30.5 -> 2.7512203 | F108: =IF(ISBLANK(T108),"Stock Holding","SWAP Contract") -> Stock Holding | G108: =ISNUMBER(I108) -> TRUE | H108: BUY | I108: 0.019 | J108: 45562.694 | K108: 700.8 | L108: 45646.606 | M108: 623.8 | N108: xStation Mobile iOS | O108: xStation Mobile iOS | P108: 14.97 | Q108: 12.28 | U108: 0 | V108: 0 | W108: 0 | X108: -2.69
B109: 1493848938 | C109: MC.FR | D109: =IFERROR(INDEX([1]Positions!$A:$A,MATCH(C109,[1]Positions!$C:$C,0)),"Other") -> MISC | E109: =(L109-J109)/30.5 -> 2.1936017 | F109: =IF(ISBLANK(T109),"Stock Holding","SWAP Contract") -> Stock Holding | G109: =ISNUMBER(I109) -> TRUE | H109: BUY | I109: 0.0213 | J109: 45579.701 | K109: 640.3 | L109: 45646.606 | M109: 623.8 | N109: xStation Mobile iOS | O109: xStation Mobile iOS | P109: 14.96 | Q109: 13.77 | U109: 0 | V109: 0 | W109: 0 | X109: -1.19
B110: 1583724019 | C110: USDMXN | D110: =IFERROR(INDEX([1]Positions!$A:$A,MATCH(C110,[1]Positions!$C:$C,0)),"Other") -> Other | E110: =(L110-J110)/30.5 -> 0.0029510147 | F110: =IF(ISBLANK(T110),"Stock Holding","SWAP Contract") -> SWAP Contract | G110: =ISNUMBER(I110) -> TRUE | H110: BUY | I110: 0.02 | J110: 45646.606 | K110: 20.2054 | L110: 45646.696 | M110: 20.1035 | N110: xStation Mobile iOS | O110: xStation Mobile iOS | R110: 20.1055 | S110: 20.3273 | T110: 10 | U110: 0 | V110: 0 | W110: 0 | X110: -10.13 | Y110: [S/L]
B111: 1583841034 | C111: USDMXN | D111: =IFERROR(INDEX([1]Positions!$A:$A,MATCH(C111,[1]Positions!$C:$C,0)),"Other") -> Other | E111: =(L111-J111)/30.5 -> 0.0021620575 | F111: =IF(ISBLANK(T111),"Stock Holding","SWAP Contract") -> SWAP Contract | G111: =ISNUMBER(I111) -> TRUE | H111: BUY | I111: 0.01 | J111: 45646.64 | K111: 20.173 | L111: 45646.706 | M111: 20.0949 | N111: xStation Mobile iOS | O111: xStation Mobile iOS | R111: 20.0975 | S111: 20.2542 | T111: 5 | U111: 0 | V111: 0 | W111: 0 | X111: -3.88 | Y111: [S/L]
B112: 1585474078 | C112: USDMXN | D112: =IFERROR(INDEX([1]Positions!$A:$A,MATCH(C112,[1]Positions!$C:$C,0)),"Other") -> Other | E112: =(L112-J112)/30.5 -> 0.0054726916 | F112: =IF(ISBLANK(T112),"Stock Holding","SWAP Contract") -> SWAP Contract | G112: =ISNUMBER(I112) -> TRUE | H112: BUY | I112: 0.02 | J112: 45649.401 | K112: 20.0935 | L112: 45649.568 | M112: 20.1707 | N112: xStation Mobile iOS | O112: xStation Mobile iOS | R112: 20 | S112: 20.17 | T112: 10 | U112: 0 | V112: 0 | W112: 0 | X112: 7.65 | Y112: [T/P]
B113: 1586033461 | C113: USDMXN | D113: =IFERROR(INDEX([1]Positions!$A:$A,MATCH(C113,[1]Positions!$C:$C,0)),"Other") -> Other | E113: =(L113-J113)/30.5 -> 2.8149289e-05 | F113: =IF(ISBLANK(T113),"Stock Holding","SWAP Contract") -> SWAP Contract | G113: =ISNUMBER(I113) -> TRUE | H113: BUY | I113: 0.01 | J113: 45649.631 | K113: 20.1772 | L113: 45649.632 | M113: 20.1671 | N113: xStation Mobile iOS | O113: xStation Mobile iOS | R113: 20.1687 | S113: 20.2379 | T113: 5 | U113: 0 | V113: 0 | W113: 0 | X113: -0.5 | Y113: [S/L]
B114: 1587036381 | C114: USDMXN | D114: =IFERROR(INDEX([1]Positions!$A:$A,MATCH(C114,[1]Positions!$C:$C,0)),"Other") -> Other | E114: =(L114-J114)/30.5 -> 0.0030278966 | F114: =IF(ISBLANK(T114),"Stock Holding","SWAP Contract") -> SWAP Contract | G114: =ISNUMBER(I114) -> TRUE | H114: BUY | I114: 0.02 | J114: 45650.488 | K114: 20.1462 | L114: 45650.58 | M114: 20.1627 | N114: xStation Mobile iOS | O114: xStation Mobile iOS | R114: 20.1627 | S114: 20.22 | T114: 10 | U114: 0 | V114: 0 | W114: 0 | X114: 1.64 | Y114: [S/L]
B115: 1500272843 | C115: ASML | D115: =IFERROR(INDEX([1]Positions!$A:$A,MATCH(C115,[1]Positions!$C:$C,0)),"Other") -> Technology | E115: =(L115-J115)/30.5 -> 2.6237564 | F115: =IF(ISBLANK(T115),"Stock Holding","SWAP Contract") -> Stock Holding | G115: =ISNUMBER(I115) -> TRUE | H115: BUY | I115: 0.0264 | J115: 45583.646 | K115: 718.5 | L115: 45663.67 | M115: 757.79 | N115: xStation Mobile iOS | O115: xStation Mobile iOS | P115: 18.97 | Q115: 20.01 | U115: 0 | V115: 0 | W115: 0 | X115: 1.04
B116: 1500272843 | C116: ASML | D116: =IFERROR(INDEX([1]Positions!$A:$A,MATCH(C116,[1]Positions!$C:$C,0)),"Other") -> Technology | E116: =(L116-J116)/30.5 -> 2.623761 | F116: =IF(ISBLANK(T116),"Stock Holding","SWAP Contract") -> Stock Holding | G116: =ISNUMBER(I116) -> TRUE | H116: BUY | I116: 0.0021 | J116: 45583.646 | K116: 718.5 | L116: 45663.671 | M116: 758.27 | N116: xStation Mobile iOS | O116: xStation Mobile iOS | P116: 1.51 | Q116: 1.59 | U116: 0 | V116: 0 | W116: 0 | X116: 0.08
B117: 1518147105 | C117: MAXN | D117: =IFERROR(INDEX([1]Positions!$A:$A,MATCH(C117,[1]Positions!$C:$C,0)),"Other") -> Technology | E117: =(L117-J117)/30.5 -> 2.2895344 | F117: =IF(ISBLANK(T117),"Stock Holding","SWAP Contract") -> Stock Holding | G117: =ISNUMBER(I117) -> TRUE | H117: BUY | I117: 1 | J117: 45597.85 | K117: 10.92 | L117: 45667.681 | M117: 6.52 | N117: xStation Mobile iOS | O117: xStation Mobile iOS | P117: 10.92 | Q117: 6.52 | U117: 0 | V117: 0 | W117: 0 | X117: -4.4
B118: 1551373923 | C118: GOOGL | D118: =IFERROR(INDEX([1]Positions!$A:$A,MATCH(C118,[1]Positions!$C:$C,0)),"Other") -> Technology | E118: =(L118-J118)/30.5 -> 1.8639366 | F118: =IF(ISBLANK(T118),"Stock Holding","SWAP Contract") -> Stock Holding | G118: =ISNUMBER(I118) -> TRUE | H118: BUY | I118: 0.1195 | J118: 45621.856 | K118: 167.24 | L118: 45678.706 | M118: 198.83 | N118: xStation Mobile iOS | O118: xStation Mobile iOS | P118: 19.99 | Q118: 23.76 | U118: 0 | V118: 0 | W118: 0 | X118: 3.77
B119: 1373744560 | C119: QCOM | D119: =IFERROR(INDEX([1]Positions!$A:$A,MATCH(C119,[1]Positions!$C:$C,0)),"Other") -> Technology | E119: =(L119-J119)/30.5 -> 6.6911466 | F119: =IF(ISBLANK(T119),"Stock Holding","SWAP Contract") -> Stock Holding | G119: =ISNUMBER(I119) -> TRUE | H119: BUY | I119: 0.1248 | J119: 45476.646 | K119: 202.58 | L119: 45680.726 | M119: 172.09 | N119: xStation Mobile iOS | O119: xStation Mobile iOS | P119: 25.28 | Q119: 21.48 | U119: 0 | V119: 0 | W119: 0 | X119: -3.8
B120: 1450039117 | C120: QCOM | D120: =IFERROR(INDEX([1]Positions!$A:$A,MATCH(C120,[1]Positions!$C:$C,0)),"Other") -> Technology | E120: =(L120-J120)/30.5 -> 4.46148 | F120: =IF(ISBLANK(T120),"Stock Holding","SWAP Contract") -> Stock Holding | G120: =ISNUMBER(I120) -> TRUE | H120: BUY | I120: 0.068 | J120: 45544.651 | K120: 161.58 | L120: 45680.726 | M120: 172.09 | N120: xStation Mobile iOS | O120: xStation Mobile iOS | P120: 10.99 | Q120: 11.7 | U120: 0 | V120: 0 | W120: 0 | X120: 0.71
...

Sheet OPEN POSITION
I5: Name and surname | L5: Account | O5: Currency | T5: 45793.063
I6: SAMUEL EDUARDO RODRIGUEZ WALTON | L6: 50704832 | O6: USD
I7: Balance | L7: Equity | O7: Margin | Q7: Free margin | T7: Margin level
I8: 85.05 | L8: 1605.25 | O8: 0 | Q8: 85.05 | T8: 0
B9: OPEN POSITION HISTORY
B10: 45793
B11: Position | C11: Symbol | D11: Chapter | E11: ToM | F11: InReport | G11: Type | H11: Volume | I11: Open time | J11: Open price | K11: Market price | L11: Purchase value | M11: SL | N11: TP | O11: Margin | P11: Commission | Q11: Swap | R11: Rollover | S11: Gross P/L | T11: Comment
B12: 1744916452 | C12: ING | D12: =IFERROR(INDEX([1]Positions!$A:$A,MATCH(C12,[1]Positions!$C:$C,0)),"Other") -> Financial Services | E12: =(NOW()-I12)/30.5 -> 1.3480436 | F12: =ISNUMBER(H12) -> TRUE | G12: BUY | H12: 0.4245 | I12: 45751.742 | J12: 17.54 | K12: 21.1 | L12: 7.45 | O12: 0 | P12: 0 | Q12: 0 | R12: 0 | S12: 1.51
B13: 1817264187 | C13: CIB | D13: =IFERROR(INDEX([1]Positions!$A:$A,MATCH(C13,[1]Positions!$C:$C,0)),"Other") -> Financial Services | E13: =(NOW()-I13)/30.5 -> 0.10521437 | F13: =ISNUMBER(H13) -> TRUE | G13: BUY | H13: 0.4757 | I13: 45789.649 | J13: 42.02 | K13: 42.15 | L13: 19.99 | O13: 0 | P13: 0 | Q13: 0 | R13: 0 | S13: 0.06
B14: 1566610015 | C14: APA | D14: =IFERROR(INDEX([1]Positions!$A:$A,MATCH(C14,[1]Positions!$C:$C,0)),"Other") -> Energy & Utilities | E14: =(NOW()-I14)/30.5 -> 5.2452774 | F14: =ISNUMBER(H14) -> TRUE | G14: BUY | H14: 0.9385 | I14: 45632.877 | J14: 21.31 | K14: 17.74 | L14: 20 | O14: 0 | P14: 0 | Q14: 0 | R14: 0 | S14: -3.35
B15: 1644796307 | C15: ACI | D15: =IFERROR(INDEX([1]Positions!$A:$A,MATCH(C15,[1]Positions!$C:$C,0)),"Other") -> Consumer Defensive | E15: =(NOW()-I15)/30.5 -> 3.2459874 | F15: =ISNUMBER(H15) -> TRUE | G15: BUY | H15: 1 | I15: 45693.855 | J15: 20.36 | K15: 21.9 | L15: 20.36 | O15: 0 | P15: 0 | Q15: 0 | R15: 0 | S15: 1.54
B16: 1582737192 | C16: MA | D16: =IFERROR(INDEX([1]Positions!$A:$A,MATCH(C16,[1]Positions!$C:$C,0)),"Other") -> Financial Services | E16: =(NOW()-I16)/30.5 -> 4.8182358 | F16: =ISNUMBER(H16) -> TRUE | G16: BUY | H16: 0.001 | I16: 45645.901 | J16: 524.43 | K16: 582.24 | L16: 0.52 | O16: 0 | P16: 0 | Q16: 0 | R16: 0 | S16: 0.06
B17: 1422773288 | C17: MO | D17: =IFERROR(INDEX([1]Positions!$A:$A,MATCH(C17,[1]Positions!$C:$C,0)),"Other") -> Consumer Defensive | E17: =(NOW()-I17)/30.5 -> 8.9840442 | F17: =ISNUMBER(H17) -> TRUE | G17: BUY | H17: 0.483 | I17: 45518.844 | J17: 51.24 | K17: 57.94 | L17: 24.75 | O17: 0 | P17: 0 | Q17: 0 | R17: 0 | S17: 3.24
B18: 1727563010 | C18: VWO | D18: =IFERROR(INDEX([1]Positions!$A:$A,MATCH(C18,[1]Positions!$C:$C,0)),"Other") -> ETF | E18: =(NOW()-I18)/30.5 -> 1.6097234 | F18: =ISNUMBER(H18) -> TRUE | G18: BUY | H18: 1 | I18: 45743.761 | J18: 46.11 | K18: 47.69 | L18: 46.11 | O18: 0 | P18: 0 | Q18: 0 | R18: 0 | S18: 1.58
B19: 1599455288 | C19: YPF | D19: =IFERROR(INDEX([1]Positions!$A:$A,MATCH(C19,[1]Positions!$C:$C,0)),"Other") -> Energy & Utilities | E19: =(NOW()-I19)/30.5 -> 4.2334469 | F19: =ISNUMBER(H19) -> TRUE | G19: BUY | H19: 0.2195 | I19: 45663.738 | J19: 45.55 | K19: 35.67 | L19: 10 | O19: 0 | P19: 0 | Q19: 0 | R19: 0 | S19: -2.17
B20: 1381417257 | C20: BATT.NL | D20: =IFERROR(INDEX([1]Positions!$A:$A,MATCH(C20,[1]Positions!$C:$C,0)),"Other") -> ETF | E20: =(NOW()-I20)/30.5 -> 10.104225 | F20: =ISNUMBER(H20) -> TRUE | G20: BUY | H20: 1 | I20: 45484.679 | J20: 16.374 | K20: 16.066 | L20: 17.9 | O20: 0 | P20: 0 | Q20: 0 | R20: 0 | S20: -0.03
B21: 1644789287 | C21: KMB | D21: =IFERROR(INDEX([1]Positions!$A:$A,MATCH(C21,[1]Positions!$C:$C,0)),"Other") -> Consumer Defensive | E21: =(NOW()-I21)/30.5 -> 3.2461115 | F21: =ISNUMBER(H21) -> TRUE | G21: BUY | H21: 0.0813 | I21: 45693.851 | J21: 129.08 | K21: 137.35 | L21: 10.49 | O21: 0 | P21: 0 | Q21: 0 | R21: 0 | S21: 0.68
B22: 1729617775 | C22: TSM | D22: =IFERROR(INDEX([1]Positions!$A:$A,MATCH(C22,[1]Positions!$C:$C,0)),"Other") -> Technology | E22: =(NOW()-I22)/30.5 -> 1.5784995 | F22: =ISNUMBER(H22) -> TRUE | G22: BUY | H22: 0.0907 | I22: 45744.713 | J22: 165.35 | K22: 194.23 | L22: 15 | O22: 0 | P22: 0 | Q22: 0 | R22: 0 | S22: 2.62
B23: 1554741910 | C23: ING | D23: =IFERROR(INDEX([1]Positions!$A:$A,MATCH(C23,[1]Positions!$C:$C,0)),"Other") -> Financial Services | E23: =(NOW()-I23)/30.5 -> 5.5445286 | F23: =ISNUMBER(H23) -> TRUE | G23: BUY | H23: 0.3495 | I23: 45623.75 | J23: 15.3 | K23: 21.1 | L23: 5.35 | O23: 0 | P23: 0 | Q23: 0 | R23: 0 | S23: 2.02
... B108: 1599435465 | C108: MA | D108: =IFERROR(INDEX([1]Positions!$A:$A,MATCH(C108,[1]Positions!$C:$C,0)),"Other") -> Financial Services | E108: =(NOW()-I108)/30.5 -> 4.233655 | F108: =ISNUMBER(H108) -> TRUE | G108: BUY | H108: 0.0289 | I108: 45663.731 | J108: 517.7 | K108: 582.24 | L108: 14.96 | O108: 0 | P108: 0 | Q108: 0 | R108: 0 | S108: 1.87
B109: Total | D109: =IFERROR(INDEX([1]Positions!$A:$A,MATCH(C109,[1]Positions!$C:$C,0)),"Other") -> Other | E109: =(NOW()-I109)/30.5 -> #VALUE! | F109: =ISNUMBER(H109) -> FALSE | P109: 0 | Q109: 0 | R109: 0 | S109: 64.76

Sheet PENDING ORDERS HISTORY 
D5: Name and surname | G5: Account | J5: Currency | M5: 45786.091
D6: SAMUEL EDUARDO RODRIGUEZ WALTON | G6: 50704832 | J6: USD
D7: Balance | G7: Equity | J7: Margin | L7: Free margin | M7: Margin level
D8: 93.01 | G8: 1531.79 | J8: 0 | L8: 93.01 | M8: 0
B9: PENDING ORDERS HISTORY
B10: 45786
B11: ID | C11: Symbol | D11: Purchase value | E11: Nominal Value | F11: Price | G11: Margin | H11: Type | I11: Order | J11: side | K11: SL | L11: TP | M11: Open time

Sheet CASH OPERATION HISTORY
D5: Name and surname | E5: Account | F5: Currency | K5: 45793.063
D6: SAMUEL EDUARDO RODRIGUEZ WALTON | E6: 50704832 | F6: USD
D7: Balance | E7: Equity | F7: Margin | J7: Free margin | K7: Margin level
D8: 85.05 | E8: 1605.25 | F8: 0 | J8: 85.05 | K8: 0
B9: CASH OPERATION HISTORY
B10: 01/01/2006 - 16/05/2025
B11: ID | C11: Type | D11: Time | E11: Comment | F11: Symbol | G11: Chapter | H11: InReport | I11: DATE | J11: Amount
B12: 807882095 | C12: Stock purchase | D12: 45789.648 | E12: OPEN BUY 0.2267 @ 44.10 | F12: EXC | G12: =IFERROR(INDEX([1]Positions!$A:$A,MATCH(F12,[1]Positions!$C:$C,0)),"Other") -> Energy & Utilities | H12: =ISNUMBER(D12) -> TRUE | I12: =TEXT(D12,"YYYY-MM-DD") -> 2025-05-12 | J12: -10
B13: 743536649 | C13: close trade | D13: 45726.375 | E13: Profit of position #1393281432 | F13: FLOA.UK | G13: =IFERROR(INDEX([1]Positions!$A:$A,MATCH(F13,[1]Positions!$C:$C,0)),"Other") -> MISC | H13: =ISNUMBER(D13) -> TRUE | I13: =TEXT(D13,"YYYY-MM-DD") -> 2025-03-10 | J13: 0.21
B14: 743536650 | C14: Stock sale | D14: 45726.375 | E14: CLOSE BUY 1/1.6706 @ 6.1860 | F14: FLOA.UK | G14: =IFERROR(INDEX([1]Positions!$A:$A,MATCH(F14,[1]Positions!$C:$C,0)),"Other") -> MISC | H14: =ISNUMBER(D14) -> TRUE | I14: =TEXT(D14,"YYYY-MM-DD") -> 2025-03-10 | J14: 5.98
B15: 743538255 | C15: close trade | D15: 45726.375 | E15: Profit of position #1393281260 | F15: SDIA.UK | G15: =IFERROR(INDEX([1]Positions!$A:$A,MATCH(F15,[1]Positions!$C:$C,0)),"Other") -> MISC | H15: =ISNUMBER(D15) -> TRUE | I15: =TEXT(D15,"YYYY-MM-DD") -> 2025-03-10 | J15: 0.3
B16: 743538256 | C16: Stock sale | D16: 45726.375 | E16: CLOSE BUY 1.4632/2.9908 @ 6.0200 | F16: SDIA.UK | G16: =IFERROR(INDEX([1]Positions!$A:$A,MATCH(F16,[1]Positions!$C:$C,0)),"Other") -> MISC | H16: =ISNUMBER(D16) -> TRUE | I16: =TEXT(D16,"YYYY-MM-DD") -> 2025-03-10 | J16: 8.51
B17: 743538257 | C17: close trade | D17: 45726.375 | E17: Profit of position #1393287040 | F17: SDIA.UK | G17: =IFERROR(INDEX([1]Positions!$A:$A,MATCH(F17,[1]Positions!$C:$C,0)),"Other") -> MISC | H17: =ISNUMBER(D17) -> TRUE | I17: =TEXT(D17,"YYYY-MM-DD") -> 2025-03-10 | J17: 0.06
B18: 743538259 | C18: Stock sale | D18: 45726.375 | E18: CLOSE BUY 0.2503/2.9908 @ 6.0200 | F18: SDIA.UK | G18: =IFERROR(INDEX([1]Positions!$A:$A,MATCH(F18,[1]Positions!$C:$C,0)),"Other") -> MISC | H18: =ISNUMBER(D18) -> TRUE | I18: =TEXT(D18,"YYYY-MM-DD") -> 2025-03-10 | J18: 1.45
B19: 743538262 | C19: close trade | D19: 45726.375 | E19: Profit of position #1403180431 | F19: SDIA.UK | G19: =IFERROR(INDEX([1]Positions!$A:$A,MATCH(F19,[1]Positions!$C:$C,0)),"Other") -> MISC | H19: =ISNUMBER(D19) -> TRUE | I19: =TEXT(D19,"YYYY-MM-DD") -> 2025-03-10 | J19: 0.05
B20: 743538263 | C20: Stock sale | D20: 45726.375 | E20: CLOSE BUY 0.2773/2.9908 @ 6.0200 | F20: SDIA.UK | G20: =IFERROR(INDEX([1]Positions!$A:$A,MATCH(F20,[1]Positions!$C:$C,0)),"Other") -> MISC | H20: =ISNUMBER(D20) -> TRUE | I20: =TEXT(D20,"YYYY-MM-DD") -> 2025-03-10 | J20: 1.62
B21: 743538266 | C21: close trade | D21: 45726.375 | E21: Profit of position #1403180445 | F21: SDIA.UK | G21: =IFERROR(INDEX([1]Positions!$A:$A,MATCH(F21,[1]Positions!$C:$C,0)),"Other") -> MISC | H21: =ISNUMBER(D21) -> TRUE | I21: =TEXT(D21,"YYYY-MM-DD") -> 2025-03-10 | J21: 0.01
B22: 743538267 | C22: Stock sale | D22: 45726.375 | E22: CLOSE BUY 0.0092/2.9908 @ 6.0200 | F22: SDIA.UK | G22: =IFERROR(INDEX([1]Positions!$A:$A,MATCH(F22,[1]Positions!$C:$C,0)),"Other") -> MISC | H22: =ISNUMBER(D22) -> TRUE | I22: =TEXT(D22,"YYYY-MM-DD") -> 2025-03-10 | J22: 0.05
B23: 743548157 | C23: close trade | D23: 45726.376 | E23: Profit of position #1393735509 | F23: VHYD.UK | G23: =IFERROR(INDEX([1]Positions!$A:$A,MATCH(F23,[1]Positions!$C:$C,0)),"Other") -> MISC | H23: =ISNUMBER(D23) -> TRUE | I23: =TEXT(D23,"YYYY-MM-DD") -> 2025-03-10 | J23: 0.13
... B39: 745059933 | C39: Stock sale | D39: 45727.386 | E39: CLOSE BUY 0.4203/0.6706 @ 6.1760 | F39: FLOA.UK | G39: =IFERROR(INDEX([1]Positions!$A:$A,MATCH(F39,[1]Positions!$C:$C,0)),"Other") -> MISC | H39: =ISNUMBER(D39) -> TRUE | I39: =TEXT(D39,"YYYY-MM-DD") -> 2025-03-11 | J39: 2.52
B40: 745059994 | C40: Subaccount Transfer | D40: 45727.386 | E40: Transfer from 50872299 to 50704832 | G40: =IFERROR(INDEX([1]Positions!$A:$A,MATCH(F40,[1]Positions!$C:$C,0)),"Other") -> Other | H40: =ISNUMBER(D40) -> TRUE | I40: =TEXT(D40,"YYYY-MM-DD") -> 2025-03-11 | J40: -52.08
B41: 745059928 | C41: close trade | D41: 45727.386 | E41: Profit of position #1393281432 | F41: FLOA.UK | G41: =IFERROR(INDEX([1]Positions!$A:$A,MATCH(F41,[1]Positions!$C:$C,0)),"Other") -> MISC | H41: =ISNUMBER(D41) -> TRUE | I41: =TEXT(D41,"YYYY-MM-DD") -> 2025-03-11 | J41: 0.02
B42: 584485943 | C42: Subaccount Transfer | D42: 45495.926 | E42: Transfer from 50704832 to 50872299 | G42: =IFERROR(INDEX([1]Positions!$A:$A,MATCH(F42,[1]Positions!$C:$C,0)),"Other") -> Other | H42: =ISNUMBER(D42) -> TRUE | I42: =TEXT(D42,"YYYY-MM-DD") -> 2024-07-22 | J42: 50
B43: 584584545 | C43: Stock purchase | D43: 45496.376 | E43: OPEN BUY 4/4.1401 @ 5.9810 | F43: FLOA.UK | G43: =IFERROR(INDEX([1]Positions!$A:$A,MATCH(F43,[1]Positions!$C:$C,0)),"Other") -> MISC | H43: =ISNUMBER(D43) -> TRUE | I43: =TEXT(D43,"YYYY-MM-DD") -> 2024-07-23 | J43: -23.92
B44: 584584380 | C44: Stock purchase | D44: 45496.376 | E44: OPEN BUY 4/4.2503 @ 5.8120 | F44: SDIA.UK | G44: =IFERROR(INDEX([1]Positions!$A:$A,MATCH(F44,[1]Positions!$C:$C,0)),"Other") -> MISC | H44: =ISNUMBER(D44) -> TRUE | I44: =TEXT(D44,"YYYY-MM-DD") -> 2024-07-23 | J44: -23.25
B45: 584587915 | C45: Stock purchase | D45: 45496.378 | E45: OPEN BUY 0.2503/4.2503 @ 5.8110 | F45: SDIA.UK | G45: =IFERROR(INDEX([1]Positions!$A:$A,MATCH(F45,[1]Positions!$C:$C,0)),"Other") -> MISC | H45: =ISNUMBER(D45) -> TRUE | I45: =TEXT(D45,"YYYY-MM-DD") -> 2024-07-23 | J45: -1.45
B46: 584598125 | C46: Stock purchase | D46: 45496.379 | E46: OPEN BUY 0.1401/4.1401 @ 5.9900 | F46: FLOA.UK | G46: =IFERROR(INDEX([1]Positions!$A:$A,MATCH(F46,[1]Positions!$C:$C,0)),"Other") -> MISC | H46: =ISNUMBER(D46) -> TRUE | I46: =TEXT(D46,"YYYY-MM-DD") -> 2024-07-23 | J46: -0.84
B47: 584801661 | C47: Stock purchase | D47: 45496.618 | E47: OPEN BUY 0.0366 @ 67.370 | F47: VHYD.UK | G47: =IFERROR(INDEX([1]Positions!$A:$A,MATCH(F47,[1]Positions!$C:$C,0)),"Other") -> MISC | H47: =ISNUMBER(D47) -> TRUE | I47: =TEXT(D47,"YYYY-MM-DD") -> 2024-07-23 | J47: -2.47
B48: 584801647 | C48: close trade | D48: 45496.618 | E48: Profit of position #1393281260 | F48: SDIA.UK | G48: =IFERROR(INDEX([1]Positions!$A:$A,MATCH(F48,[1]Positions!$C:$C,0)),"Other") -> MISC | H48: =ISNUMBER(D48) -> TRUE | I48: =TEXT(D48,"YYYY-MM-DD") -> 2024-07-23 | J48: 0
B49: 584801648 | C49: Stock sale | D49: 45496.618 | E49: CLOSE BUY 0.5612 @ 5.8100 | F49: SDIA.UK | G49: =IFERROR(INDEX([1]Positions!$A:$A,MATCH(F49,[1]Positions!$C:$C,0)),"Other") -> MISC | H49: =ISNUMBER(D49) -> TRUE | I49: =TEXT(D49,"YYYY-MM-DD") -> 2024-07-23 | J49: 3.26
B50: 584801643 | C50: close trade | D50: 45496.618 | E50: Profit of position #1393281432 | F50: FLOA.UK | G50: =IFERROR(INDEX([1]Positions!$A:$A,MATCH(F50,[1]Positions!$C:$C,0)),"Other") -> MISC | H50: =ISNUMBER(D50) -> TRUE | I50: =TEXT(D50,"YYYY-MM-DD") -> 2024-07-23 | J50: -0.01
B51: 584801644 | C51: Stock sale | D51: 45496.618 | E51: CLOSE BUY 0.632 @ 5.9670 | F51: FLOA.UK | G51: =IFERROR(INDEX([1]Positions!$A:$A,MATCH(F51,[1]Positions!$C:$C,0)),"Other") -> MISC | H51: =ISNUMBER(D51) -> TRUE | I51: =TEXT(D51,"YYYY-MM-DD") -> 2024-07-23 | J51: 3.78
B52: 585465634 | C52: Stock purchase | D52: 45497.654 | E52: OPEN BUY 0.074 @ 67.130 | F52: VHYD.UK | G52: =IFERROR(INDEX([1]Positions!$A:$A,MATCH(F52,[1]Positions!$C:$C,0)),"Other") -> MISC | H52: =ISNUMBER(D52) -> TRUE | I52: =TEXT(D52,"YYYY-MM-DD") -> 2024-07-24 | J52: -4.97
B53: 585465630 | C53: close trade | D53: 45497.654 | E53: Profit of position #1393281260 | F53: SDIA.UK | G53: =IFERROR(INDEX([1]Positions!$A:$A,MATCH(F53,[1]Positions!$C:$C,0)),"Other") -> MISC | H53: =ISNUMBER(D53) -> TRUE | I53: =TEXT(D53,"YYYY-MM-DD") -> 2024-07-24 | J53: -0.01
B54: 585465631 | C54: Stock sale | D54: 45497.654 | E54: CLOSE BUY 0.555/1.555 @ 5.8010 | F54: SDIA.UK | G54: =IFERROR(INDEX([1]Positions!$A:$A,MATCH(F54,[1]Positions!$C:$C,0)),"Other") -> MISC | H54: =ISNUMBER(D54) -> TRUE | I54: =TEXT(D54,"YYYY-MM-DD") -> 2024-07-24 | J54: 3.23
... B91: 747747258 | C91: Withholding Tax | D91: 45729.498 | E91: MSFT.US USD WHT 30% | F91: MSFT | G91: =IFERROR(INDEX([1]Positions!$A:$A,MATCH(F91,[1]Positions!$C:$C,0)),"Other") -> Technology | H91: =ISNUMBER(D91) -> TRUE | I91: =TEXT(D91,"YYYY-MM-DD") -> 2025-03-13 | J91: -0.01
B92: 735126956 | C92: deposit | D92: 45716.85 | E92: SafetyPay deposit, SafetyPay provider transaction id=0125059444032332, SafetyPay merchant reference id=249604, id=17602808 | G92: =IFERROR(INDEX([1]Positions!$A:$A,MATCH(F92,[1]Positions!$C:$C,0)),"Other") -> Other | H92: =ISNUMBER(D92) -> TRUE | I92: =TEXT(D92,"YYYY-MM-DD") -> 2025-02-28 | J92: 85
B93: 686269321 | C93: DIVIDENT | D93: 45653.524 | E93: VHYD.UK USD 0.4296/ SHR | F93: VHYD.UK | G93: =IFERROR(INDEX([1]Positions!$A:$A,MATCH(F93,[1]Positions!$C:$C,0)),"Other") -> MISC | H93: =ISNUMBER(D93) -> TRUE | I93: =TEXT(D93,"YYYY-MM-DD") -> 2024-12-27 | J93: 0.03
B94: 735131727 | C94: Stock purchase | D94: 45716.856 | E94: OPEN BUY 0.1958 @ 178.67 | F94: TSM | G94: =IFERROR(INDEX([1]Positions!$A:$A,MATCH(F94,[1]Positions!$C:$C,0)),"Other") -> Technology | H94: =ISNUMBER(D94) -> TRUE | I94: =TEXT(D94,"YYYY-MM-DD") -> 2025-02-28 | J94: -34.98
B95: 735132884 | C95: Stock purchase | D95: 45716.857 | E95: OPEN BUY 0.7278 @ 20.60 | F95: APA | G95: =IFERROR(INDEX([1]Positions!$A:$A,MATCH(F95,[1]Positions!$C:$C,0)),"Other") -> Energy & Utilities | H95: =ISNUMBER(D95) -> TRUE | I95: =TEXT(D95,"YYYY-MM-DD") -> 2025-02-28 | J95: -14.99
B96: 747758629 | C96: DIVIDENT | D96: 45729.498 | E96: MSFT.US USD 0.8300/ SHR | F96: MSFT | G96: =IFERROR(INDEX([1]Positions!$A:$A,MATCH(F96,[1]Positions!$C:$C,0)),"Other") -> Technology | H96: =ISNUMBER(D96) -> TRUE | I96: =TEXT(D96,"YYYY-MM-DD") -> 2025-03-13 | J96: 0.02
B97: 747758630 | C97: Withholding Tax | D97: 45729.498 | E97: MSFT.US USD WHT 30% | F97: MSFT | G97: =IFERROR(INDEX([1]Positions!$A:$A,MATCH(F97,[1]Positions!$C:$C,0)),"Other") -> Technology | H97: =ISNUMBER(D97) -> TRUE | I97: =TEXT(D97,"YYYY-MM-DD") -> 2025-03-13 | J97: -0.01
B98: 735132266 | C98: Stock purchase | D98: 45716.856 | E98: OPEN BUY 1 @ 44.49 | F98: VWO | G98: =IFERROR(INDEX([1]Positions!$A:$A,MATCH(F98,[1]Positions!$C:$C,0)),"Other") -> ETF | H98: =ISNUMBER(D98) -> TRUE | I98: =TEXT(D98,"YYYY-MM-DD") -> 2025-02-28 | J98: -44.49
B99: 747790405 | C99: DIVIDENT | D99: 45729.498 | E99: MSFT.US USD 0.8300/ SHR | F99: MSFT | G99: =IFERROR(INDEX([1]Positions!$A:$A,MATCH(F99,[1]Positions!$C:$C,0)),"Other") -> Technology | H99: =ISNUMBER(D99) -> TRUE | I99: =TEXT(D99,"YYYY-MM-DD") -> 2025-03-13 | J99: 0.03
B100: 747790406 | C100: Withholding Tax | D100: 45729.498 | E100: MSFT.US USD WHT 30% | F100: MSFT | G100: =IFERROR(INDEX([1]Positions!$A:$A,MATCH(F100,[1]Positions!$C:$C,0)),"Other") -> Technology | H100: =ISNUMBER(D100) -> TRUE | I100: =TEXT(D100,"YYYY-MM-DD") -> 2025-03-13 | J100: -0.01
B101: 747779319 | C101: DIVIDENT | D101: 45729.498 | E101: MSFT.US USD 0.8300/ SHR | F101: MSFT | G101: =IFERROR(INDEX([1]Positions!$A:$A,MATCH(F101,[1]Positions!$C:$C,0)),"Other") -> Technology | H101: =ISNUMBER(D101) -> TRUE | I101: =TEXT(D101,"YYYY-MM-DD") -> 2025-03-13 | J101: 0.02
B102: 747779320 | C102: Withholding Tax | D102: 45729.498 | E102: MSFT.US USD WHT 30% | F102: MSFT | G102: =IFERROR(INDEX([1]Positions!$A:$A,MATCH(F102,[1]Positions!$C:$C,0)),"Other") -> Technology | H102: =ISNUMBER(D102) -> TRUE | I102: =TEXT(D102,"YYYY-MM-DD") -> 2025-03-13 | J102: -0.01
B103: 747786766 | C103: DIVIDENT | D103: 45729.498 | E103: MSFT.US USD 0.8300/ SHR | F103: MSFT | G103: =IFERROR(INDEX([1]Positions!$A:$A,MATCH(F103,[1]Positions!$C:$C,0)),"Other") -> Technology | H103: =ISNUMBER(D103) -> TRUE | I103: =TEXT(D103,"YYYY-MM-DD") -> 2025-03-13 | J103: 0.04
B104: 747786767 | C104: Withholding Tax | D104: 45729.498 | E104: MSFT.US USD WHT 30% | F104: MSFT | G104: =IFERROR(INDEX([1]Positions!$A:$A,MATCH(F104,[1]Positions!$C:$C,0)),"Other") -> Technology | H104: =ISNUMBER(D104) -> TRUE | I104: =TEXT(D104,"YYYY-MM-DD") -> 2025-03-13 | J104: -0.01
... B138: 812396911 | C138: Sec Fee | D138: 45792.666 | E138: Sec Fee adj FSLR.US 20250514 | F138: FSLR | G138: =IFERROR(INDEX([1]Positions!$A:$A,MATCH(F138,[1]Positions!$C:$C,0)),"Other") -> Energy & Utilities | H138: =ISNUMBER(D138) -> TRUE | I138: =TEXT(D138,"YYYY-MM-DD") -> 2025-05-15 | J138: 0
B139: 749767690 | C139: deposit | D139: 45730.865 | E139: SafetyPay deposit, SafetyPay provider transaction id=0125073485538638, SafetyPay merchant reference id=254335, id=18121108 | G139: =IFERROR(INDEX([1]Positions!$A:$A,MATCH(F139,[1]Positions!$C:$C,0)),"Other") -> Other | H139: =ISNUMBER(D139) -> TRUE | I139: =TEXT(D139,"YYYY-MM-DD") -> 2025-03-14 | J139: 85
B140: 812643919 | C140: Stock purchase | D140: 45792.761 | E140: OPEN BUY 0.3559 @ 28.09 | F140: AGIO | G140: =IFERROR(INDEX([1]Positions!$A:$A,MATCH(F140,[1]Positions!$C:$C,0)),"Other") -> Healthcare | H140: =ISNUMBER(D140) -> TRUE | I140: =TEXT(D140,"YYYY-MM-DD") -> 2025-05-15 | J140: -10
B141: 812644050 | C141: Stock purchase | D141: 45792.761 | E141: OPEN BUY 0.2894 @ 34.55 | F141: DAR | G141: =IFERROR(INDEX([1]Positions!$A:$A,MATCH(F141,[1]Positions!$C:$C,0)),"Other") -> Consumer Defensive | H141: =ISNUMBER(D141) -> TRUE | I141: =TEXT(D141,"YYYY-MM-DD") -> 2025-05-15 | J141: -10
B142: 752507751 | C142: Stock purchase | D142: 45734.855 | E142: OPEN BUY 0.0861 @ 127.72 | F142: FSLR | G142: =IFERROR(INDEX([1]Positions!$A:$A,MATCH(F142,[1]Positions!$C:$C,0)),"Other") -> Energy & Utilities | H142: =ISNUMBER(D142) -> TRUE | I142: =TEXT(D142,"YYYY-MM-DD") -> 2025-03-18 | J142: -11
B143: 752508164 | C143: Stock purchase | D143: 45734.856 | E143: OPEN BUY 0.1244 @ 160.64 | F143: GOOGL | G143: =IFERROR(INDEX([1]Positions!$A:$A,MATCH(F143,[1]Positions!$C:$C,0)),"Other") -> Technology | H143: =ISNUMBER(D143) -> TRUE | I143: =TEXT(D143,"YYYY-MM-DD") -> 2025-03-18 | J143: -19.98
B144: 754634504 | C144: close trade | D144: 45737.113 | E144: Profit of position #1717095547 | F144: USDMXN | G144: =IFERROR(INDEX([1]Positions!$A:$A,MATCH(F144,[1]Positions!$C:$C,0)),"Other") -> Other | H144: =ISNUMBER(D144) -> TRUE | I144: =TEXT(D144,"YYYY-MM-DD") -> 2025-03-21 | J144: 2.98
B145: 754634505 | C145: swap | D145: 45737.113 | E145: Swap of position #1717095547 | F145: USDMXN | G145: =IFERROR(INDEX([1]Positions!$A:$A,MATCH(F145,[1]Positions!$C:$C,0)),"Other") -> Other | H145: =ISNUMBER(D145) -> TRUE | I145: =TEXT(D145,"YYYY-MM-DD") -> 2025-03-21 | J145: -0.8
B146: 757003245 | C146: DIVIDENT | D146: 45741.427 | E146: VWO.US USD 0.0468/ SHR | F146: VWO | G146: =IFERROR(INDEX([1]Positions!$A:$A,MATCH(F146,[1]Positions!$C:$C,0)),"Other") -> ETF | H146: =ISNUMBER(D146) -> TRUE | I146: =TEXT(D146,"YYYY-MM-DD") -> 2025-03-25 | J146: 0.05
B147: 757003246 | C147: Withholding Tax | D147: 45741.427 | E147: VWO.US USD WHT 30% | F147: VWO | G147: =IFERROR(INDEX([1]Positions!$A:$A,MATCH(F147,[1]Positions!$C:$C,0)),"Other") -> ETF | H147: =ISNUMBER(D147) -> TRUE | I147: =TEXT(D147,"YYYY-MM-DD") -> 2025-03-25 | J147: -0.02
B148: 757003247 | C148: DIVIDENT | D148: 45741.427 | E148: VWO.US USD 0.0468/ SHR | F148: VWO | G148: =IFERROR(INDEX([1]Positions!$A:$A,MATCH(F148,[1]Positions!$C:$C,0)),"Other") -> ETF | H148: =ISNUMBER(D148) -> TRUE | I148: =TEXT(D148,"YYYY-MM-DD") -> 2025-03-25 | J148: 0.05
B149: 757003248 | C149: Withholding Tax | D149: 45741.427 | E149: VWO.US USD WHT 30% | F149: VWO | G149: =IFERROR(INDEX([1]Positions!$A:$A,MATCH(F149,[1]Positions!$C:$C,0)),"Other") -> ETF | H149: =ISNUMBER(D149) -> TRUE | I149: =TEXT(D149,"YYYY-MM-DD") -> 2025-03-25 | J149: -0.02
B150: 742196232 | C150: DIVIDENT | D150: 45723.492 | E150: YUM.US USD 0.7100/ SHR | F150: YUM | G150: =IFERROR(INDEX([1]Positions!$A:$A,MATCH(F150,[1]Positions!$C:$C,0)),"Other") -> Consumer Cyclical | H150: =ISNUMBER(D150) -> TRUE | I150: =TEXT(D150,"YYYY-MM-DD") -> 2025-03-07 | J150: 0
B151: 757634903 | C151: close trade | D151: 45741.872 | E151: Profit of position #1554741910 | F151: ING | G151: =IFERROR(INDEX([1]Positions!$A:$A,MATCH(F151,[1]Positions!$C:$C,0)),"Other") -> Financial Services | H151: =ISNUMBER(D151) -> TRUE | I151: =TEXT(D151,"YYYY-MM-DD") -> 2025-03-25 | J151: 3.05
... B155: 758733045 | C155: Stock sale | D155: 45742.776 | E155: CLOSE BUY 0.01 @ 547.14 | F155: MA | G155: =IFERROR(INDEX([1]Positions!$A:$A,MATCH(F155,[1]Positions!$C:$C,0)),"Other") -> Financial Services | H155: =ISNUMBER(D155) -> TRUE | I155: =TEXT(D155,"YYYY-MM-DD") -> 2025-03-26 | J155: 4.55
B156: 758903820 | C156: deposit | D156: 45743.015 | E156: SafetyPay deposit, SafetyPay provider transaction id=0125085947634834, SafetyPay merchant reference id=257598, id=18402027 | G156: =IFERROR(INDEX([1]Positions!$A:$A,MATCH(F156,[1]Positions!$C:$C,0)),"Other") -> Other | H156: =ISNUMBER(D156) -> TRUE | I156: =TEXT(D156,"YYYY-MM-DD") -> 2025-03-27 | J156: 85
B157: 759582657 | C157: Sec Fee | D157: 45743.62 | E157: Sec Fee adj MA.US 20250326 | F157: MA | G157: =IFERROR(INDEX([1]Positions!$A:$A,MATCH(F157,[1]Positions!$C:$C,0)),"Other") -> Financial Services | H157: =ISNUMBER(D157) -> TRUE | I157: =TEXT(D157,"YYYY-MM-DD") -> 2025-03-27 | J157: 0
B158: 759868932 | C158: close trade | D158: 45743.766 | E158: Profit of position #1358151307 | F158: PEP | G158: =IFERROR(INDEX([1]Positions!$A:$A,MATCH(F158,[1]Positions!$C:$C,0)),"Other") -> Consumer Defensive | H158: =ISNUMBER(D158) -> TRUE | I158: =TEXT(D158,"YYYY-MM-DD") -> 2025-03-27 | J158: -0.21
B159: 759868933 | C159: Stock sale | D159: 45743.766 | E159: CLOSE BUY 0.0124 @ 149.33 | F159: PEP | G159: =IFERROR(INDEX([1]Positions!$A:$A,MATCH(F159,[1]Positions!$C:$C,0)),"Other") -> Consumer Defensive | H159: =ISNUMBER(D159) -> TRUE | I159: =TEXT(D159,"YYYY-MM-DD") -> 2025-03-27 | J159: 2.06
B160: 759869187 | C160: Stock purchase | D160: 45743.767 | E160: OPEN BUY 1 @ 21.13 | F160: ACI | G160: =IFERROR(INDEX([1]Positions!$A:$A,MATCH(F160,[1]Positions!$C:$C,0)),"Other") -> Consumer Defensive | H160: =ISNUMBER(D160) -> TRUE | I160: =TEXT(D160,"YYYY-MM-DD") -> 2025-03-27 | J160: -21.13
B161: 759869902 | C161: close trade | D161: 45743.768 | E161: Profit of position #1422773288 | F161: MO | G161: =IFERROR(INDEX([1]Positions!$A:$A,MATCH(F161,[1]Positions!$C:$C,0)),"Other") -> Consumer Defensive | H161: =ISNUMBER(D161) -> TRUE | I161: =TEXT(D161,"YYYY-MM-DD") -> 2025-03-27 | J161: 1.37
B162: 759869903 | C162: Stock sale | D162: 45743.768 | E162: CLOSE BUY 0.2 @ 58.08 | F162: MO | G162: =IFERROR(INDEX([1]Positions!$A:$A,MATCH(F162,[1]Positions!$C:$C,0)),"Other") -> Consumer Defensive | H162: =ISNUMBER(D162) -> TRUE | I162: =TEXT(D162,"YYYY-MM-DD") -> 2025-03-27 | J162: 10.25
B163: 759864523 | C163: Stock purchase | D163: 45743.761 | E163: OPEN BUY 1 @ 46.11 | F163: VWO | G163: =IFERROR(INDEX([1]Positions!$A:$A,MATCH(F163,[1]Positions!$C:$C,0)),"Other") -> ETF | H163: =ISNUMBER(D163) -> TRUE | I163: =TEXT(D163,"YYYY-MM-DD") -> 2025-03-27 | J163: -46.11
B164: 759865080 | C164: Stock purchase | D164: 45743.762 | E164: OPEN BUY 0.3274 @ 30.54 | F164: AGIO | G164: =IFERROR(INDEX([1]Positions!$A:$A,MATCH(F164,[1]Positions!$C:$C,0)),"Other") -> Healthcare | H164: =ISNUMBER(D164) -> TRUE | I164: =TEXT(D164,"YYYY-MM-DD") -> 2025-03-27 | J164: -10
B165: 759868722 | C165: close trade | D165: 45743.766 | E165: Profit of position #1450043624 | F165: KMB | G165: =IFERROR(INDEX([1]Positions!$A:$A,MATCH(F165,[1]Positions!$C:$C,0)),"Other") -> Consumer Defensive | H165: =ISNUMBER(D165) -> TRUE | I165: =TEXT(D165,"YYYY-MM-DD") -> 2025-03-27 | J165: -0.11
B166: 759868723 | C166: Stock sale | D166: 45743.766 | E166: CLOSE BUY 0.0138 @ 139.86 | F166: KMB | G166: =IFERROR(INDEX([1]Positions!$A:$A,MATCH(F166,[1]Positions!$C:$C,0)),"Other") -> Consumer Defensive | H166: =ISNUMBER(D166) -> TRUE | I166: =TEXT(D166,"YYYY-MM-DD") -> 2025-03-27 | J166: 2.04
B167: 759875711 | C167: Stock purchase | D167: 45743.774 | E167: OPEN BUY 1 @ 72.87 | F167: BND | G167: =IFERROR(INDEX([1]Positions!$A:$A,MATCH(F167,[1]Positions!$C:$C,0)),"Other") -> ETF | H167: =ISNUMBER(D167) -> TRUE | I167: =TEXT(D167,"YYYY-MM-DD") -> 2025-03-27 | J167: -72.87
B168: 760803346 | C168: Sec Fee | D168: 45744.635 | E168: Sec Fee adj PEP.US 20250327 | F168: PEP | G168: =IFERROR(INDEX([1]Positions!$A:$A,MATCH(F168,[1]Positions!$C:$C,0)),"Other") -> Consumer Defensive | H168: =ISNUMBER(D168) -> TRUE | I168: =TEXT(D168,"YYYY-MM-DD") -> 2025-03-28 | J168: 0
... B171: 761014425 | C171: Stock purchase | D171: 45744.713 | E171: OPEN BUY 0.0907 @ 165.35 | F171: TSM | G171: =IFERROR(INDEX([1]Positions!$A:$A,MATCH(F171,[1]Positions!$C:$C,0)),"Other") -> Technology | H171: =ISNUMBER(D171) -> TRUE | I171: =TEXT(D171,"YYYY-MM-DD") -> 2025-03-28 | J171: -15
B172: 745059993 | C172: Subaccount Transfer | D172: 45727.386 | E172: Transfer from 50872299 to 50704832 | G172: =IFERROR(INDEX([1]Positions!$A:$A,MATCH(F172,[1]Positions!$C:$C,0)),"Other") -> Other | H172: =ISNUMBER(D172) -> TRUE | I172: =TEXT(D172,"YYYY-MM-DD") -> 2025-03-11 | J172: 52.08
B173: 762151528 | C173: DIVIDENT | D173: 45747.483 | E173: PEP.US USD 1.3550/ SHR | F173: PEP | G173: =IFERROR(INDEX([1]Positions!$A:$A,MATCH(F173,[1]Positions!$C:$C,0)),"Other") -> Consumer Defensive | H173: =ISNUMBER(D173) -> TRUE | I173: =TEXT(D173,"YYYY-MM-DD") -> 2025-03-31 | J173: 0.12
B174: 762151529 | C174: Withholding Tax | D174: 45747.483 | E174: PEP.US USD WHT 30% | F174: PEP | G174: =IFERROR(INDEX([1]Positions!$A:$A,MATCH(F174,[1]Positions!$C:$C,0)),"Other") -> Consumer Defensive | H174: =ISNUMBER(D174) -> TRUE | I174: =TEXT(D174,"YYYY-MM-DD") -> 2025-03-31 | J174: -0.04
B175: 762179517 | C175: DIVIDENT | D175: 45747.483 | E175: PEP.US USD 1.3550/ SHR | F175: PEP | G175: =IFERROR(INDEX([1]Positions!$A:$A,MATCH(F175,[1]Positions!$C:$C,0)),"Other") -> Consumer Defensive | H175: =ISNUMBER(D175) -> TRUE | I175: =TEXT(D175,"YYYY-MM-DD") -> 2025-03-31 | J175: 0.16
B176: 762179518 | C176: Withholding Tax | D176: 45747.483 | E176: PEP.US USD WHT 30% | F176: PEP | G176: =IFERROR(INDEX([1]Positions!$A:$A,MATCH(F176,[1]Positions!$C:$C,0)),"Other") -> Consumer Defensive | H176: =ISNUMBER(D176) -> TRUE | I176: =TEXT(D176,"YYYY-MM-DD") -> 2025-03-31 | J176: -0.05
B177: 762177357 | C177: DIVIDENT | D177: 45747.483 | E177: PEP.US USD 1.3550/ SHR | F177: PEP | G177: =IFERROR(INDEX([1]Positions!$A:$A,MATCH(F177,[1]Positions!$C:$C,0)),"Other") -> Consumer Defensive | H177: =ISNUMBER(D177) -> TRUE | I177: =TEXT(D177,"YYYY-MM-DD") -> 2025-03-31 | J177: 0.08
B178: 762177358 | C178: Withholding Tax | D178: 45747.483 | E178: PEP.US USD WHT 30% | F178: PEP | G178: =IFERROR(INDEX([1]Positions!$A:$A,MATCH(F178,[1]Positions!$C:$C,0)),"Other") -> Consumer Defensive | H178: =ISNUMBER(D178) -> TRUE | I178: =TEXT(D178,"YYYY-MM-DD") -> 2025-03-31 | J178: -0.02
B179: 762177784 | C179: DIVIDENT | D179: 45747.483 | E179: PEP.US USD 1.3550/ SHR | F179: PEP | G179: =IFERROR(INDEX([1]Positions!$A:$A,MATCH(F179,[1]Positions!$C:$C,0)),"Other") -> Consumer Defensive | H179: =ISNUMBER(D179) -> TRUE | I179: =TEXT(D179,"YYYY-MM-DD") -> 2025-03-31 | J179: 0.1
B180: 762177785 | C180: Withholding Tax | D180: 45747.483 | E180: PEP.US USD WHT 30% | F180: PEP | G180: =IFERROR(INDEX([1]Positions!$A:$A,MATCH(F180,[1]Positions!$C:$C,0)),"Other") -> Consumer Defensive | H180: =ISNUMBER(D180) -> TRUE | I180: =TEXT(D180,"YYYY-MM-DD") -> 2025-03-31 | J180: -0.03
B181: 762184116 | C181: DIVIDENT | D181: 45747.483 | E181: PEP.US USD 1.3550/ SHR | F181: PEP | G181: =IFERROR(INDEX([1]Positions!$A:$A,MATCH(F181,[1]Positions!$C:$C,0)),"Other") -> Consumer Defensive | H181: =ISNUMBER(D181) -> TRUE | I181: =TEXT(D181,"YYYY-MM-DD") -> 2025-03-31 | J181: 0.14
B182: 762184117 | C182: Withholding Tax | D182: 45747.483 | E182: PEP.US USD WHT 30% | F182: PEP | G182: =IFERROR(INDEX([1]Positions!$A:$A,MATCH(F182,[1]Positions!$C:$C,0)),"Other") -> Consumer Defensive | H182: =ISNUMBER(D182) -> TRUE | I182: =TEXT(D182,"YYYY-MM-DD") -> 2025-03-31 | J182: -0.04
B183: 762201892 | C183: DIVIDENT | D183: 45747.483 | E183: PEP.US USD 1.3550/ SHR | F183: PEP | G183: =IFERROR(INDEX([1]Positions!$A:$A,MATCH(F183,[1]Positions!$C:$C,0)),"Other") -> Consumer Defensive | H183: =ISNUMBER(D183) -> TRUE | I183: =TEXT(D183,"YYYY-MM-DD") -> 2025-03-31 | J183: 0.08
B184: 762201893 | C184: Withholding Tax | D184: 45747.483 | E184: PEP.US USD WHT 30% | F184: PEP | G184: =IFERROR(INDEX([1]Positions!$A:$A,MATCH(F184,[1]Positions!$C:$C,0)),"Other") -> Consumer Defensive | H184: =ISNUMBER(D184) -> TRUE | I184: =TEXT(D184,"YYYY-MM-DD") -> 2025-03-31 | J184: -0.02
... B204: 769436100 | C204: Stock purchase | D204: 45751.723 | E204: OPEN BUY 0.643 @ 15.55 | F204: APA | G204: =IFERROR(INDEX([1]Positions!$A:$A,MATCH(F204,[1]Positions!$C:$C,0)),"Other") -> Energy & Utilities | H204: =ISNUMBER(D204) -> TRUE | I204: =TEXT(D204,"YYYY-MM-DD") -> 2025-04-04 | J204: -10
B205: 769465419 | C205: deposit | D205: 45751.733 | E205: SafetyPay deposit, SafetyPay provider transaction id=0125094541214514, SafetyPay merchant reference id=261181, id=18734513 | G205: =IFERROR(INDEX([1]Positions!$A:$A,MATCH(F205,[1]Positions!$C:$C,0)),"Other") -> Other | H205: =ISNUMBER(D205) -> TRUE | I205: =TEXT(D205,"YYYY-MM-DD") -> 2025-04-04 | J205: 200
B206: 769492457 | C206: Stock purchase | D206: 45751.745 | E206: OPEN BUY 0.0616 @ 324.48 | F206: V | G206: =IFERROR(INDEX([1]Positions!$A:$A,MATCH(F206,[1]Positions!$C:$C,0)),"Other") -> Financial Services | H206: =ISNUMBER(D206) -> TRUE | I206: =TEXT(D206,"YYYY-MM-DD") -> 2025-04-04 | J206: -19.99
B207: 769493151 | C207: Stock purchase | D207: 45751.745 | E207: OPEN BUY 1 @ 74.13 | F207: BND | G207: =IFERROR(INDEX([1]Positions!$A:$A,MATCH(F207,[1]Positions!$C:$C,0)),"Other") -> ETF | H207: =ISNUMBER(D207) -> TRUE | I207: =TEXT(D207,"YYYY-MM-DD") -> 2025-04-04 | J207: -74.13
B208: 769480903 | C208: Stock purchase | D208: 45751.739 | E208: OPEN BUY 0.2701 @ 148.09 | F208: TSM | G208: =IFERROR(INDEX([1]Positions!$A:$A,MATCH(F208,[1]Positions!$C:$C,0)),"Other") -> Technology | H208: =ISNUMBER(D208) -> TRUE | I208: =TEXT(D208,"YYYY-MM-DD") -> 2025-04-04 | J208: -40
B209: 769487423 | C209: Stock purchase | D209: 45751.742 | E209: OPEN BUY 1/1.4245 @ 17.54 | F209: ING | G209: =IFERROR(INDEX([1]Positions!$A:$A,MATCH(F209,[1]Positions!$C:$C,0)),"Other") -> Financial Services | H209: =ISNUMBER(D209) -> TRUE | I209: =TEXT(D209,"YYYY-MM-DD") -> 2025-04-04 | J209: -17.54
B210: 769487406 | C210: Stock purchase | D210: 45751.742 | E210: OPEN BUY 0.4245/1.4245 @ 17.54 | F210: ING | G210: =IFERROR(INDEX([1]Positions!$A:$A,MATCH(F210,[1]Positions!$C:$C,0)),"Other") -> Financial Services | H210: =ISNUMBER(D210) -> TRUE | I210: =TEXT(D210,"YYYY-MM-DD") -> 2025-04-04 | J210: -7.45
B211: 705921636 | C211: Sec Fee | D211: 45681.692 | E211: Sec Fee adj QCOM.US 20250123 | F211: QCOM | G211: =IFERROR(INDEX([1]Positions!$A:$A,MATCH(F211,[1]Positions!$C:$C,0)),"Other") -> Technology | H211: =ISNUMBER(D211) -> TRUE | I211: =TEXT(D211,"YYYY-MM-DD") -> 2025-01-24 | J211: 0
B212: 772553486 | C212: Stock purchase | D212: 45754.579 | E212: OPEN BUY 1 @ 37.2580 | F212: VBTC.DE | G212: =IFERROR(INDEX([1]Positions!$A:$A,MATCH(F212,[1]Positions!$C:$C,0)),"Other") -> ETF | H212: =ISNUMBER(D212) -> TRUE | I212: =TEXT(D212,"YYYY-MM-DD") -> 2025-04-07 | J212: -41.06
...

Sheet CLOSED POSITION HISTORY MT
H5: Name and surname | K5: Account | N5: Currency | W5: 45786.091
H6: SAMUEL EDUARDO RODRIGUEZ WALTON | K6: 50704832 | N6: USD
H7: Balance | K7: Equity | N7: Margin | Q7: Free margin | T7: Margin level
H8: 93.01 | K8: 1531.79 | N8: 0 | Q8: 93.01 | T8: 0
B9: CLOSED POSITION HISTORY MT
B10: 01/01/2006 - 09/05/2025
B12: Position | D12: Symbol | F12: Type | G12: Volume | H12: Open time | I12: Open price | J12: Close time | K12: Close price | L12: Commission | M12: Swap | N12: Gross P/L | O12: Comment
B13: 561654650 | D13: SHELL.NL | F13: Closed | G13: 0.4139 | H13: 45446.375 | I13: 33.545 | J13: 45453.664 | K13: 32.605 | L13: 0 | M13: 0 | N13: -0.73 | O13: ""
B14: 561850164 | D14: US.30 | F14: Closed | G14: 0.01 | H14: 45453.906 | I14: 38900 | J14: 45453.91 | K14: 38869 | L14: 0 | M14: 0 | N14: -1.55 | O14: ""
B15: 565713106 | D15: PEP | F15: Closed | G15: 0.123 | H15: 45460.646 | I15: 1.65 | J15: 45460.738 | K15: 165.24 | L15: 0 | M15: 0 | N15: 0 | O15: ""
B16: 565713108 | D16: PEP | F16: Closed | G16: 0 | H16: 45460.646 | I16: 1.65 | J16: 45460 | K16: 165.24 | L16: 0 | M16: 0 | N16: 0 | O16: ""
B17: 565825453 | D17: SMFG | F17: Closed | G17: 1 | H17: 45446.904 | I17: 13.37 | J17: 45460.885 | K17: 12.62 | L17: 0 | M17: 0 | N17: -0.75 | O17: ""
B18: 568018581 | D18: NVDA | F18: Closed | G18: 0.12 | H18: 45452.644 | I18: 118.42 | J18: 45464.646 | K18: 126.75 | L18: 0 | M18: 0 | N18: 1 | O18: Transfer In
B19: 568018754 | D19: QCOM | F19: Closed | G19: 0.0975 | H19: 45446.894 | I19: 205.08 | J19: 45464.646 | K19: 211.24 | L19: 0 | M19: 0 | N19: 0.6 | O19: ""
B20: 568018921 | D20: NVDA | F20: Closed | G20: 0.051 | H20: 45452.644 | I20: 118.42 | J20: 45464.646 | K20: 126.76 | L20: 0 | M20: 0 | N20: 0.42 | O20: Transfer In
B21: 568057989 | D21: AVGO | F21: Closed | G21: 0.0115 | H21: 45460.686 | I21: 1797.13 | J21: 45464.66 | K21: 1686.26 | L21: 0 | M21: 0 | N21: -1.28 | O21: ""
B22: 568079573 | D22: GILD | F22: Closed | G22: 0.2806 | H22: 45464.662 | I22: 71.61 | J22: 45464.667 | K22: 70.96 | L22: 0 | M22: 0 | N22: -0.18 | O22: ""
B23: 575788975 | D23: TSM | F23: Closed | G23: 0.1322 | H23: 45446.646 | I23: 155.59 | J23: 45478.652 | K23: 183.6 | L23: 0 | M23: 0 | N23: 3.7 | O23: ""
B24: 576566234 | D24: WMT | F24: Closed | G24: 0.1488 | H24: 45449.868 | I24: 67.2 | J24: 45481.658 | K24: 69.65 | L24: 0 | M24: 0 | N24: 0.36 | O24: ""
... B131: 803547672 | D131: MSFT | F131: Closed | G131: 0.0372 | H131: 45523.666 | I131: 419.46 | J131: 45784.777 | K131: 434.71 | L131: 0 | M131: 0 | N131: 0.56 | O131: ""
B132: Total | L132: 0 | M132: -2.32 | N132: 9.58

Sheet BALANCE OPERATION HISTORY MT
D5: Name and surname | E5: Account | F5: Currency | H5: 45786.091
D6: SAMUEL EDUARDO RODRIGUEZ WALTON | E6: 50704832 | F6: USD
D7: Balance | E7: Equity | F7: Margin | G7: Free margin | H7: Margin level
D8: 93.01 | E8: 1531.79 | F8: 0 | G8: 93.01 | H8: 0
B9: BALANCE OPERATION HISTORY MT
B10: 01/01/2006 - 09/05/2025
B11: ID | C11: Type | D11: Time | E11: Comment | F11: Amount
B12: 576516261 | C12: Deposit | D12: 45443 | E12: ECOMMPAY card deposit, ECOMMPAY provider transaction id=1717160381025_178431418,ECOMMPAY merchant re | F12: 100
B13: 577153112 | C13: Withdraw | D13: 45446 | E13: OPEN BUY 0.4139 @ 33.545 | F13: -15.15
B14: 577470756 | C14: Withdraw | D14: 45446 | E14: OPEN BUY 0.1322 @ 155.59 | F14: -20.57
B15: 577778020 | C15: Withdraw | D15: 45446 | E15: OPEN BUY 0.0975 @ 205.08 | F15: -20
B16: 577784122 | C16: Withdraw | D16: 45446 | E16: OPEN BUY 1 @ 13.37 | F16: -13.37
B17: 579538038 | C17: Withdraw | D17: 45448 | E17: OPEN BUY 0.0171 @ 1184.19 | F17: -20.25
B18: 580399287 | C18: Withdraw | D18: 45449 | E18: OPEN BUY 0.1488 @ 67.20 | F18: -10
B19: 581654651 | C19: Deposit | D19: 45453 | E19: CLOSE BUY 0.4139 @ 32.605 | F19: 15.15
B20: 581852140 | C20: Withdraw | D20: 45453 | E20: OPEN BUY 0.0234 @ 427.17 | F20: -10
B21: 584919536 | C21: Deposit | D21: 45458 | E21: ECOMMPAY card deposit, ECOMMPAY provider transaction id=1718411934936_-192576474,ECOMMPAY merchant r | F21: 50
B22: 585607855 | C22: Withdraw | D22: 45460 | E22: OPEN BUY 0.123 @ 1.65 | F22: -0.2
B23: 585611180 | C23: Withdraw | D23: 45460 | E23: OPEN BUY 1 @ 22.89 | F23: -22.89
... B467: 823547673 | C467: Deposit | D467: 45784 | E467: CLOSE BUY 0.0372/0.0606 @ 434.71 | F467: 15.61
B468: Total | F468: 68.27
